Workbook

Sheet Start Here
B2: Crowsons Distribution - Wholesale Supplier Sourcing List
B3: 358 UK & EU suppliers for Amazon UK wholesale across 12 niches. Researched Oct 2026.
B5: What's new in this version
B6: Sorted Country > Category > Priority | C6: The Suppliers tab is sorted by Country A-Z, then Category A-Z within each country, then Amazon UK Demand (A first), then Priority. Country is the first column and each country is shaded in alternating bands, so you can work through one country - and one niche - at a time. Pan-European / online platforms are at the bottom.
B7: NEW: Top Picks tab + Amazon UK Demand | C7: Start with the Top Picks tab: the suppliers whose brands are household names that already sell well on Amazon UK (A-rated). Every supplier now has an 'Amazon UK Demand' rating - A Strong (green), B Moderate (yellow), C Low / little UK demand (grey) - and within each country and niche the A-rated suppliers are listed first. Filter the Suppliers tab on A or B to skip small local brands with little UK demand.
B8: Low Priority tab + 2nd scam check | C8: Priority 1-2 suppliers (weak Amazon fit, marketplaces, retailers, capped after the scam check) have moved off the Suppliers tab to a separate 'Low Priority' tab, so the main list is priority 3-5 only. A second check scanned 2025-26 insolvency notices and EU Safety Gate alerts: Tunturi was removed (parent Accell Group declared bankrupt Aug 2026) and INGLOT and La Rive were flagged CAUTION.
B9: Anti-scam check | C9: Every wholesaler, trader and marketplace was checked against company registers (Companies House, KvK, KRS, ARES, SIREN...), insolvency notices, regulator fines and independent reviews. 25 suppliers failed (liquidation, dissolved, administration, fines, or no evidence the business exists) and were moved to the 'Removed - Failed Check' tab. Every remaining supplier has a 'Scam Check' result: PASS (green), CHECK (yellow - limited public info, verify before paying) or CAUTION (orange - specific risk noted). The Contact First tab now only lists PASS suppliers.
B10: Quality check | C10: Every supplier was re-checked: missing phone numbers, emails, addresses and registry IDs were filled in for ~30 suppliers; 3 suppliers with no verifiable contact or registration were removed; websites we could not confirm are now a click-to-search link; and a new 'Contact First' tab lists the best EU suppliers with a direct phone/email, cheapest countries first.
B11: Round 5: cheapest-country sourcing | C11: Round 5 targets the EU countries where stock is cheapest to buy - mainly Poland, Czech Republic, Bulgaria, Romania, the Baltics, Portugal and Greece - and their home-grown manufacturers. Most Round 5 suppliers are verified through a government export agency (CzechTrade, Poland's trade.gov.pl, Bulgarian/Lithuanian registries) or a major trade fair, which is the best protection against fake 'wholesalers'. Round 5 rows are shaded green in the Company column.
B12: Country Price Level column + Best-Value Countries tab | C12: Each supplier now shows whether its country is Low-cost, Mid or Higher for buying stock. The new Best-Value Countries tab lists, for every niche, the cheapest EU countries to source from, why, and how many suppliers you already have there.
B13: Round 4: quality-filtered EU brands | C13: Round 4 added EU-only suppliers that passed a strict quality bar: identifiable company + proof of establishment (trade-fair exhibitor, official registry, years trading or recognised brand) + a usable contact route. Weak / directory-only leads were left out.
B14: Country Index tab | C14: Lists every country with supplier counts - click 'Go to' to jump straight to that country's first row.
B15: Also operates in | C15: New column showing other countries a supplier covers (the Country column now holds one main country so the grouping works).
B16: Keeping your tracker notes | C16: If you already filled in the tracker in the previous file, copy the yellow columns across by matching the Company name - or send me the old file and I'll merge it.
B18: How to use this workbook
B19: 1. Suppliers | C19: The master list, grouped by Country A-Z, then Category A-Z, then Priority (5 = best fit for Amazon). Use the filter arrows to filter by Category, Country, Priority or Added.
B20: 0. Top Picks | C20: START HERE: suppliers of brands with proven Amazon UK demand, grouped by niche, with direct contact details and a link to the full row.
B21: 1a. Low Priority | C21: Priority 1-2 suppliers kept for reference only - weaker Amazon fit or higher risk. Use only once the main list is worked through.
B22: 1b. Country Index | C22: Jump to any country's block of suppliers with one click.
B23: 1d. Contact First | C23: Your shortlist: every priority 4-5 EU supplier with a direct phone/email, cheapest countries first. Start your outreach here.
B24: 1c. Best-Value Countries | C24: For each niche: the cheapest EU countries to buy from, why, and how many low-cost-country suppliers you already have. Plus anti-scam checks.
B25: 2. Yellow columns | C25: Your outreach tracker. Status, Method and Account Approved have drop-down lists. 'Suggested Follow-up' fills in automatically (5 working days after Date Contacted) and turns red when overdue.
B26: 3. LinkedIn Outreach | C26: One-click LinkedIn searches for each company page and its sales / account-manager staff, plus a tracker.
B27: 4. Niche Guide | C27: Read before contacting suppliers in a new niche - it lists the compliance documents to ask for.
B28: 5. Profit Calculator | C28: Check every product before ordering. Blue cells are inputs; black cells are formulas.
B29: 6. Templates | C29: Copy-paste first-contact email, follow-up, LinkedIn notes and invoice / ungating request.
B30: 7. Dashboard | C30: Live counts by niche, region and outreach status.
B31: 8. Find More Suppliers / Due Diligence | C31: Directories & trade shows to keep growing the list, and a checklist to vet suppliers before paying.
B33: Priority score (1-5)
B34: 5 | C34: Established, branded stock, sells to online / Amazon sellers or provides invoices suitable for ungating. Contact first.
B35: 4 | C35: Established and branded, but may have higher MOQs, selective accounts or a narrower range.
B36: 3 | C36: Credible, worth contacting - confirm terms, online-selling policy and invoice details.
B37: 2 | C37: Lower fit (territory-limited, pro-only brands, limited info) or larger-scale target for later.
B38: 1 | C38: Low confidence, known red flag, or not suitable for Amazon - kept so you know to avoid / verify.
B40: Data confidence
B41: Official / company website | C41: Details came from the supplier's own site or an official register (Companies House, KRS, MHRA, LEI).
B42: Directory / press / trade show | C42: From trade press, exhibitor lists or business directories - confirm on the company website before relying on them.
B43: Marketplace / unverified | C43: Self-published profile only. Verify registration (Companies House / KvK / KRS / VIES VAT) before engaging.
B44: Blank cells | C44: Not publicly available. MOQs are usually only shared once a trade account is approved - ask in your first email.
B46: Key Amazon UK considerations
B47: Brand / category gating | C47: Many brands in fragrance, beauty, toys, baby and health need approval. Amazon wants invoices from a real wholesaler/distributor (not a retailer) dated within 180 days, showing supplier name, address, phone, website, your business details and 10+ units.
B48: EU suppliers after Brexit | C48: Buying from the EU means import VAT, possible duty and customs paperwork. Ask for DDP (delivered duty paid) quotes or use a freight forwarder, and get an EORI number. Use the Profit Calculator's freight & duty columns.
B49: UK product compliance | C49: Cosmetics need a UK Responsible Person + SCPN notification; toys need UKCA/CE marking + EN71; electricals need UK plugs + UKCA/CE. EU-only labelled stock may not be compliant for the UK.
B50: Online-selling policies | C50: Some suppliers forbid Amazon resale (see 'Sells to Online/Amazon Sellers?' column). Ask before applying.
B51: Hazmat | C51: Perfume, aerosols, lithium batteries (power tools) and gas canisters are dangerous goods on Amazon - ask suppliers for Safety Data Sheets.
B53: About LinkedIn outreach
C54: Messages must be sent from your own LinkedIn account. Automation tools break LinkedIn's terms and risk a ban, so this workbook gives you one-click searches + templates to make manual outreach fast. Tip: send ~15-25 connection requests per day, personalise the first line, and follow up after 4-5 working days.

Sheet Top Picks
A1: Top Picks - suppliers of brands that already sell well on Amazon UK
A2: 55 suppliers whose brands are household names with established, well-selling Amazon UK listings - so you can join existing listings instead of building demand. Grouped by Category, best priority first. Demand is our estimate: check each ASIN on Keepa / SellerAmp (sales rank, number of sellers, Amazon on the listing) before ordering, and watch for brand-gated listings.
A4: Category | B4: Priority | C4: Company | D4: Country | E4: Supplier Type | F4: Key Brands / Products | G4: Amazon Fit Notes | H4: Phone | I4: Email | J4: Website | K4: Scam Check | L4: Go to row
A5: B2B Marketplace | B5: 5 | C5: Qogita | D5: UK | E5: B2B wholesale marketplace | F5: 10k+ brands, 500k+ products from 500+ vetted suppliers - health, beauty, fragrance, household | G5: Provides commercial invoices that can support ungating - built for Amazon sellers | I5: via website | J5: https://www.qogita.com | K5: PASS - well-known company: VC-backed European B2B wholesale platform. | L5: Go to row
A6: Baby Products | B6: 5 | C6: Babybase Ltd | D6: UK | E6: Wholesaler / UK distributor | F6: Tommee Tippee, MAM, Shnuggle, Munchkin, Matchstick Monkey, My Buggy Buddy | G6: Multi-brand, low MOQ - strong fit; ask about marketplace policy | H6: +44 1886 887758 | I6: sales@babybase.co.uk | J6: https://www.babybase.co.uk | K6: PASS (checked) - Companies House 01475315 active since 1980. | L6: Go to row
A7: Baby Products | B7: 4 | C7: Béaba Group (incl. Childhome) | D7: France | E7: Brand owner / distributor | F7: Béaba Babycook, feeding, hygiene, sleep; Childhome; distributes iCandy (FR/Benelux) | G7: Babycook is a strong Amazon seller; also on Qogita | J7: https://www.beaba.com | K7: PASS - established brand / group | L7: Go to row
A8: Baby Products | B8: 4 | C8: MAPA GmbH (NUK) | D8: Germany | E8: Brand owner / manufacturer | F8: NUK bottles & dummies, Fresh Fruit feeders; also Billy Boy, household gloves | G8: NUK is a top Amazon baby brand | J8: https://www.mapa.de | K8: PASS - company register entry | L8: Go to row
A9: Baby Products | B9: 3 | C9: MAM Babyartikel GmbH | D9: Germany | E9: Brand distributor (MAM Baby AG subsidiary) | F9: MAM dummies, bottles, teethers, feeding | G9: Official brand source = best possible invoices | H9: +49 4263 9317 0 | J9: https://www.mambaby.com | K9: PASS - established brand / group | L9: Go to row
A10: Baby Products | B10: 3 | C10: Artsana S.p.A. (Chicco, Boppy) | D10: Italy | E10: Brand owner / manufacturer | F10: Chicco baby feeding, toys, nursery; Boppy; Control (health) | G10: Buy UK stock via RKW | H10: +39 031 382790 (verify) | J10: https://www.artsana.com | K10: PASS - established brand / group | L10: Go to row
A11: Beauty | B11: 4 | C11: cosnova GmbH (essence, CATRICE) | D11: Germany | E11: Brand owner (direct + local distributors) | F11: essence, CATRICE, Physicians Formula (EU) | G11: essence & CATRICE are top Amazon beauty sellers - may route you to UK distributor | H11: +49 6196 76156-0 | I11: service@cosnova.eu | J11: https://www.cosnova.com | K11: PASS - well-known company: Owner of essence & CATRICE - one of Europe's largest make-up brands. | L11: Go to row
A12: Beauty | B12: 4 | C12: Weleda AG (German branch) | D12: Germany | E12: Brand owner / manufacturer | F12: Weleda natural skincare, baby care (Calendula), Skin Food | G12: Skin Food is a strong Amazon seller | I12: dialog@weleda.de | J12: https://www.weleda.de | K12: PASS - established brand / group | L12: Go to row
A13: Beauty | B13: 3 | C13: QudoBeauty | D13: Romania | E13: K-beauty B2B wholesaler | F13: COSRX, Beauty of Joseon + other Korean skincare (CPNP-registered) | G13: K-beauty (COSRX, Beauty of Joseon) is a top Amazon UK beauty seller - check brand gating | H13: +40 742 372 490 | I13: emy@qudobeauty.com | J13: https://qudobeauty.com | K13: CAUTION - Launched 2025; legal entity not confirmed - get CUI/VAT number before ordering. | L13: Go to row
A14: DIY & Tools | B14: 5 | C14: Toolbank Ltd | D14: UK | E14: Trade-only wholesale distributor | F14: DeWalt, Milwaukee, HiKoki, Metabo, Black+Decker, Olympia + hand tools, fixings, consumables | G14: Ask about online/marketplace reseller policy - branded power tools need care on price (MAP) | H14: +44 344 463 6001 | J14: https://www.toolbank.com | K14: PASS - company register entry | L14: Go to row
A15: DIY & Tools | B15: 4 | C15: Fiskars Group (Fiskars Finland Oy Ab) | D15: Finland | E15: Brand owner (listed) | F15: Fiskars garden tools, axes, scissors; also Gerber, Iittala (home) | G15: Fiskars is a top Amazon garden brand | J15: https://www.fiskarsgroup.com | K15: PASS - listed company | L15: Go to row
A16: DIY & Tools | B16: 4 | C16: Einhell Germany AG | D16: Germany | E16: Brand owner (listed) | F16: Einhell Power X-Change cordless tools, garden tools, workshop | G16: Huge Amazon brand; lithium batteries = hazmat docs | I16: via website contact form | J16: https://www.einhell.com/einhell-worldwide/ | K16: PASS - listed company | L16: Go to row
A17: DIY & Tools | B17: 4 | C17: fischerwerke GmbH & Co. KG | D17: Germany | E17: Brand owner / manufacturer | F17: fischer wall plugs, anchors & fixings; fischertechnik | G17: Fixings kits sell well | H17: +49 7443 120 | J17: https://www.fischer.de | K17: PASS - well-known company: fischer - world-leading German fixings manufacturer (120+ countries). | L17: Go to row
A18: DIY & Tools | B18: 4 | C18: GARDENA Deutschland GmbH (Husqvarna Group) | D18: Germany | E18: Brand owner | F18: GARDENA hoses, watering, garden tools, robotic mowers | G18: Strong Amazon garden brand | H18: +49 731 490-0 | I18: service@gardena.com | J18: https://www.gardena.com | K18: PASS - established brand / group | L18: Go to row
A19: DIY & Tools | B19: 4 | C19: KNIPEX-Werk C. Gustav Putsch KG | D19: Germany | E19: Brand owner / manufacturer | F19: KNIPEX pliers, Cobra, wire strippers | G19: KNIPEX Cobra pliers are top sellers; brand may be gated | H19: +49 202 4794-0 | I19: info@knipex.de | J19: https://www.knipex.com | K19: PASS - major trade-fair exhibitor | L19: Go to row
A20: DIY & Tools | B20: 4 | C20: Wera Werkzeuge GmbH | D20: Germany | E20: Brand owner / manufacturer | F20: Wera screwdrivers, bits, ratchets, Kraftform | G20: Wera sells very well on Amazon UK | H20: +49 202 4045-322 | I20: info@wera.de | J20: https://www.wera.de | K20: PASS - established brand / group | L20: Go to row
A21: DIY & Tools | B21: 4 | C21: Wiha Werkzeuge GmbH | D21: Germany | E21: Brand owner / manufacturer | F21: Wiha screwdrivers, VDE insulated tools, bits | H21: +49 7722 959-0 | I21: info.de@wiha.com | J21: https://www.wiha.com | K21: PASS - well-known company: Major German hand-tool manufacturer. | L21: Go to row
A22: DIY & Tools | B22: 4 | C22: Draper Tools | D22: UK | E22: Brand owner / distributor (stockist programme) | F22: Draper, Draper Expert, Draper Tools + 1000s of tool & garage lines | G22: Brand-direct invoices; check stockist terms on online pricing | H22: +44 23 8049 4333 (orders) | I22: orders@drapertools.com | J22: https://www.drapertools.com | K22: PASS - established brand / group | L22: Go to row
A23: DIY & Tools | B23: 3 | C23: Campbell Miller Tools | D23: UK | E23: Bosch distributor | F23: Bosch (UK's largest Bosch distributor) + trade tools | J23: https://bosch-pt.com/uk_bssdealer/uk/en/start/bss_acct/dealers_list/campbell_miller.htm | K23: PASS (checked) - Campbell Miller (Tools) Ltd SC034278, active since 1959. | L23: Go to row
A24: Fragrance | B24: 5 | C24: Knights Fragrances | D24: UK | E24: Wholesaler / Distributor | F24: Prestige & mass-market branded fragrances | G24: Supplies online retailers - good fit | J24: https://www.knights-fragrances.co.uk | K24: CAUTION - Directory info only (since 1984, 11-50 staff) - confirm Companies House number. | L24: Go to row
A25: Fragrance | B25: 4 | C25: BJUTIP a.s. | D25: Czech Republic | E25: Distributor | F25: Armaf, Afnan, Lattafa, Paris Corner, French Avenue, Khadlaj, Maison Asrar + others | G25: Has an e-commerce seller programme - Arabian brands popular & often easier to list on Amazon | H25: +420 724 076 367 | I25: sales@bjutip.com (wholesale); info@bjutip.com | J25: https://www.bjutip.com | K25: CAUTION - Registered (IČO 10865373) but young (2021) and sells heavily-counterfeited Arabian brands - ask for brand authorisation letters. | L25: Go to row
A26: Fragrance | B26: 4 | C26: Shaneel Group (Shaneel Enterprises Ltd) | D26: UK | E26: Wholesaler / Distributor / Brand owner | F26: Branded fragrance supply; group incl. Mayfair Perfumes, Designer Parfums, Worth Paris, DDF Skincare | G26: Owns some brands - ask about brand authorisation for those | J26: https://www.shaneel.com/shaneel-enterprises | K26: PASS (checked) - Companies House 02171783 active since 1987 (perfume & cosmetics wholesale). | L26: Go to row
A27: Fragrance | B27: 3 | C27: Emporium Handels & Vertriebs GmbH (B&S Group) | D27: Germany | E27: Wholesaler | F27: 8,000+ perfume & cosmetics products | K27: PASS - established brand / group | L27: Go to row
A28: Fragrance | B28: 3 | C28: MisterM Plus Sp. z o.o. Sp.k. | D28: Poland | E28: Wholesaler / Exporter | F28: Coty, P&G, Reckitt Benckiser - perfumes, cosmetics, hygiene | G28: FMCG brands (P&G/Coty) - strong Amazon sellers | K28: PASS (checked) - KRS-registered; no insolvency or complaints found. | L28: Go to row
A29: General Wholesale / FMCG | B29: 4 | C29: West Coast Supply Group | D29: Netherlands | E29: A-brand FMCG distributor | F29: A-brands: personal care, beauty, home care, food, drinks, medical, electronics | G29: A-brand FMCG - strong Amazon sellers | I29: sales@westcoastsupplygroup.com | J29: https://www.westcoastsupplygroup.com | K29: PASS (checked) - 40+ years; ~200 staff; active in 75 countries. | L29: Go to row
A30: General Wholesale / FMCG | B30: 4 | C30: Booker Wholesale (incl. Makro UK) | D30: UK | E30: Cash & carry / delivered wholesale | F30: Grocery, household, health & beauty, confectionery, pet | G30: Fine for invoices; margins tight - use promo deals | J30: https://www.booker.co.uk | K30: PASS - established brand / group | L30: Go to row
A31: General Wholesale / FMCG | B31: 3 | C31: Costco UK (Business Membership) | D31: UK | E31: Warehouse club | F31: Grocery, household, health & beauty, toys, electronics | G31: Business membership allows resale; receipts show Costco details | H31: +44 1923 830477 (Central Membership) | J31: https://www.costco.co.uk | K31: PASS - well-known company: Costco - global warehouse club. | L31: Go to row
A32: Health & Personal Care | B32: 5 | C32: Harrisons Direct (Albert Harrison & Co Ltd) | D32: UK | E32: Wholesaler | F32: Health & beauty, GSL medicines (pain relief, hay fever), toiletries, household | G32: Branded FMCG lines - good for wholesale arbitrage; note Amazon rules on medicines | H32: +44 1254 306840 | J32: https://www.harrisonsdirect.co.uk | K32: PASS (checked) - MHRA wholesale authorisation UK WDA(H) 2530; trading since 1919. | L32: Go to row
A33: Health & Personal Care | B33: 4 | C33: Beurer GmbH (Beurer UK Ltd) | D33: Germany | E33: Brand owner with UK subsidiary | F33: Beurer BP monitors, thermometers, massagers, scales, TENS, beauty devices | G33: Huge Amazon health-device brand; check UK account terms | H33: +49 731 3989-0 | J33: https://www.beurer.com/uk/facts/ | K33: PASS - established brand / group | L33: Go to row
A34: Health & Personal Care | B34: 4 | C34: TePe Munhygienprodukter AB | D34: Sweden | E34: Brand owner / manufacturer | F34: TePe interdental brushes, toothbrushes, oral care | G34: Interdental brushes are strong repeat sellers | H34: +46 40 670 11 00 | I34: info@tepe.com | J34: https://tepe.com/global/contact | K34: PASS - established brand / group | L34: Go to row
A35: Health & Personal Care | B35: 3 | C35: MEDISANA AG | D35: Germany | E35: Brand owner | F35: Medisana BP monitors, inhalers, massagers, scales, heated blankets | G35: Also on Qogita (low MOV) | H35: +49 2131 3668-0 | I35: info@medisana.de | J35: https://www.medisana.de | K35: PASS - established brand / group | L35: Go to row
A36: Home & Kitchen | B36: 5 | C36: RKW Ltd (Sutton Venture Group) | D36: UK | E36: Brand owner / distributor | F36: Tower, Swan, Goblin, Redring, Wade, Royal Victoria, Burco; exclusive Smeg SDA distributor | G36: Tower & Swan are big Amazon UK sellers - brand-direct invoices | H36: +44 333 220 6070 | I36: sales@rkwltd.com | J36: https://www.rkwltd.com | K36: PASS - major trade-fair exhibitor | L36: Go to row
A37: Home & Kitchen | B37: 4 | C37: Bialetti Industrie S.p.A. | D37: Italy | E37: Brand owner (listed) | F37: Bialetti moka pots & coffee, Rondine & Aeternum cookware, Girmi appliances | G37: Moka pots are evergreen Amazon sellers | H37: +39 030 7720011 | J37: https://www.bialetti.it | K37: PASS - listed company | L37: Go to row
A38: Home & Kitchen | B38: 4 | C38: EPE International Ltd | D38: UK | E38: Distributor (housewares & SDA) | F38: Kenwood, De'Longhi, Kärcher, Philips, Braun (food prep/laundry), Salter, Tefal/Jamie Oliver cookware | J38: https://www.epeinternational.com | K38: PASS (checked) - Companies House 04897647; 20+ years; BHETA & Bira member. | L38: Go to row
A39: Home & Kitchen | B39: 3 | C39: Leifheit AG | D39: Germany | E39: Brand owner (listed company) | F39: Leifheit, Soehnle - cleaning, laundry, kitchen, scales | G39: Brand-direct; very popular on Amazon (may have MAP rules) | J39: https://www.leifheit.com | K39: PASS - listed company | L39: Go to row
A40: Home & Kitchen | B40: 3 | C40: Wolfsohn | D40: Germany | E40: Branded electronics & household wholesaler | F40: 6,000+ SKUs in stock: Braun, Philips, Samsung, Xiaomi, QCY, PoundMax | J40: https://www.ifa-berlin.com/exhibitors/wolfsohn | K40: PASS (checked) - IFA Berlin exhibitor; 6,000+ branded SKUs in stock. | L40: Go to row
A41: Home & Kitchen | B41: 3 | C41: Keter Luxembourg SARL (Curver) | D41: Luxembourg | E41: Brand owner / manufacturer | F41: Curver storage boxes & baskets, Keter | G41: Storage boxes sell well but are bulky - check FBA fees | H41: +352 52 47 17 773 | J41: https://www.curver.com | K41: PASS - major trade-fair exhibitor | L41: Go to row
A42: Home & Kitchen | B42: 3 | C42: Brabantia Export BV | D42: Netherlands | E42: Brand owner - export desk | F42: Brabantia bins, laundry, kitchen & bathroom | G42: Brand-direct; check online pricing policy | H42: +31 40 20 72 318 | I42: via website | J42: https://www.brabantia.com/uk/offices | K42: PASS - well-known company: Brabantia's official export desk. | L42: Go to row
A43: Home & Kitchen | B43: 3 | C43: Bluestem Group | D43: UK | E43: Exclusive distribution partner | F43: De'Longhi, Kenwood, Braun, Ariete | H43: +44 1473 271272 | I43: sales@bluestemgroup.co.uk | K43: PASS (checked) - Owner of Igenix, Statesman & Ewbank brands (Ipswich, since 1988). | L43: Go to row
A44: Pet Supplies | B44: 5 | C44: TRIXIE Heimtierbedarf (incl. Trixie UK Pet Product Ltd) | D44: Germany | E44: Brand owner selling direct to retailers | F44: TRIXIE - 6,000+ pet accessories, toys, beds, treats; exports to 80+ countries | G44: Brand-direct invoices; very popular Amazon brand | H44: +44 20 7154 2940 (UK - verify) | I44: sales@trixie.de | J44: https://www.trixie.de | K44: PASS - major trade-fair exhibitor | L44: Go to row
A45: Pet Supplies | B45: 4 | C45: Beaphar B.V. | D45: Netherlands | E45: Brand owner / distributor | F45: Beaphar pet health & care (flea, worming, grooming, treats) - 600+ products | G45: Pet health products may need extra compliance (vet medicines are restricted) | H45: +31 572 348834 (verify) | J45: https://www.beaphar.com | K45: PASS - company register entry | L45: Go to row
A46: Pet Supplies | B46: 4 | C46: Pedigree Wholesale | D46: UK | E46: Pet wholesaler | F46: KONG, Chuckit!, James Wellbeloved, Forthglade, Nutriment, Carnilove - 10,000+ products | G46: Pet supplies is a top Amazon UK category | H46: +44 115 982 3900 | I46: sales@petproducts.co.uk | J46: https://www.petproducts.co.uk | K46: PASS (checked) - 50+ years; Companies House 01047681 active. | L46: Go to row
A47: Sports & Outdoors | B47: 4 | C47: Oase Outdoors ApS (Outwell, Easy Camp, Robens) | D47: Denmark | E47: Brand owner | F47: Outwell, Easy Camp, Robens tents, camping furniture & equipment | G47: Popular camping brands on Amazon UK | J47: https://www.oase-outdoors.dk | K47: PASS - established brand / group | L47: Go to row
A48: Stationery & Office | B48: 4 | C48: edding International GmbH | D48: Germany | E48: Brand owner (listed) | F48: edding markers, paint pens, highlighters, nail varnish | G48: Strong Amazon brand | H48: +49 4102 808-0 | I48: info@edding.de | J48: https://www.edding.com/en-uk/ | K48: PASS - listed company | L48: Go to row
A49: Stationery & Office | B49: 4 | C49: STAEDTLER Mars GmbH & Co. KG | D49: Germany | E49: Brand owner / manufacturer | F49: STAEDTLER pencils, markers, erasers, art & drawing supplies | G49: Evergreen Amazon stationery brand | H49: +49 911 9365-0 | I49: info@staedtler.com | J49: https://www.staedtler.com/intl/en/company | K49: PASS - well-known company: World-famous German stationery manufacturer. | L49: Go to row
A50: Stationery & Office | B50: 4 | C50: F.I.L.A. S.p.A. (Giotto, Lyra, DOMS, Canson, Daler-Rowney) | D50: Italy | E50: Brand owner / manufacturer (listed) | F50: Giotto, Tratto, Lyra, Canson, Daler-Rowney, Maimeri, DOMS | G50: Art supplies are strong on Amazon | J50: https://www.fila.it | K50: PASS - listed company | L50: Go to row
A51: Stationery & Office | B51: 3 | C51: ALSO Nederland | D51: Netherlands | E51: Distributor (resellers & webshops only) | F51: Original printing supplies & office brands (largest in Europe for original print supplies) | G51: Supplies webshops | J51: https://www.also.com/ec/cms5/en_2420/2420/index.jsp | K51: PASS - well-known company: Part of ALSO Holding (SIX Swiss Exchange listed IT distributor). | L51: Go to row
A52: Toys & Games | B52: 5 | C52: Franckh-Kosmos Verlags-GmbH & Co. KG (KOSMOS) | D52: Germany | E52: Publisher / manufacturer | F52: CATAN, EXIT games, Ubongo, KOSMOS science kits | G52: CATAN & EXIT are top sellers - brand-direct via UK arm | H52: +49 711 21910 | I52: info@kosmos.de | J52: https://www.kosmos.de | K52: PASS - major trade-fair exhibitor | L52: Go to row
A53: Toys & Games | B53: 5 | C53: A.B. Gee of Ripley Ltd | D53: UK | E53: Official distributor / wholesaler | F53: Hasbro, Mattel, Funko, MGA, Zapf + more | G53: Supplies online stores - excellent invoices for toy ungating | H53: +44 1773 570444 | I53: sales@abgee.co.uk | J53: https://www.abgee.co.uk | K53: PASS - company register entry | L53: Go to row
A54: Toys & Games | B54: 5 | C54: NDA Toys | D54: UK | E54: Online wholesale distributor | F54: Hasbro, Mattel, Funko, Playmobil | G54: Actively serves online sellers - very good fit | J54: https://www.nda-toys.com | K54: PASS (checked) - London Toy Fair exhibitor; official Hasbro / Mattel / Funko distributor. | L54: Go to row
A55: Toys & Games | B55: 5 | C55: Wind Designs Ltd | D55: UK | E55: National distributor | F55: Hasbro, Mattel, Basic Fun!, Bandai, John Adams, PlayMonster, Moose; exclusive for Trends UK | G55: Supplies online retailers - good fit | H55: +44 1353 724140 | J55: https://www.wind-designs.com | K55: PASS (checked) - Companies House 04371524 active; national distributor for Hasbro & Mattel. | L55: Go to row
A56: Toys & Games | B56: 4 | C56: Carrera Revell Europe GmbH | D56: Germany | E56: Manufacturer & distributor | F56: Carrera slot cars & RC, Revell model kits & 3D puzzles; distributes Rollplay | G56: Model kits & RC sell strongly (RC batteries = hazmat) | J56: https://www.carrera-revell-toys.com | K56: PASS - well-known company: Owner of Carrera & Revell - major toy group. | L56: Go to row
A57: Toys & Games | B57: 4 | C57: Simba Dickie Group GmbH (Simba, Dickie, Smoby, Majorette, Noris, Schuco) | D57: Germany | E57: Brand owner / manufacturer | F57: Simba, Dickie Toys, Smoby, Majorette, BIG, Noris games, Eichhorn, Schuco, Jada | G57: Major toy group - brand-direct invoices | H57: +49 911 9765-01 | J57: https://www.simba-dickie-group.com | K57: PASS - well-known company: One of Europe's largest toy groups. | L57: Go to row
A58: Toys & Games | B58: 4 | C58: Clementoni S.p.A. | D58: Italy | E58: Brand owner / manufacturer | F58: Clementoni puzzles, science & educational toys, Sapientino | G58: Brand-direct; science kits & puzzles sell well | J58: https://www.clementoni.com | K58: PASS - established brand / group | L58: Go to row
A59: Toys & Games | B59: 3 | C59: BRIO AB (Ravensburger group) | D59: Sweden | E59: Brand owner | F59: BRIO wooden railway, infant & toddler toys | G59: Brand-direct invoices; may be brand-gated | J59: https://www.brio.eu | K59: PASS - established brand / group | L59: Go to row

Sheet Suppliers
A1: Country | B1: ID | C1: Priority (1-5) | D1: Category | E1: Company | F1: Amazon UK Demand | G1: Website | H1: City / Region | I1: Also operates in | J1: Region | K1: Country Price Level | L1: Address | M1: Phone | N1: Email | O1: Supplier Type | P1: Key Brands / Products | Q1: Segment | R1: MOQ / Min. Order | S1: Account Requirements | T1: Ships to UK? | U1: Sells to Online/Amazon Sellers? | V1: Dropship? | W1: Registry ID | X1: Legitimacy Evidence | Y1: Amazon Fit Notes | Z1: Notes / Red Flags | AA1: Data Confidence | AB1: Scam Check (Oct 2026) | AC1: Source | AD1: LinkedIn Company Search | AE1: Added | AF1: Status | AG1: Date Contacted | AH1: Method | AI1: Contact Name | AJ1: Response / Notes | AK1: Suggested Follow-up | AL1: Account Approved? | AM1: Next Step
A2: Austria | B2: 1 | C2: 3 | D2: Stationery & Office | E2: KORES GmbH | F2: B - Moderate | G2: https://www.kores.com | H2: Vienna | J2: EU / Europe | K2: Higher | L2: Leopold-Ungar-Platz 2/Top 334, 1190 Wien | O2: Brand owner / manufacturer | P2: Kores glue sticks, correction tape, office & school supplies, printer supplies | Q2: Office & school supplies | R2: Account based | S2: Distributors & retailers | T2: Sold in 80+ countries - ask | U2: Unknown | V2: Unknown | X2: Advantage Austria company profile; production in CZ & MX | AA2: Government trade agency + company catalogue | AB2: PASS - government export agency / trade body listing | AC2: Source link | AD2: Search LinkedIn | AE2: Round 4 | AF2: Not contacted | AK2: =IF(AG2="","",WORKDAY(AG2,5))
A3: Austria | B3: 2 | C3: 3 | D3: Toys & Games | E3: Stadlbauer Marketing + Vertrieb GmbH | F3: B - Moderate | G3: https://www.stadlbauer.at | H3: Puch bei Hallein (Salzburg) | J3: EU / Europe | K3: Higher | L3: Rennbahn Allee 1, 5412 Puch bei Hallein | O3: Distributor & brand owner | P3: Exclusive Playmobil (Austria); Carrera, Pustefix, Schildkröt, Bburago, Disney & Nintendo licences | Q3: Branded toys | R3: Account based | S3: Retailers (DACH) | T3: DACH territory | U3: Unknown | V3: Unknown | X3: Part of Carrera Revell group (Quantum Capital) since 2019 | Y3: Useful for Amazon.de | AA3: Investor announcement + press | AB3: PASS - established brand / group | AC3: Source link | AD3: Search LinkedIn | AE3: Round 4 | AF3: Not contacted | AK3: =IF(AG3="","",WORKDAY(AG3,5))
A4: Austria | B4: 3 | C4: 3 | D4: Toys & Games | E4: Wiener Spielkartenfabrik Ferd. Piatnik & Söhne | F4: B - Moderate | G4: https://www.piatnik.com | H4: Vienna | J4: EU / Europe | K4: Higher | L4: Vienna | O4: Brand owner / manufacturer | P4: Piatnik playing cards, Activity, puzzles, party games | Q4: Games & puzzles | R4: On request | S4: Retailers & distributors | T4: Exports 80% of output to 72 countries - ask | U4: Unknown | V4: Unknown | X4: 200-year-old Austrian company; featured by Advantage Austria (gov trade agency) | AA4: Government trade agency article | AB4: PASS - government export agency / trade body listing | AC4: Source link | AD4: Search LinkedIn | AE4: Round 4 | AF4: Not contacted | AK4: =IF(AG4="","",WORKDAY(AG4,5))
A5: Belgium | B5: 4 | C5: 4 | D5: DIY & Tools | E5: Varo (Vic Van Rompuy NV) | F5: C - Low / little UK demand | G5: https://varo.com/contact | H5: Lier | J5: EU / Europe | K5: Higher | L5: Joseph Van Instraat 9, 2500 Lier | M5: +32 3 292 92 90 | N5: info@varo.com | O5: Brand owner / distributor | P5: Powerplus, Kreator, Premion tools & garden equipment | Q5: Power & garden tools | R5: On request | S5: Retailers & distributors | T5: Sold across Europe - ask | U5: Unknown | V5: Unknown | X5: Sold via major EU DIY chains & e-tailers (Bricomarché, Alza) | Y5: Budget-friendly tool brands suit Amazon | AA5: Company website (via search) | AB5: PASS - well-known company: Belgian tool group (Powerplus, Silverline Benelux) - established brand owner. | AC5: Source link | AD5: Search LinkedIn | AE5: Round 4 | AF5: Not contacted | AK5: =IF(AG5="","",WORKDAY(AG5,5))
A6: Belgium | B6: 5 | C6: 3 | D6: Fragrance | E6: Beautylux | F6: B - Moderate | G6: https://www.beautylux.be | H6: Brussels (Schaerbeek) | J6: EU / Europe | K6: Higher | L6: Rue François Bossaerts, Schaerbeek, Brussels (confirm) | M6: +32 2 732 .... (see website) | O6: Importer / Distributor | P6: Pure Altitude, Berdoues, Ariana Grande, Bentley + others; 2,500+ refs | Q6: Designer / celebrity fragrance | R6: On request | S6: Retail accounts | T6: Check | U6: Unknown | V6: Unknown | X6: Established 1980; 450+ points of sale in Benelux | Y6: Official importer for some brands - good invoices | AA6: Directory - confirm on website | AB6: CAUTION - Since 1980 per directories, but Belgian enterprise number not confirmed. | AC6: Source link | AD6: Search LinkedIn | AE6: Round 1 | AF6: Not contacted | AK6: =IF(AG6="","",WORKDAY(AG6,5))
A7: Belgium | B7: 6 | C7: 3 | D7: Home & Kitchen | E7: Galico NV | F7: C - Low / little UK demand | G7: https://galico.be | H7: Vichte (West Flanders) | J7: EU / Europe | K7: Higher | L7: Oudenaardestraat 49b, B-8570 Vichte | M7: +32 56 62 69 69 | N7: info@galico.be | O7: Brand owner / distributor | P7: Escalo (ladders), Practo Home (storage), Practo Garden, Casibel (household); distributes Grosfillex, Mottez, Garantia, Kendo tools | Q7: Household, storage, ladders, garden, hand tools | R7: On request | S7: Retailers (BE/FR/LU) | T7: Ask | U7: Unknown | V7: Unknown | W7: BE 0453.670.483 | X7: VAT BE 0453.670.483; B2B portal | Y7: Own brands = direct invoices | Z7: Also covers DIY (Kendo hand tools, Escalo ladders). | AA7: Company website (via search) | AB7: PASS - well-known company: Established Belgian housewares brand owner/distributor. | AC7: Source link | AD7: Search LinkedIn | AE7: Round 2 | AF7: Not contacted | AK7: =IF(AG7="","",WORKDAY(AG7,5))
A8: Belgium | B8: 7 | C8: 4 | D8: Pet Supplies | E8: Savic NV | F8: B - Moderate | G8: https://www.savic.be | H8: Heule (Kortrijk) | J8: EU / Europe | K8: Higher | L8: Ringlaan 10, 8501 Heule | M8: +32 65 35 33 45 | N8: info@savic.be (verify) | O8: Brand owner / manufacturer | P8: Savic small-animal cages, cat litter trays, dog & bird products | Q8: Pet habitats & accessories | R8: On request | S8: Distributors & retailers | T8: Sold in 73-80+ countries - ask | U8: Unknown | V8: Unknown | X8: Family business; Interzoo exhibitor; Head of Intl Sales Pascal Nichelson | AA8: Trade directories + trade fair | AB8: PASS - major trade-fair exhibitor | AC8: Source link | AD8: Search LinkedIn | AE8: Round 4 | AF8: Not contacted | AK8: =IF(AG8="","",WORKDAY(AG8,5))
A9: Belgium | B9: 8 | C9: 4 | D9: Pet Supplies | E9: Flamingo Pet Products NV | F9: C - Low / little UK demand | G9: https://www.flamingo.be/en/for-companies | H9: Olen | J9: EU / Europe | K9: Higher | L9: Lammerdries-Winkelstraat 25, 2250 Olen | M9: +32 14 25 84 80 | N9: info@flamingo.be | O9: Wholesaler / manufacturer | P9: Flamingo - 10,000+ pet products; private label available | Q9: Pet accessories & toys | R9: On request | S9: Companies - B2B section on website | T9: Ask | U9: Unknown | V9: Unknown | X9: Interzoo & Zoomark exhibitor; long-established | AA9: Trade show listings | AB9: PASS - major trade-fair exhibitor | AC9: Source link | AD9: Search LinkedIn | AE9: Round 2 | AF9: Not contacted | AK9: =IF(AG9="","",WORKDAY(AG9,5))
A10: Belgium | B10: 9 | C10: 3 | D10: Pet Supplies | E10: Laroy Group (Duvo+) | F10: C - Low / little UK demand | G10: Not confirmed - click to search | H10: Wondelgem (Ghent) | J10: EU / Europe | K10: Higher | L10: Industrieweg 98-100, 9032 Wondelgem | M10: +32 9 258 13 00 (verify) | O10: Manufacturer & distributor | P10: Duvo+, Witte Molen, CéDé - 10,000+ products | Q10: Pet food & accessories | R10: On request | S10: Pet shops & international trade partners | T10: Ask | U10: Unknown | V10: Unknown | X10: Major Belgian pet group (Laroy Duvo + CéDé + Witte Molen) | AA10: Trade press | AB10: PASS - established brand / group | AC10: Source link | AD10: Search LinkedIn | AE10: Round 3 | AF10: Not contacted | AK10: =IF(AG10="","",WORKDAY(AG10,5))
A11: Belgium | B11: 10 | C11: 3 | D11: Pet Supplies | E11: Moderna Products NV | F11: C - Low / little UK demand | G11: https://www.modernaproducts.com | H11: Izegem | J11: EU / Europe | K11: Higher | L11: Zuidkaai 35, 8870 Izegem | O11: Manufacturer & distributor | P11: Moderna litter boxes, bowls, carriers, storage (also private label) | Q11: Pet plastics | R11: On request | S11: Distributors & retailers | T11: Exports to 60-79 countries - ask | U11: Unknown | V11: Unknown | X11: 3rd-generation family business; production in BE & US; Interzoo exhibitor | AA11: Trade fair listing | AB11: PASS - major trade-fair exhibitor | AC11: Source link | AD11: Search LinkedIn | AE11: Round 4 | AF11: Not contacted | AK11: =IF(AG11="","",WORKDAY(AG11,5))
A12: Belgium | B12: 11 | C12: 3 | D12: Pet Supplies | E12: Vadigran NV | F12: C - Low / little UK demand | G12: https://www.vadigran.com | H12: Ghislenghien | J12: EU / Europe | K12: Higher | L12: Chemin Preuscamps 20B, 7822 Ghislenghien (BE0431.312.379) | M12: +32 68 26 96 40 | O12: Distributor / manufacturer | P12: ~6,000 pet products (food & accessories) in 40 countries | Q12: Pet food & accessories | R12: On request | S12: Retailers; currently recruiting distributors | T12: Ask | U12: Unknown | V12: Unknown | W12: BE0431.312.379 | X12: Interzoo exhibitor; Belgian registry | Z12: Actively recruiting distributors. | AA12: Trade directory + registry + trade fair | AB12: PASS - company register entry | AC12: Source link | AD12: Search LinkedIn | AE12: Round 4 | AF12: Not contacted | AK12: =IF(AG12="","",WORKDAY(AG12,5))
A13: Bulgaria | B13: 12 | C13: 4 | D13: Beauty | E13: Bulgarian Rose AD (Bulgarska Roza Karlovo) | F13: C - Low / little UK demand | G13: Not confirmed - click to search | H13: Karlovo | J13: EU / Europe | K13: Low-cost | L13: Industrial Zone 1, 4300 Karlovo | N13: Via official distributor Cosmetics Bulgaria (cosmeticsbulgaria.com) | O13: Manufacturer (listed) | P13: Bulgarian Rose rose-oil skincare, hair & body care | Q13: Rose cosmetics | R13: On request | S13: Export to 40+ countries; distributors | T13: Ask | U13: Unknown | V13: Unknown | W13: EIK 115009344 | X13: Listed on Bulgarian Stock Exchange; EIK 115009344; Stara Planina Hold group; founded 1948 | Y13: Rose skincare at very low unit cost - good margin on gift sets | AA13: Stock exchange profile + business registry | AB13: PASS - listed company | AC13: Source link | AD13: Search LinkedIn | AE13: Round 5 | AF13: Not contacted | AK13: =IF(AG13="","",WORKDAY(AG13,5))
A14: Bulgaria | B14: 13 | C14: 3 | D14: Beauty | E14: Lema Kazanlak (rose distillery) | F14: C - Low / little UK demand | G14: http://www.lemabg.com | H14: Kazanlak | J14: EU / Europe | K14: Low-cost | L14: Southern Industrial Zone, Kazanlak | O14: Producer / manufacturer | P14: Lema rose oil, rose water, rose cosmetics | Q14: Rose water & oils | R14: On request | S14: Direct inquiry | T14: Ask | U14: Unknown | V14: Unknown | X14: Listed by the Bulgarian Ministry of Tourism; own Rosa Damascena plantations | Y14: Rose water toners sell well; check cosmetics compliance (UK RP / CPNP) | Z14: Make sure UK cosmetics labelling and a Responsible Person are in place | AA14: Government tourism listing + distributor page | AB14: PASS - government export agency / trade body listing | AC14: Source link | AD14: Search LinkedIn | AE14: Round 5 | AF14: Not contacted | AK14: =IF(AG14="","",WORKDAY(AG14,5))
A15: Bulgaria | B15: 14 | C15: 3 | D15: Home & Kitchen | E15: Parmash AD | F15: C - Low / little UK demand | G15: Not confirmed - click to search | H15: Sliven | J15: EU / Europe | K15: Low-cost | L15: Debela Koria, Stopanski dvor 1, 8800 Sliven | M15: +359 44 667 308 | O15: Manufacturer | P15: Clothes dryers/airers, ironing boards, plate racks, household ladders | Q15: Laundry & household | R15: On request | S15: Retail chains in BG, DE, RO, IT, RS, MK | T15: Ask | U15: Unknown | V15: Unknown | X15: Ambiente 2025 exhibitor; joint-stock company (AD) | Y15: Airers & ironing boards are oversize - compare FBM vs FBA | AA15: Trade fair exhibitor listing | AB15: PASS - major trade-fair exhibitor | AC15: Source link | AD15: Search LinkedIn | AE15: Round 5 | AF15: Not contacted | AK15: =IF(AG15="","",WORKDAY(AG15,5))
A16: Croatia | B16: 15 | C16: 3 | D16: Health & Personal Care | E16: Saponia d.d. | F16: C - Low / little UK demand | G16: https://www.saponia.hr | H16: Osijek | J16: EU / Europe | K16: Low-cost | L16: M. Gupca 2, 31000 Osijek | M16: +385 31 513 513 | O16: Manufacturer (listed) | P16: Kalodont toothpaste, Arf, Faks, Ornel, liquid soaps, detergents | Q16: Personal & home care | R16: Pallet / account based | S16: Export to 15+ countries incl. DE, PL, HU, US | T16: Ask | U16: Unknown | V16: Unknown | X16: Listed on Zagreb Stock Exchange; ~EUR 133m revenue (2024); 725 staff | Y16: Toothpaste & soaps: low unit cost; detergents are heavy | AA16: Stock exchange filings + business registry | AB16: PASS - listed company | AC16: Source link | AD16: Search LinkedIn | AE16: Round 5 | AF16: Not contacted | AK16: =IF(AG16="","",WORKDAY(AG16,5))
A17: Czech Republic | B17: 16 | C17: 3 | D17: Beauty | E17: Dermacol a.s. | F17: B - Moderate | G17: https://www.dermacol.cz | H17: Prague | J17: EU / Europe | K17: Low-cost | L17: Vytvarna 1023/4, 161 00 Praha 6 (verify) | O17: Brand owner / manufacturer | P17: Dermacol Make-up Cover, foundations, skincare | Q17: Make-up & skincare | R17: Account based | S17: Regional distributors (60+ countries) | T17: Ask | U17: Unknown | V17: Unknown | X17: Brand since 1966 (Barrandov film studio); Cosmoprof exhibitor; sold via Notino | Y17: Make-up Cover is a known cult product; low Czech prices | Z17: Check the Czech register (ARES) before ordering | AA17: Business press + retailer data | AB17: PASS - major trade-fair exhibitor | AC17: Source link | AD17: Search LinkedIn | AE17: Round 5 | AF17: Not contacted | AK17: =IF(AG17="","",WORKDAY(AG17,5))
A18: Czech Republic | B18: 17 | C18: 3 | D18: Beauty | E18: MANUFAKTURA (Czech cosmetics) | F18: C - Low / little UK demand | G18: Not confirmed - click to search | H18: Prague | J18: EU / Europe | K18: Low-cost | L18: Melantrichova 17, 110 00 Praha 1 | O18: Manufacturer / brand owner | P18: Manufaktura beer, wine & herbal cosmetics, bath salts, gift sets | Q18: Natural cosmetics & gift sets | R18: On request | S18: Head of Sales: David Rožek | T18: Ask | U18: Unknown | V18: Unknown | W18: IČO 49687387 | X18: CzechTrade listing; IČO 49687387; 250+ staff; own shop chain since 1991 | Y18: Gift sets do well in Q4 | AA18: Government export directory | AB18: PASS - government export agency / trade body listing | AC18: Source link | AD18: Search LinkedIn | AE18: Round 5 | AF18: Not contacted | AK18: =IF(AG18="","",WORKDAY(AG18,5))
A19: Czech Republic | B19: 18 | C19: 4 | D19: DIY & Tools | E19: HECHT MOTORS s.r.o. | F19: C - Low / little UK demand | G19: https://en.hecht.cz | H19: Prague | J19: EU / Europe | K19: Low-cost | L19: Prague 4, Czech Republic (see website) | N19: export@hecht.cz | O19: Brand owner / importer-distributor | P19: HECHT lawn mowers, trimmers, chainsaws, pressure washers, workshop tools, e-scooters | Q19: Garden machinery & power tools | R19: On request (export price list) | S19: Export dealers; subsidiaries in SK, PL, HU; ~600 staff | T19: Ask - actively expanding export | U19: Unknown | V19: Unknown | X19: Brand owner since 1994; largest CZ/SK garden & power-products supplier; publishes English export catalogues | Y19: Battery garden tools & pressure washers sell well; petrol items are hazmat; need UK plugs | Z19: Products largely made in Asia under the Hecht brand - check CE/UKCA documents | AA19: Company export catalogues + company site | AB19: PASS - established brand / group | AC19: Source link | AD19: Search LinkedIn | AE19: Round 5 | AF19: Not contacted | AK19: =IF(AG19="","",WORKDAY(AG19,5))
A20: Czech Republic | B20: 19 | C20: 4 | D20: DIY & Tools | E20: NAREX s.r.o. | F20: C - Low / little UK demand | G20: https://www.narex.cz | H20: Česká Lípa | J20: EU / Europe | K20: Low-cost | L20: Chelčického 1932, 470 01 Česká Lípa | M20: +420 481 645 183 | N20: narex@narex.cz | O20: Manufacturer / brand owner | P20: Narex power tools (drills, grinders, saws); Narex Bystřice chisels & woodworking tools | Q20: Power tools & woodworking | R20: Dealer account | S20: Sales partners; commercial terms via sales team | T20: Ask - Narex chisels already sold in UK | U20: Unknown | V20: Unknown | X20: Official company contacts page; long-established Czech tool maker | Y20: Narex chisels have a strong UK woodworking following at lower prices than UK brands | Z20: Power tools need UK plugs / UKCA | AA20: Official company website | AB20: PASS - established brand / group | AC20: Source link | AD20: Search LinkedIn | AE20: Round 5 | AF20: Not contacted | AK20: =IF(AG20="","",WORKDAY(AG20,5))
A21: Czech Republic | B21: 20 | C21: 3 | D21: DIY & Tools | E21: PILANA Metal spol. s r.o. | F21: C - Low / little UK demand | G21: http://www.pilanametal.cz | H21: Hulín | J21: EU / Europe | K21: Low-cost | L21: Nádražní 804, 768 24 Hulín | O21: Manufacturer | P21: Pilana hacksaw blades, band saw blades, small saws & hand cutting tools | Q21: Saw blades & cutting tools | R21: On request | S21: Sales managers: Jiří Mizera, Marek Stratil; ships to 60+ countries | T21: Ask | U21: Unknown | V21: Unknown | W21: IČO 25328956 | X21: CzechTrade listing; IČO 25328956; cutting-tool tradition since 1934 | Y21: Hacksaw blade multipacks - cheap, light consumables | AA21: Government export directory | AB21: PASS - government export agency / trade body listing | AC21: Source link | AD21: Search LinkedIn | AE21: Round 5 | AF21: Not contacted | AK21: =IF(AG21="","",WORKDAY(AG21,5))
A22: Czech Republic | B22: 21 | C22: 4 | D22: Fragrance | E22: BJUTIP a.s. | F22: A - Strong (household name) | G22: https://www.bjutip.com | H22: Brno - Modřice | J22: EU / Europe | K22: Low-cost | L22: Tyršova 1182, 664 42 Brno - Modřice (visit: Vintrovna 395/25, Popůvky 664 41) | M22: +420 724 076 367 | N22: sales@bjutip.com (wholesale); info@bjutip.com | O22: Distributor | P22: Armaf, Afnan, Lattafa, Paris Corner, French Avenue, Khadlaj, Maison Asrar + others | Q22: Arabian / niche fragrance | R22: Min. order value €1,000 | S22: B2B registration on website | T22: Check - EU based (post-Brexit customs apply) | U22: Unknown | V22: Unknown | X22: Registered Regional Court Brno, B 8541; dedicated e-commerce seller programme | Y22: Has an e-commerce seller programme - Arabian brands popular & often easier to list on Amazon | Z22: Strong fit for Lattafa/Armaf etc. Register at bjutip.com/register. | AA22: Company website (via search) | AB22: CAUTION - Registered (IČO 10865373) but young (2021) and sells heavily-counterfeited Arabian brands - ask for brand authorisation letters. | AC22: Source link | AD22: Search LinkedIn | AE22: Round 1 | AF22: Not contacted | AK22: =IF(AG22="","",WORKDAY(AG22,5))
A23: Czech Republic | B23: 22 | C23: 4 | D23: Health & Personal Care | E23: NUTREND D.S., a.s. | F23: C - Low / little UK demand | G23: https://www.nutrend-supplements.com | H23: Olomouc | J23: EU / Europe | K23: Low-cost | L23: Chválkovice 604, 779 00 Olomouc | M23: +420 583 842 592 | N23: export@nutrend.eu | O23: Brand owner / manufacturer | P23: Nutrend sports nutrition, bars, supplements | Q23: Sports nutrition | R23: On request | S23: Distributors (export dept.) | T23: Exports to 60-74 countries - ask | U23: Unknown | V23: Unknown | X23: ~52% exported; record CZK 1.26bn revenue; Gulfood exhibitor | AA23: Catalogue + trade fair + business press | AB23: PASS - major trade-fair exhibitor | AC23: Source link | AD23: Search LinkedIn | AE23: Round 4 | AF23: Not contacted | AK23: =IF(AG23="","",WORKDAY(AG23,5))
A24: Czech Republic | B24: 23 | C24: 4 | D24: Health & Personal Care | E24: SPOKAR a.s. | F24: C - Low / little UK demand | G24: http://www.spokar.com | H24: Pelhřimov | J24: EU / Europe | K24: Low-cost | L24: Libkovodská 1428, 393 01 Pelhřimov | O24: Manufacturer | P24: Spokar toothbrushes, interdental brushes, household & paint brushes | Q24: Oral care & brushes | R24: On request | S24: Key Account Manager: Jan Canek; exports to DE, DK, NO, US, MX | T24: Ask | U24: Unknown | V24: Unknown | W24: IČO 25183427 | X24: CzechTrade listing; IČO 25183427; producing since 1882 | Y24: Toothbrush multipacks & cleaning brushes - low cost, repeat buys; private label possible | AA24: Government export directory | AB24: PASS - government export agency / trade body listing | AC24: Source link | AD24: Search LinkedIn | AE24: Round 5 | AF24: Not contacted | AK24: =IF(AG24="","",WORKDAY(AG24,5))
A25: Czech Republic | B25: 24 | C25: 3 | D25: Health & Personal Care | E25: ALPA, a.s. | F25: C - Low / little UK demand | G25: Not confirmed - click to search | H25: Velké Meziříčí | J25: EU / Europe | K25: Low-cost | L25: Hornoměstská 378/74, 594 01 Velké Meziříčí | M25: +420 566 521 401 (switchboard) | O25: Manufacturer / brand owner | P25: Alpa Francovka (herbal rub), Pedik foot care, Alpa kids cosmetics | Q25: Herbal body care & kids toiletries | R25: On request | S25: Business manager: Ing. Pavel Smažil | T25: Ask - sold on Notino UK | U25: Unknown | V25: Unknown | W25: IČO 27666468 / DIČ CZ27666468 | X25: CzechTrade listing; IČO 27666468; Francovka trademark since 1913 | Y25: Niche herbal products; little UK competition | Z25: Liquids with alcohol - check hazmat | AA25: Government export directory | AB25: PASS - government export agency / trade body listing | AC25: Source link | AD25: Search LinkedIn | AE25: Round 5 | AF25: Not contacted | AK25: =IF(AG25="","",WORKDAY(AG25,5))
A26: Czech Republic | B26: 25 | C26: 4 | D26: Home & Kitchen | E26: Tescoma s.r.o. (export centre Tescoma S.p.A., Italy) | F26: B - Moderate | G26: https://www.tescoma.cz | H26: Zlín (HQ); export centre Brescia, Italy | J26: EU / Europe | K26: Low-cost | L26: U Tescomy 241, 760 01 Zlín / Export: Via Traversa Caduti del Lavoro 3, 25046 Cazzago San Martino (IT) | M26: +39 030 775 1394 (export centre) | O26: Brand owner / manufacturer | P26: Tescoma kitchen utensils, cookware, baking, storage (thousands of SKUs) | Q26: Kitchenware | R26: On request | S26: Distributors & retailers | T26: Sold in 100-130 countries - ask | U26: Unknown | V26: Unknown | X26: Ambiente exhibitor; branches in IT, ES, PT, SK, PL, DE, CN | Y26: Kitchen gadgets largely ungated - brand-direct invoices | Z26: Use the Italian export centre for foreign accounts. | AA26: Trade fair profile + Wikipedia | AB26: PASS - major trade-fair exhibitor | AC26: Source link | AD26: Search LinkedIn | AE26: Round 4 | AF26: Not contacted | AK26: =IF(AG26="","",WORKDAY(AG26,5))
A27: Czech Republic | B27: 26 | C27: 3 | D27: Home & Kitchen | E27: Remoska s.r.o. | F27: B - Moderate | G27: Not confirmed - click to search | H27: Kopřivnice (Vlčovice) | J27: EU / Europe | K27: Low-cost | L27: Průmyslový park 303, Vlčovice, 742 21 Kopřivnice | O27: Manufacturer | P27: Remoska portable electric ovens, pans | Q27: Small cooking appliances | R27: On request | S27: ~40% exported, half of that to the UK | T27: Yes - already strong UK market | U27: Unknown | V27: Unknown | W27: IČO 01885219 | X27: CzechTrade listing; IČO 01885219; brand since 1957; Forbes CZ coverage | Y27: Remoska has a UK following - check existing UK distributor exclusivity | Z27: UK may have an exclusive distributor | AA27: Government export directory + business press | AB27: PASS - government export agency / trade body listing | AC27: Source link | AD27: Search LinkedIn | AE27: Round 5 | AF27: Not contacted | AK27: =IF(AG27="","",WORKDAY(AG27,5))
A28: Czech Republic | B28: 27 | C28: 4 | D28: Home & Kitchen | E28: PLASTIA s.r.o. (Urbalive) | F28: C - Low / little UK demand | G28: https://www.plastia.cz | H28: Nové Veselí (Vysočina) | J28: EU / Europe | K28: Low-cost | L28: Žďárská 313, 592 14 Nové Veselí | M28: +420 566 667 001 | N28: info@plastia.cz | O28: Manufacturer (family-owned) | P28: Plastia self-watering planters, Urbalive (incl. pet products) | Q28: Planters & home-garden | R28: On request | S28: Distributors in 56+ countries | T28: Ask | U28: Unknown | V28: Unknown | X28: CzechTrade listing; Spoga+Gafa, IPM Essen & Interzoo exhibitor | Y28: Self-watering pots & herb planters sell well; light and stackable | AA28: Government export directory + 3 trade fairs | AB28: PASS - government export agency / trade body listing | AC28: Source link | AD28: Search LinkedIn | AE28: Round 5 | AF28: Not contacted | AK28: =IF(AG28="","",WORKDAY(AG28,5))
A29: Czech Republic | B29: 28 | C29: 3 | D29: Home & Kitchen | E29: BLEX, a.s. | F29: C - Low / little UK demand | G29: Not confirmed - click to search | H29: Karlovy Vary | J29: EU / Europe | K29: Low-cost | L29: Závodu míru 327/4, 360 17 Karlovy Vary | O29: Manufacturer | P29: Tinplate & non-stick bakeware, wire kitchenware | Q29: Bakeware | R29: On request | S29: Export buyers (export manager: Kateřina Veselá) | T29: Ask - exports worldwide | U29: Unknown | V29: Unknown | W29: IČO 25247409 | X29: Listed in the CzechTrade (government agency) exporter directory | Y29: Baking tins & moulds are a steady category; possible private label | AA29: Government export directory | AB29: PASS - government export agency / trade body listing | AC29: Source link | AD29: Search LinkedIn | AE29: Round 4 | AF29: Not contacted | AK29: =IF(AG29="","",WORKDAY(AG29,5))
A30: Czech Republic | B30: 29 | C30: 3 | D30: Home & Kitchen | E30: Dřevotvar družstvo | F30: C - Low / little UK demand | G30: https://www.drevotvar.cz | H30: Jablonné nad Orlicí | J30: EU / Europe | K30: Low-cost | L30: Slezská 535, 561 64 Jablonné nad Orlicí | M30: +420 465 677 111 (sales: +420 465 677 219) | N30: drevotvar@drevotvar.cz | O30: Manufacturer (cooperative) | P30: Wooden kitchen utensils & boards | Q30: Wooden kitchenware | R30: On request | S30: Export buyers (85% of output exported) | T30: Ask | U30: Unknown | V30: Unknown | W30: IČO 00029882 | X30: Listed in the CzechTrade exporter directory | Y30: Wooden utensils & chopping boards - possible private label | AA30: Government export directory | AB30: PASS - government export agency / trade body listing | AC30: Source link | AD30: Search LinkedIn | AE30: Round 4 | AF30: Not contacted | AK30: =IF(AG30="","",WORKDAY(AG30,5))
A31: Czech Republic | B31: 30 | C31: 3 | D31: Pet Supplies | E31: Funky Dog (Czech eco pet accessories) | F31: C - Low / little UK demand | G31: Not confirmed - click to search | H31: Prague | J31: EU / Europe | K31: Low-cost | L31: Braunerova 7, 180 00 Praha | O31: Manufacturer / brand owner | P31: Funky Dog vegan collars, leads, beds | Q31: Eco pet accessories | R31: On request | S31: Distributors (SK, AT, IT, SI); CEO Katarína Králová | T31: Ask | U31: Unknown | V31: Unknown | W31: IČO 03688623 | X31: CzechTrade listing; IČO 03688623; since 2015 | Y31: Eco/vegan collars are a growing niche | Z31: Small firm - check capacity | AA31: Government export directory | AB31: PASS - government export agency / trade body listing | AC31: Source link | AD31: Search LinkedIn | AE31: Round 5 | AF31: Not contacted | AK31: =IF(AG31="","",WORKDAY(AG31,5))
A32: Czech Republic | B32: 31 | C32: 3 | D32: Pet Supplies | E32: Tommi CZ s.r.o. (Tommiland B2B) | F32: C - Low / little UK demand | G32: http://www.tommicz.eu | H32: Písek | J32: EU / Europe | K32: Low-cost | L32: Za Nádražím 2569, 397 01 Písek | M32: +420 382 264 269 | O32: Manufacturer / distributor | P32: Asan, Cat Step, Dr. Jag, Catwill, Doggies + European brands - 3,500+ products | Q32: Pet care & litter | R32: Min. order value ~€1,000 (2018 - confirm) | S32: Registered partners only (B2B e-shop) | T32: Exports - ask | U32: Unknown | V32: Unknown | X32: Founded 1989; CzechTrade exporter; export manager Hana Bečková | AA32: Trade show + CzechTrade directory | AB32: PASS - government export agency / trade body listing | AC32: Source link | AD32: Search LinkedIn | AE32: Round 2 | AF32: Not contacted | AK32: =IF(AG32="","",WORKDAY(AG32,5))
A33: Czech Republic | B33: 32 | C33: 4 | D33: Sports & Outdoors | E33: GALA a.s. | F33: C - Low / little UK demand | G33: https://www.gala.cz | H33: Prostějov | J33: EU / Europe | K33: Low-cost | L33: Západní 1/75, 796 04 Prostějov | M33: +420 739 648 045 | N33: grmelova@gala.cz (sales manager) | O33: Manufacturer | P33: Gala volleyballs, basketballs, footballs, handballs | Q33: Sports balls | R33: On request | S33: Sales manager Alena Grmelová | T33: Ask | U33: Unknown | V33: Unknown | W33: IČO 49969820 | X33: FIBA equipment partner; IČO 49969820; published annual reports | Y33: Volleyballs & beach balls sell well in summer; low cost vs Mikasa/Molten | AA33: FIBA partner listing + company register | AB33: PASS - company register entry | AC33: Source link | AD33: Search LinkedIn | AE33: Round 5 | AF33: Not contacted | AK33: =IF(AG33="","",WORKDAY(AG33,5))
A34: Czech Republic | B34: 33 | C34: 4 | D34: Sports & Outdoors | E34: Plastkon product s.r.o. (Gizmo Riders) | F34: C - Low / little UK demand | G34: http://www.plastkon.cz | H34: Mikulovice | J34: EU / Europe | K34: Low-cost | L34: Hlavní 147, 790 84 Mikulovice | O34: Manufacturer | P34: Gizmo Riders & Snowflake sledges, snow shovels; Gardenico & Flower Lover garden products | Q34: Sledges, winter & garden plastics | R34: On request | S34: Exports to 70+ countries | T34: Ask | U34: Unknown | V34: Unknown | W34: IČO 63321289 | X34: CzechTrade listing; IČO 63321289; since 1998; ~195 staff | Y34: Sledges sell strongly Nov-Jan in UK (snow years); plant pots in spring | Z34: Very seasonal - order early | AA34: Government export directory + company site | AB34: PASS - government export agency / trade body listing | AC34: Source link | AD34: Search LinkedIn | AE34: Round 5 | AF34: Not contacted | AK34: =IF(AG34="","",WORKDAY(AG34,5))
A35: Czech Republic | B35: 34 | C35: 3 | D35: Sports & Outdoors | E35: BP Lumen s.r.o. | F35: C - Low / little UK demand | G35: Not confirmed - click to search | H35: Úpice | J35: EU / Europe | K35: Low-cost | L35: Puškinova 546, 542 32 Úpice | O35: Manufacturer + parts wholesaler | P35: Levit & Qayron bikes/e-bikes; wholesale bicycle parts & accessories; private-label assembly | Q35: Bicycle parts & accessories wholesale | R35: On request | S35: Exports to 20+ European countries | T35: Ask | U35: Unknown | V35: Unknown | W35: IČO 05565375 | X35: CzechTrade listing; IČO 05565375; trading since 1991; 51-250 staff | Y35: Bike parts/accessories wholesale (tubes, tyres, lights) - small items suit FBA | Z35: E-bikes have lithium batteries (hazmat) | AA35: Government export directory | AB35: PASS - government export agency / trade body listing | AC35: Source link | AD35: Search LinkedIn | AE35: Round 5 | AF35: Not contacted | AK35: =IF(AG35="","",WORKDAY(AG35,5))
A36: Czech Republic | B36: 35 | C36: 3 | D36: Sports & Outdoors | E36: Sedco s.r.o. | F36: C - Low / little UK demand | G36: Not confirmed - click to search | H36: Prostějov | J36: EU / Europe | K36: Low-cost | L36: Průmyslová 3143/5, 796 01 Prostějov | N36: obchod@sedco.cz | O36: Wholesaler / importer + own brand | P36: Sedco sports & recreation equipment (balls, fitness, rackets, outdoor games) | Q36: Sports & recreation wholesale | R36: Trade account | S36: Wholesale customers; sells on Decathlon marketplace | T36: Ask | U36: Unknown | V36: Unknown | X36: Registered 2000 (EMIS); own warehouse complex in Prostějov; Decathlon marketplace seller (CZ & PL) | Y36: Cheap fitness & garden-game items; check own-brand vs third-party lines | AA36: Marketplace seller data + business database | AB36: PASS - company register entry | AC36: Source link | AD36: Search LinkedIn | AE36: Round 5 | AF36: Not contacted | AK36: =IF(AG36="","",WORKDAY(AG36,5))
A37: Czech Republic | B37: 36 | C37: 4 | D37: Stationery & Office | E37: KOH-I-NOOR HARDTMUTH a.s. | F37: B - Moderate | G37: https://www.koh-i-noor.cz | H37: České Budějovice | J37: EU / Europe | K37: Low-cost | L37: F. A. Gerstnera 21/3, 370 01 České Budějovice | N37: kht@koh-i-noor.cz | O37: Brand owner / manufacturer | P37: Koh-i-noor pencils, crayons, art supplies, Progresso | Q37: Art & school supplies | R37: On request | S37: Distributors & retailers (trade arm in Pelhřimov) | T37: Exports to 90+ countries - ask | U37: Unknown | V37: Unknown | X37: Historic Czech manufacturer; factories in CZ & BG | Y37: Art supplies sell well | AA37: Wikipedia + retailer imprint + registry | AB37: PASS - company register entry | AC37: Source link | AD37: Search LinkedIn | AE37: Round 4 | AF37: Not contacted | AK37: =IF(AG37="","",WORKDAY(AG37,5))
A38: Czech Republic | B38: 37 | C38: 4 | D38: Toys & Games | E38: Dino Toys s.r.o. | F38: C - Low / little UK demand | G38: https://www.dinotoys.cz | H38: Mnichovo Hradiště | J38: EU / Europe | K38: Low-cost | L38: K Pískovně 108, 295 01 Mnichovo Hradiště | M38: +420 324 709 315 (verify) | N38: export@dinotoys.cz | O38: Manufacturer | P38: Dino puzzles, board games, cards; Disney & Krtek (Little Mole) licences | Q38: Puzzles & board games | R38: On request | S38: Export manager: Barbora Kovaříková; exports to 20+ countries | T38: Ask | U38: Unknown | V38: Unknown | W38: IČO 49101650 | X38: CzechTrade (government export agency) listing; IČO 49101650; since 1993 | Y38: Puzzles are made in CZ at low cost - good margin potential; check licence rules for Disney lines | AA38: Government export directory + retailer data | AB38: PASS - government export agency / trade body listing | AC38: Source link | AD38: Search LinkedIn | AE38: Round 5 | AF38: Not contacted | AK38: =IF(AG38="","",WORKDAY(AG38,5))
A39: Czech Republic | B39: 38 | C39: 3 | D39: Toys & Games | E39: Albi Česká republika a.s. | F39: C - Low / little UK demand | G39: https://www.albi.cz | H39: Červený Kostelec (warehouse) | J39: EU / Europe | K39: Low-cost | L39: Lhota za Červeným Kostelcem 439 (warehouse) | O39: Publisher / distributor / retailer | P39: Albi board games, gifts, Kouzelné čtení; distributes partner publishers | Q39: Board games & gifts | R39: On request | S39: Bookshops, toy stores, hypermarkets | T39: CZ/SK/PL focus - ask | U39: Unknown | V39: Unknown | X39: Czech business award winner; own shop chain; Ares Games EU distribution partner | AA39: Business press + job listings | AB39: PASS - well-known company: Leading Czech games publisher & retailer. | AC39: Source link | AD39: Search LinkedIn | AE39: Round 4 | AF39: Not contacted | AK39: =IF(AG39="","",WORKDAY(AG39,5))
A40: Czech Republic | B40: 39 | C40: 3 | D40: Toys & Games | E40: Bino Europe k.s. | F40: C - Low / little UK demand | G40: Not confirmed - click to search | H40: Mladá Boleslav | J40: EU / Europe | K40: Low-cost | L40: tř. Václava Klementa 836, 293 01 Mladá Boleslav | O40: Manufacturer / distributor | P40: Bino wooden & plastic toys, children's furniture, nursery equipment | Q40: Toddler & wooden toys | R40: On request | S40: Exports to 30+ countries; offices in China & Germany | T40: Ask | U40: Unknown | V40: Unknown | W40: IČO 24220931 / VAT CZ24220931 | X40: CzechTrade listing; IČO 24220931; VAT CZ24220931; LEI 3157004KB9Y233461R58 | Y40: Cheap wooden/toddler toys; ask for EN71 reports (some made in China) | Z40: Some products made in China - check origin & compliance | AA40: Government export directory + company register | AB40: PASS - government export agency / trade body listing | AC40: Source link | AD40: Search LinkedIn | AE40: Round 5 | AF40: Not contacted | AK40: =IF(AG40="","",WORKDAY(AG40,5))
A41: Denmark | B41: 40 | C41: 4 | D41: Baby Products | E41: BabyDan A/S | F41: B - Moderate | G41: https://www.babydan.com | H41: Låsby | J41: EU / Europe | K41: Higher | L41: Niels Bohr Vej 14, 8670 Låsby | N41: info@babydan.com | O41: Brand owner / manufacturer | P41: BabyDan safety gates (EN 1930), playpens, home safety | Q41: Baby safety | R41: On request | S41: Retailers & distributors | T41: Ask | U41: Unknown | V41: Unknown | X41: Own factories in Denmark; 90+ Trustpilot reviews | Y41: Safety gates are a strong Amazon category | AA41: Retailer listing + company site | AB41: PASS - well-known company: Danish baby-safety brand since 1977, sold worldwide. | AC41: Source link | AD41: Search LinkedIn | AE41: Round 4 | AF41: Not contacted | AK41: =IF(AG41="","",WORKDAY(AG41,5))
A42: Denmark | B42: 41 | C42: 3 | D42: Baby Products | E42: Liewood A/S | F42: B - Moderate | G42: https://www.liewood.com | H42: Copenhagen | J42: EU / Europe | K42: Higher | L42: Blegdamsvej 124, 2100 Copenhagen | N42: customerservice@liewood.com (ask for wholesale) | O42: Brand owner | P42: Liewood baby & kids tableware, toys, textiles | Q42: Premium baby & kids lifestyle | R42: Wholesale minimum order (ask) | S42: Retail stores / webshops; 900+ wholesale partners | T42: Yes - sold internationally | U42: Unknown | V42: Unknown | X42: Manufacturer contact on EU retailer GPSR listings; sold via Boozt | Y42: Silicone tableware & bibs sell well; check brand gating | Z42: Premium brand - check MAP pricing policy | AA42: Retailer GPSR data + company LinkedIn | AB42: PASS - well-known company: Well-known Danish kids' lifestyle brand (900+ wholesale partners). | AC42: Source link | AD42: Search LinkedIn | AE42: Round 4 | AF42: Not contacted | AK42: =IF(AG42="","",WORKDAY(AG42,5))
A43: Denmark | B43: 42 | C43: 3 | D43: Beauty | E43: ECOOKING A/S | F43: C - Low / little UK demand | G43: https://www.ecooking.com | H43: Bjert (Kolding) | J43: EU / Europe | K43: Higher | L43: Gl. Skartved 11, 6091 Bjert (verify) | M43: +45 70 70 73 66 (verify) | O43: Brand owner | P43: Ecooking organic skincare | Q43: Organic skincare | R43: Account based | S43: Shops & online retailers (32 countries) | T43: Ask | U43: Unknown | V43: Unknown | X43: 70% owned by Bluegem Capital (2021 deal); stocked by Lyko | Y43: Clean-beauty serums & creams have growing demand | AA43: PE press release + business data | AB43: PASS - established brand / group | AC43: Source link | AD43: Search LinkedIn | AE43: Round 4 | AF43: Not contacted | AK43: =IF(AG43="","",WORKDAY(AG43,5))
A44: Denmark | B44: 43 | C44: 3 | D44: Pet Supplies | E44: Jørgen Kruuse A/S (KRUUSE, BUSTER) | F44: B - Moderate | G44: https://kruuse.com/frontpage/welcome-at-kruuse/about-kruuse | H44: Langeskov | J44: EU / Europe | K44: Higher | L44: Erik Stocks Allé 3, 5550 Langeskov | O44: Veterinary & pet products supplier | P44: BUSTER pet accessories (food dispensers, collars), KRUUSE vet supplies | Q44: Pet accessories & vet | R44: Account based | S44: Appointed distributors (350+ in 100+ countries) | T44: Ask who distributes BUSTER in the UK | U44: Unknown | V44: Unknown | X44: Majority-owned by Henry Schein (NASDAQ); 12,000 catalogue lines | Y44: BUSTER activity toys sell well | AA44: Company site + investor news | AB44: PASS - listed company | AC44: Source link | AD44: Search LinkedIn | AE44: Round 4 | AF44: Not contacted | AK44: =IF(AG44="","",WORKDAY(AG44,5))
A45: Denmark | B45: 44 | C45: 4 | D45: Sports & Outdoors | E45: Oase Outdoors ApS (Outwell, Easy Camp, Robens) | F45: A - Strong (household name) | G45: https://www.oase-outdoors.dk | H45: Give | J45: EU / Europe | K45: Higher | L45: Give (HQ) | O45: Brand owner | P45: Outwell, Easy Camp, Robens tents, camping furniture & equipment | Q45: Camping | R45: Account based | S45: Dealers & agents in 45 countries | T45: UK is a main market - ask for UK agent | U45: Unknown | V45: Unknown | X45: Owned by Ratos (listed Swedish investor); founded 1984 | Y45: Popular camping brands on Amazon UK | AA45: Investor portfolio page | AB45: PASS - established brand / group | AC45: Source link | AD45: Search LinkedIn | AE45: Round 4 | AF45: Not contacted | AK45: =IF(AG45="","",WORKDAY(AG45,5))
A46: Denmark | B46: 45 | C46: 3 | D46: Sports & Outdoors | E46: Select Sport A/S (incl. Derbystar) | F46: B - Moderate | G46: https://www.select-sport.com | H46: Glostrup | J46: EU / Europe | K46: Higher | L46: Fabriksparken 46, 2600 Glostrup | O46: Brand owner / manufacturer | P46: Select & Derbystar footballs, handballs, sportswear, accessories | Q46: Team sports | R46: Account based | S46: Distributors & retailers (exports to 50+ countries) | T46: Ask | U46: Unknown | V46: Unknown | X46: Owns Derbystar since 1991; Bundesliga match-ball supplier | Y46: Footballs sell well seasonally | AA46: Wikipedia + Bundesliga release | AB46: PASS - established brand / group | AC46: Source link | AD46: Search LinkedIn | AE46: Round 4 | AF46: Not contacted | AK46: =IF(AG46="","",WORKDAY(AG46,5))
A47: Denmark | B47: 46 | C47: 3 | D47: Stationery & Office | E47: Creativ Company A/S | F47: C - Low / little UK demand | G47: Not confirmed - click to search | H47: Holstebro | J47: EU / Europe | K47: Higher | L47: Rasmus Færchs Vej 23, 7500 Holstebro (verify) | O47: Art & craft wholesaler | P47: Art & craft materials | Q47: Arts & crafts | R47: On request | S47: Schools & wholesale customers | T47: Yes - UK is a main market | U47: Unknown | V47: Unknown | W47: CVR 28692927 | X47: Sells in 40 countries | AA47: Company profile (Nordic9) | AB47: PASS - company register entry | AC47: Source link | AD47: Search LinkedIn | AE47: Round 2 | AF47: Not contacted | AK47: =IF(AG47="","",WORKDAY(AG47,5))
A48: Denmark | B48: 47 | C48: 4 | D48: Toys & Games | E48: Plus-Plus A/S | F48: B - Moderate | G48: https://www.plusplus.com | H48: Holbæk | J48: EU / Europe | K48: Higher | L48: Borupvej 20, Holbæk | O48: Brand owner / manufacturer | P48: Plus-Plus construction pieces (made in Denmark) | Q48: Construction toys | R48: Account based | S48: Distributors (40+ countries) | T48: Yes - UK office in Berkshire (since 2023) | U48: Unknown | V48: Unknown | X48: Own Danish factory; Formland & London Toy Fair exhibitor | Y48: Popular creative toy on Amazon | Z48: Contact the UK office. | AA48: Trade fair listings + trade data | AB48: PASS - major trade-fair exhibitor | AC48: Source link | AD48: Search LinkedIn | AE48: Round 4 | AF48: Not contacted | AK48: =IF(AG48="","",WORKDAY(AG48,5))
A49: Finland | B49: 48 | C49: 4 | D49: Beauty | E49: Lumene Oy | F49: B - Moderate | G49: https://www.lumene.com | H49: Espoo | J49: EU / Europe | K49: Higher | L49: Lasikuja 2, 02780 Espoo | O49: Brand owner / manufacturer | P49: Lumene Nordic skincare & makeup, Cutrin haircare | Q49: Skincare & cosmetics | R49: Account based | S49: Distributors & retailers | T49: UK is a key market - ask who distributes | U49: Unknown | V49: Unknown | X49: Leading Finnish cosmetics brand; Verdane & Creades owned | Y49: Lumene sells well on Amazon UK | AA49: Wikipedia + investor news + trade data | AB49: PASS - well-known company: Finland's best-known cosmetics brand. | AC49: Source link | AD49: Search LinkedIn | AE49: Round 4 | AF49: Not contacted | AK49: =IF(AG49="","",WORKDAY(AG49,5))
A50: Finland | B50: 49 | C50: 4 | D50: DIY & Tools | E50: Fiskars Group (Fiskars Finland Oy Ab) | F50: A - Strong (household name) | G50: https://www.fiskarsgroup.com | H50: Espoo | J50: EU / Europe | K50: Higher | L50: Keilaniementie 10, 02150 Espoo | O50: Brand owner (listed) | P50: Fiskars garden tools, axes, scissors; also Gerber, Iittala (home) | Q50: Garden & hand tools | R50: Account based | S50: Regional sales offices & official distributors | T50: Has UK sales office - ask | U50: Unknown | V50: Unknown | X50: Helsinki-listed; global consumer-goods group | Y50: Fiskars is a top Amazon garden brand | AA50: Wikipedia + embassy news | AB50: PASS - listed company | AC50: Source link | AD50: Search LinkedIn | AE50: Round 4 | AF50: Not contacted | AK50: =IF(AG50="","",WORKDAY(AG50,5))
A51: Finland | B51: 50 | C51: 4 | D51: Home & Kitchen | E51: Orthex Finland Ab Oy (SmartStore) | F51: B - Moderate | G51: https://www.orthexgroup.com | H51: Espoo | J51: EU / Europe | K51: Higher | L51: Suomalaistentie 7, 02270 Espoo | M51: +358 19 32961 (verify) | N51: Contact form on orthexgroup.fi | O51: Brand owner / manufacturer (listed) | P51: SmartStore storage boxes, GastroMax kitchenware, Orthex garden | Q51: Storage & kitchenware | R51: Account based | S51: Retailers & distributors; 8 sales organisations incl. UK | T51: Yes - has UK sales organisation | U51: Unknown | V51: Unknown | X51: Nasdaq Helsinki-listed group | Y51: SmartStore storage boxes are popular; bulky items cost more in FBA fees | AA51: Investor site + retailer GPSR data | AB51: PASS - listed company | AC51: Source link | AD51: Search LinkedIn | AE51: Round 4 | AF51: Not contacted | AK51: =IF(AG51="","",WORKDAY(AG51,5))
A52: Finland | B52: 51 | C52: 5 | D52: Toys & Games | E52: Tactic Games Oy | F52: B - Moderate | G52: https://www.tactic.net | H52: Pori | J52: EU / Europe | K52: Higher | L52: Raumanjuovantie 2, 28100 Pori | N52: sales.uk@tactic.net (UK distributor enquiries) | O52: Manufacturer & distributor | P52: Tactic games, Mölkky, Heros wooden toys, Plasto, Bex Sport, Puzzle Lovers | Q52: Games & outdoor games | R52: On request | S52: Import & distribution partners (moving UK to partner model) | T52: Actively seeking UK import/distribution partners | U52: Unknown | V52: Unknown | X52: Leading Nordic board-game maker & toy distributor; own factory & logistics in Pori | Y52: Opportunity: they want UK partners right now | Z52: Book meeting: juha.nieminen@tactic.net. | AA52: Company presentation (Kids' Time) + registry + LinkedIn post | AB52: PASS - company register entry | AC52: Source link | AD52: Search LinkedIn | AE52: Round 4 | AF52: Not contacted | AK52: =IF(AG52="","",WORKDAY(AG52,5))
A53: France | B53: 52 | C53: 4 | D53: Baby Products | E53: Béaba Group (incl. Childhome) | F53: A - Strong (household name) | G53: https://www.beaba.com | H53: Bellignat | J53: EU / Europe | K53: Higher | L53: Bellignat | O53: Brand owner / distributor | P53: Béaba Babycook, feeding, hygiene, sleep; Childhome; distributes iCandy (FR/Benelux) | Q53: Baby feeding & nursery | R53: On request | S53: Retailers & distributors | T53: Sold in 70+ countries - ask | U53: Unknown | V53: Unknown | X53: Backed by Bluegem Capital; acquired Childhome (BE) 2020 | Y53: Babycook is a strong Amazon seller; also on Qogita | AA53: Investor profile + trade press | AB53: PASS - established brand / group | AC53: Source link | AD53: Search LinkedIn | AE53: Round 4 | AF53: Not contacted | AK53: =IF(AG53="","",WORKDAY(AG53,5))
A54: France | B54: 53 | C54: 4 | D54: Baby Products | E54: Babymoov Group | F54: B - Moderate | G54: https://www.babymoov.com | H54: Clermont-Ferrand | J54: EU / Europe | K54: Higher | L54: 16 rue Jacqueline Auriol, ZI Gravanches, 63100 Clermont-Ferrand | M54: +33 4 73 28 60 00 (verify) | O54: Brand owner / manufacturer | P54: Babymoov, doomoo | Q54: Baby monitors, feeding, sleep & travel | R54: Account based | S54: Specialist stores & web retailers in 50+ countries | T54: Ask - exports ~46% of sales | U54: Unknown | V54: Unknown | X54: ~EUR 55m turnover (2022); sold via Boulanger, Nature & Découvertes | Y54: Baby monitors & bottle warmers are strong Amazon lines | AA54: Company profiles + retailer listings | AB54: PASS - well-known company: Established French baby brand (~EUR 55m turnover). | AC54: Source link | AD54: Search LinkedIn | AE54: Round 4 | AF54: Not contacted | AK54: =IF(AG54="","",WORKDAY(AG54,5))
A55: France | B55: 54 | C55: 3 | D55: Baby Products | E55: Laboratoires Expanscience (Mustela) | F55: B - Moderate | G55: https://www.expanscience.com/en/expanscience/company | H55: Paris La Défense | J55: EU / Europe | K55: Higher | L55: 1 place des Saisons, 92048 Paris La Défense | M55: +33 1 43 34 60 00 | O55: Brand owner / manufacturer | P55: Mustela baby skincare, Noviderm | Q55: Baby skincare | R55: Account based | S55: 14 subsidiaries & distributors in 100+ countries | T55: Ask - via UK distributor/subsidiary | U55: Unknown | V55: Unknown | X55: Cosmébio member; family-owned French lab | Y55: Mustela is a strong baby-care seller | AA55: Industry directory + company press | AB55: PASS - well-known company: Mustela owner - major French pharma/cosmetics lab. | AC55: Source link | AD55: Search LinkedIn | AE55: Round 4 | AF55: Not contacted | AK55: =IF(AG55="","",WORKDAY(AG55,5))
A56: France | B56: 55 | C56: 3 | D56: Health & Personal Care | E56: Laboratoires Arkopharma | F56: C - Low / little UK demand | G56: https://www.arkopharma.com | H56: Carros (Nice) | J56: EU / Europe | K56: Higher | L56: Zone Industrielle de Carros, 06510 Carros | O56: Brand owner / manufacturer | P56: Arkopharma Arkogélules, Azinc, Arkoroyal | Q56: Herbal supplements | R56: Account based | S56: Direct or via distributors in 55 countries | T56: Ask | U56: Unknown | V56: Unknown | W56: SIREN 307378489 | X56: SIREN 307378489; ~EUR 164m revenue (2024) | Y56: Supplements sell well; Amazon category approval needed | Z56: Revenue fell in 2024 - check terms | AA56: Company registry (Pappers) + business press | AB56: PASS - company register entry | AC56: Source link | AD56: Search LinkedIn | AE56: Round 4 | AF56: Not contacted | AK56: =IF(AG56="","",WORKDAY(AG56,5))
A57: France | B57: 56 | C57: 3 | D57: Pet Supplies | E57: Zolux SAS | F57: B - Moderate | G57: https://en.zolux.com | H57: Saintes | J57: EU / Europe | K57: Higher | L57: 141 Cours Paul Doumer, 17100 Saintes | N57: export@zolux.com | O57: Brand owner / distributor | P57: Zolux, Francodex, Mastery, Saint Bernard, Anah | Q57: Pet accessories & care | R57: On request | S57: Retailers, distributors, exporters | T57: Partners in 50+ countries - ask | U57: Unknown | V57: Unknown | X57: ~€128m turnover (2022); subsidiaries FR, PL, IT, Iberia | AA57: Industry directory + company profile | AB57: PASS - established brand / group | AC57: Source link | AD57: Search LinkedIn | AE57: Round 3 | AF57: Not contacted | AK57: =IF(AG57="","",WORKDAY(AG57,5))
A58: France | B58: 57 | C58: 4 | D58: Sports & Outdoors | E58: Zéfal SAS | F58: B - Moderate | G58: https://www.zefal.com | H58: Jargeau (Loiret) | J58: EU / Europe | K58: Higher | L58: Jargeau | O58: Brand owner / manufacturer | P58: Zéfal pumps, bottles, mudguards, locks, bike accessories | Q58: Cycling accessories | R58: On request | S58: Distributors (exclusive UK distributor: Chicken CycleKit - sales@chickencyclekit.co.uk) | T58: Yes - via Chicken CycleKit (UK) | U58: Unknown | V58: Unknown | X58: ~70% of turnover exported; long-established French brand | Y58: Small, light accessories = great FBA fit | Z58: Buy UK stock via Chicken CycleKit. | AA58: Trade press | AB58: PASS - established brand / group | AC58: Source link | AD58: Search LinkedIn | AE58: Round 4 | AF58: Not contacted | AK58: =IF(AG58="","",WORKDAY(AG58,5))
A59: France | B59: 58 | C59: 4 | D59: Stationery & Office | E59: Groupe Hamelin (Oxford, ELBA) - Hamelin GmbH export arm | F59: B - Moderate | G59: https://www.hamelinbrands.com | H59: Hérouville-Saint-Clair (Caen); sales co. Gronau (DE) | J59: EU / Europe | K59: Higher | L59: Hérouville-Saint-Clair, Normandy | N59: corporate.de@hamelinbrands.zendesk.com | O59: Brand owner / manufacturer | P59: Oxford notebooks, ELBA filing, Lamouette, Herlitz-style school paper | Q59: Notebooks & filing | R59: Account based | S59: Distributors & retailers (Hamelin GmbH handles DACH & export) | T59: Has UK operations (ELBA/Oxford) - ask | U59: Unknown | V59: Unknown | X59: Founded 1864; €400-600m turnover; Paperworld exhibitor | Y59: Oxford notebooks are strong sellers | AA59: Business press + trade fair listing | AB59: PASS - major trade-fair exhibitor | AC59: Source link | AD59: Search LinkedIn | AE59: Round 4 | AF59: Not contacted | AK59: =IF(AG59="","",WORKDAY(AG59,5))
A60: France | B60: 59 | C60: 4 | D60: Stationery & Office | E60: Maped SAS | F60: B - Moderate | G60: https://www.maped.com | H60: Argonay (Haute-Savoie) | J60: EU / Europe | K60: Higher | L60: 530 route de Pringy, 74370 Argonay | M60: +33 4 50 27 26 85 (verify) | O60: Brand owner / manufacturer | P60: Maped scissors, geometry, pencil cases, colouring; Helix (UK); owns Juratoys | Q60: School & office supplies | R60: Account based | S60: Distributors & retailers (18 subsidiaries) | T60: Has UK operation (Helix) - ask | U60: Unknown | V60: Unknown | X60: Present in 120+ countries; family-owned French group | Y60: Back-to-school bestsellers | AA60: Trade data + company directories | AB60: PASS - established brand / group | AC60: Source link | AD60: Search LinkedIn | AE60: Round 4 | AF60: Not contacted | AK60: =IF(AG60="","",WORKDAY(AG60,5))
A61: France | B61: 60 | C61: 3 | D61: Stationery & Office | E61: Exacompta Clairefontaine (ExaClair Ltd UK) | F61: B - Moderate | G61: https://exaclair.com/about_exaclair.php | H61: Étival-Clairefontaine (FR); UK office King's Lynn | J61: EU / Europe | K61: Higher | L61: ExaClair Ltd, King's Lynn, Norfolk (UK subsidiary) | O61: Manufacturer group with UK subsidiary | P61: Clairefontaine, Rhodia, Exacompta, Quo Vadis, Brause, Jacques Herbin, Decopatch | Q61: Premium paper & office | R61: Account based | S61: Stationery retailers | T61: Yes - ExaClair Ltd (UK) | U61: Unknown | V61: Unknown | X61: Euronext-listed group | Y61: Rhodia/Clairefontaine notebooks sell well | Z61: Use the UK subsidiary. | AA61: Wikipedia + trade press | AB61: PASS - listed company | AC61: Source link | AD61: Search LinkedIn | AE61: Round 3 | AF61: Not contacted | AK61: =IF(AG61="","",WORKDAY(AG61,5))
A62: France | B62: 61 | C62: 4 | D62: Toys & Games | E62: Juratoys SAS (Janod, Kaloo, Lilliputiens) | F62: B - Moderate | G62: https://www.janod.com | H62: Orgelet (Jura) | J62: EU / Europe | K62: Higher | L62: 13 rue de l'Industrie, 39270 Orgelet | M62: +33 3 84 25 40 26 (verify) | O62: Brand owner | P62: Janod wooden toys, Kaloo plush, Lilliputiens | Q62: Wooden & early-years toys | R62: Account based | S62: Retailers | T62: Has a UK office | U62: Unknown | V62: Unknown | X62: Offices in UK, US, HK, CN; reported acquired by Maped (2022) | Y62: Janod already sold on Amazon - brand-direct invoices | AA62: Trade show listing + trade press | AB62: PASS - established brand / group | AC62: Source link | AD62: Search LinkedIn | AE62: Round 4 | AF62: Not contacted | AK62: =IF(AG62="","",WORKDAY(AG62,5))
A63: France | B63: 62 | C63: 3 | D63: Toys & Games | E63: WDK Groupe Partner | F63: C - Low / little UK demand | G63: Not confirmed - click to search | H63: Tauxigny (Centre-Val de Loire) | J63: EU / Europe | K63: Higher | L63: 90 rue Guglielmo Marconi, Node Park Touraine, 37310 Tauxigny | M63: +33 2 47 43 80 43 | N63: asevingue@wdkpartner.com | O63: Toy & leisure wholesaler | P63: 10,000+ toy references; 14m toys sold/yr; runs Jouets Sajou network | Q63: Toys & family leisure | R63: On request | S63: Retailers | T63: France focus - ask | U63: Yes (marketplaces) | V63: Unknown | X63: France's No.1 toy wholesaler (trade press) | Y63: Already sells via marketplaces (Nature & Découvertes) | AA63: Marketplace seller profile + trade press | AB63: PASS (checked) - France's largest toy wholesaler; 64-store Jouets Sajou network. | AC63: Source link | AD63: Search LinkedIn | AE63: Round 2 | AF63: Not contacted | AK63: =IF(AG63="","",WORKDAY(AG63,5))
A64: Germany | B64: 63 | C64: 3 | D64: B2B Marketplace | E64: zentrada | F64: C - Low / little UK demand | G64: https://www.zentrada.eu | J64: EU / Europe | K64: Higher | O64: B2B trading network (consumer goods) | P64: Consumer goods from European wholesalers & importers (gifts, home, toys, seasonal) | Q64: General merchandise | R64: Per supplier | S64: Commercial buyers (retailers) | T64: Has .co.uk site - check | U64: Unknown | V64: Unknown | X64: Long-running EU B2B network; TradeSafe buyer protection & payment | Y64: Mostly generic/importer goods - check listing ownership | Z64: Auto-translated offers in 8 languages. | AA64: Company site + trade fair article | AB64: PASS - well-known company: Long-running European B2B wholesale network (since 2005). | AC64: Source link | AD64: Search LinkedIn | AE64: Round 2 | AF64: Not contacted | AK64: =IF(AG64="","",WORKDAY(AG64,5))
A65: Germany | B65: 64 | C65: 4 | D65: Baby Products | E65: MAPA GmbH (NUK) | F65: A - Strong (household name) | G65: https://www.mapa.de | H65: Zeven (Lower Saxony) | J65: EU / Europe | K65: Higher | L65: Industriestraße 21-25, 27404 Zeven | O65: Brand owner / manufacturer | P65: NUK bottles & dummies, Fresh Fruit feeders; also Billy Boy, household gloves | Q65: Baby feeding & soothers | R65: Account based | S65: Distributors & retailers (export director in place) | T65: Ask who handles NUK in UK | U65: Unknown | V65: Unknown | X65: Founded 1947/48; manufactures NUK; ships to NUK USA | Y65: NUK is a top Amazon baby brand | AA65: Registry profile + trade data | AB65: PASS - company register entry | AC65: Source link | AD65: Search LinkedIn | AE65: Round 4 | AF65: Not contacted | AK65: =IF(AG65="","",WORKDAY(AG65,5))
A66: Germany | B66: 65 | C66: 3 | D66: Baby Products | E66: MAM Babyartikel GmbH | F66: A - Strong (household name) | G66: https://www.mambaby.com | H66: Scheeßel (Lower Saxony) | J66: EU / Europe | K66: Higher | L66: Rudolf-Diesel-Str. 6, 27383 Scheeßel | M66: +49 4263 9317 0 | O66: Brand distributor (MAM Baby AG subsidiary) | P66: MAM dummies, bottles, teethers, feeding | Q66: Baby feeding & soothers | R66: Account based | S66: Retail chains & wholesale customers | T66: DE/AT/Benelux focus - UK has separate MAM UK | U66: Unknown | V66: No | X66: Official distribution arm of MAM Baby AG | Y66: Official brand source = best possible invoices | Z66: Approach as 'online retailer'; may refer you to a wholesaler. | AA66: Job listing + retailer imprint | AB66: PASS - established brand / group | AC66: Source link | AD66: Search LinkedIn | AE66: Round 2 | AF66: Not contacted | AK66: =IF(AG66="","",WORKDAY(AG66,5))
A67: Germany | B67: 66 | C67: 4 | D67: Baby Products | E67: hauck GmbH & Co. KG | F67: B - Moderate | G67: https://www.hauck.de | H67: Sonnefeld (Bavaria) | J67: EU / Europe | K67: Higher | L67: Frohnlacher Str. 8, 96242 Sonnefeld | O67: Brand owner / manufacturer | P67: hauck pushchairs, highchairs, travel cots, safety gates, toys | Q67: Nursery & travel | R67: Account based | S67: Specialty juvenile stores & chains (European sales team) | T67: Ask | U67: Unknown | V67: Unknown | X67: Founded 1923 (100-year anniversary 2023) | Y67: Highchairs & gates sell well; bulky items = higher FBA fees | AA67: Directory + trade press | AB67: PASS - established brand / group | AC67: Source link | AD67: Search LinkedIn | AE67: Round 4 | AF67: Not contacted | AK67: =IF(AG67="","",WORKDAY(AG67,5))
A68: Germany | B68: 67 | C68: 4 | D68: Baby Products | E68: Lässig GmbH | F68: B - Moderate | G68: https://www.laessig-fashion.de | H68: Babenhausen (Hesse) | J68: EU / Europe | K68: Higher | L68: Im Riemen 32, 64832 Babenhausen | M68: +49 6073 744890 | N68: service@laessig-gmbh.de | O68: Brand owner | P68: LÄSSIG changing bags, kids' backpacks, tableware, swimwear (GOTS certified) | Q68: Baby bags & accessories | R68: On request | S68: Retailers | T68: Ask | U68: Unknown | V68: Unknown | X68: GOTS-certified; Maison&Objet exhibitor | Y68: Changing bags sell well; brand-direct invoices | AA68: Retailer imprint + certification database | AB68: PASS - major trade-fair exhibitor | AC68: Source link | AD68: Search LinkedIn | AE68: Round 4 | AF68: Not contacted | AK68: =IF(AG68="","",WORKDAY(AG68,5))
A69: Germany | B69: 68 | C69: 3 | D69: Baby Products | E69: 2E Vertriebs-GmbH (Simple Parenting) | F69: C - Low / little UK demand | G69: https://www.2e-vertrieb.de | H69: Cologne | J69: EU / Europe | K69: Higher | L69: Bismarckstraße 60, 50672 Köln | M69: +49 221 99987860 | N69: info@2e-vertrieb.de | O69: Distributor (brand rights) | P69: Family & parenting brands (distribution rights) | Q69: Baby & parenting | R69: On request | S69: Trade | T69: DACH/Benelux/France focus - ask | U69: Unknown | V69: Unknown | W69: HRB 80853 | X69: HRB 80853 Köln; founded 2014; MDs Daniel Gruber & Christian Thalmann | AA69: Company registry profile | AB69: PASS (checked) - HRB 80853 Köln; 18 staff. | AC69: Source link | AD69: Search LinkedIn | AE69: Round 2 | AF69: Not contacted | AK69: =IF(AG69="","",WORKDAY(AG69,5))
A70: Germany | B70: 69 | C70: 3 | D70: Baby Products | E70: reer GmbH | F70: C - Low / little UK demand | G70: https://www.reer.de | H70: Leonberg | J70: EU / Europe | K70: Higher | L70: Mühlstraße 41, 71229 Leonberg | M70: +49 7152 928520 | N70: service@reer.de | O70: Brand owner | P70: reer child-safety (locks, gates, corner guards), bottle warmers, baby monitors | Q70: Baby safety | R70: On request | S70: Retailers | T70: Ask | U70: Unknown | V70: Unknown | X70: 100+ year history; Ambiente exhibitor (Safe & Care GmbH) | Y70: Safety items sell well; check EN standards on pack | AA70: Retailer product pages + trade fair | AB70: PASS - major trade-fair exhibitor | AC70: Source link | AD70: Search LinkedIn | AE70: Round 3 | AF70: Not contacted | AK70: =IF(AG70="","",WORKDAY(AG70,5))
A71: Germany | B71: 70 | C71: 4 | D71: Beauty | E71: cosnova GmbH (essence, CATRICE) | F71: A - Strong (household name) | G71: https://www.cosnova.com | H71: Sulzbach (Taunus) | J71: EU / Europe | K71: Higher | L71: Am Limespark 2, 65843 Sulzbach | M71: +49 6196 76156-0 | N71: service@cosnova.eu | O71: Brand owner (direct + local distributors) | P71: essence, CATRICE, Physicians Formula (EU) | Q71: Mass cosmetics | R71: Account based | S71: Drugstores, retailers & online retail partners | T71: Sold in 90+ countries - ask about UK distributor | U71: Unknown | V71: No | X71: 22,000+ points of sale; publishes annual results | Y71: essence & CATRICE are top Amazon beauty sellers - may route you to UK distributor | AA71: Company letterhead / press releases | AB71: PASS - well-known company: Owner of essence & CATRICE - one of Europe's largest make-up brands. | AC71: Source link | AD71: Search LinkedIn | AE71: Round 3 | AF71: Not contacted | AK71: =IF(AG71="","",WORKDAY(AG71,5))
A72: Germany | B72: 71 | C72: 4 | D72: Beauty | E72: Weleda AG (German branch) | F72: A - Strong (household name) | G72: https://www.weleda.de | H72: Schwäbisch Gmünd | J72: EU / Europe | K72: Higher | L72: Möhlerstraße 3, 73525 Schwäbisch Gmünd | N72: dialog@weleda.de | O72: Brand owner / manufacturer | P72: Weleda natural skincare, baby care (Calendula), Skin Food | Q72: Natural skincare & baby care | R72: Account based | S72: Via subsidiaries in 20 countries & distributors | T72: Yes - Weleda UK subsidiary | U72: Unknown | V72: Unknown | X72: Largest Weleda branch; group present in 50+ countries | Y72: Skin Food is a strong Amazon seller | Z72: Contact Weleda UK for UK accounts. | AA72: Wikipedia + retailer imprint | AB72: PASS - established brand / group | AC72: Source link | AD72: Search LinkedIn | AE72: Round 4 | AF72: Not contacted | AK72: =IF(AG72="","",WORKDAY(AG72,5))
A73: Germany | B73: 72 | C73: 3 | D73: Beauty | E73: ARTDECO cosmetic GmbH | F73: B - Moderate | G73: https://www.artdeco.de | H73: Karlsfeld (near Munich) | J73: EU / Europe | K73: Higher | L73: Gaußstraße 13, 85757 Karlsfeld (HRB 76194 Munich) | O73: Brand owner / manufacturer | P73: ARTDECO, Annemarie Börlind (group), Dr. Belter | Q73: Cosmetics | R73: Account based | S73: Distributors & retailers | T73: Sold in 65+ countries - ask | U73: Unknown | V73: Unknown | W73: HRB 76194 | X73: Registered HRB 76194; branches FR & IT; sister co. PLCC (export@plcc-gmbh.com) | AA73: Company register + trade fair listing | AB73: PASS - company register entry | AC73: Source link | AD73: Search LinkedIn | AE73: Round 4 | AF73: Not contacted | AK73: =IF(AG73="","",WORKDAY(AG73,5))
A74: Germany | B74: 73 | C74: 3 | D74: Beauty | E74: LOGOCOS Naturkosmetik GmbH & Co. KG (Sante, Logona) | F74: C - Low / little UK demand | G74: https://www.sante.de | H74: Salzhemmendorf (production) / Düsseldorf (sales) | J74: EU / Europe | K74: Higher | L74: Salzhemmendorf, Lower Saxony | O74: Brand owner / manufacturer | P74: Sante natural cosmetics, Logona natural haircare & colour | Q74: Natural cosmetics | R74: Account based | S74: Retailers & export partners (export key account team) | T74: Has export business development team - ask | U74: Unknown | V74: Unknown | X74: Certified natural cosmetics; formerly L'Oréal-owned (2018-22) | AA74: Company job postings + trade press | AB74: PASS - well-known company: Major German natural-cosmetics maker (Sante, Logona). | AC74: Source link | AD74: Search LinkedIn | AE74: Round 4 | AF74: Not contacted | AK74: =IF(AG74="","",WORKDAY(AG74,5))
A75: Germany | B75: 74 | C75: 4 | D75: DIY & Tools | E75: Einhell Germany AG | F75: A - Strong (household name) | G75: https://www.einhell.com/einhell-worldwide/ | H75: Landau an der Isar | J75: EU / Europe | K75: Higher | L75: Wiesenweg 22, 94405 Landau/Isar | N75: via website contact form | O75: Brand owner (listed) | P75: Einhell Power X-Change cordless tools, garden tools, workshop | Q75: Power & garden tools | R75: Account based | S75: Retailers, mail-order, online retailers (49 subsidiaries) | T75: Has Einhell UK subsidiary | U75: Unknown | V75: Unknown | X75: 2,700+ staff; sold in 99+ countries; listed company | Y75: Huge Amazon brand; lithium batteries = hazmat docs | Z75: Contact Einhell UK for UK accounts. | AA75: Company site + investor news | AB75: PASS - listed company | AC75: Source link | AD75: Search LinkedIn | AE75: Round 4 | AF75: Not contacted | AK75: =IF(AG75="","",WORKDAY(AG75,5))
A76: Germany | B76: 75 | C76: 4 | D76: DIY & Tools | E76: fischerwerke GmbH & Co. KG | F76: A - Strong (household name) | G76: https://www.fischer.de | H76: Waldachtal | J76: EU / Europe | K76: Higher | L76: Klaus-Fischer-Straße 1, 72178 Waldachtal | M76: +49 7443 120 | O76: Brand owner / manufacturer | P76: fischer wall plugs, anchors & fixings; fischertechnik | Q76: Fixings & fasteners | R76: Account based | S76: Dealers via 50 subsidiaries & importers | T76: Has fischer UK subsidiary | U76: Unknown | V76: Unknown | X76: Exports to 120+ countries; Nordic Swan licensed | Y76: Fixings kits sell well | AA76: Wikipedia + company press texts | AB76: PASS - well-known company: fischer - world-leading German fixings manufacturer (120+ countries). | AC76: Source link | AD76: Search LinkedIn | AE76: Round 4 | AF76: Not contacted | AK76: =IF(AG76="","",WORKDAY(AG76,5))
A77: Germany | B77: 76 | C77: 4 | D77: DIY & Tools | E77: GARDENA Deutschland GmbH (Husqvarna Group) | F77: A - Strong (household name) | G77: https://www.gardena.com | H77: Ulm | J77: EU / Europe | K77: Higher | L77: Hans-Lorenser-Str. 40, 89079 Ulm | M77: +49 731 490-0 | N77: service@gardena.com | O77: Brand owner | P77: GARDENA hoses, watering, garden tools, robotic mowers | Q77: Garden tools & watering | R77: Account based | S77: Dealers & retailers | T77: Husqvarna UK handles UK - ask | U77: Unknown | V77: Unknown | X77: Part of Husqvarna Group since 2007 | Y77: Strong Amazon garden brand | AA77: Business directory + manuals | AB77: PASS - established brand / group | AC77: Source link | AD77: Search LinkedIn | AE77: Round 4 | AF77: Not contacted | AK77: =IF(AG77="","",WORKDAY(AG77,5))
A78: Germany | B78: 77 | C78: 4 | D78: DIY & Tools | E78: KNIPEX-Werk C. Gustav Putsch KG | F78: A - Strong (household name) | G78: https://www.knipex.com | H78: Wuppertal | J78: EU / Europe | K78: Higher | L78: Oberkamper Str. 13, 42349 Wuppertal | M78: +49 202 4794-0 | N78: info@knipex.de | O78: Brand owner / manufacturer | P78: KNIPEX pliers, Cobra, wire strippers | Q78: Professional hand tools | R78: Authorised dealer | S78: Specialist tool distributors (100 countries) | T78: Ask - UK distribution exists | U78: Unknown | V78: Unknown | X78: Exhibitor at SHK Essen, Light+Building, Intersolar; ~60% export | Y78: KNIPEX Cobra pliers are top sellers; brand may be gated | Z78: Premium brand - check Amazon brand gating first | AA78: Multiple trade fair listings + industry directory | AB78: PASS - major trade-fair exhibitor | AC78: Source link | AD78: Search LinkedIn | AE78: Round 4 | AF78: Not contacted | AK78: =IF(AG78="","",WORKDAY(AG78,5))
A79: Germany | B79: 78 | C79: 4 | D79: DIY & Tools | E79: Wera Werkzeuge GmbH | F79: A - Strong (household name) | G79: https://www.wera.de | H79: Wuppertal | J79: EU / Europe | K79: Higher | L79: Wuppertal | M79: +49 202 4045-322 | N79: info@wera.de | O79: Brand owner / manufacturer | P79: Wera screwdrivers, bits, ratchets, Kraftform | Q79: Professional hand tools | R79: Account based | S79: Distributors & dealers | T79: Yes - Wera Tools UK Ltd (queries@wera-tools.co.uk) | U79: Unknown | V79: Unknown | X79: Premium German tool brand with UK subsidiary | Y79: Wera sells very well on Amazon UK | Z79: Use Wera Tools UK. | AA79: Distributor catalogue (2018) | AB79: PASS - established brand / group | AC79: Source link | AD79: Search LinkedIn | AE79: Round 4 | AF79: Not contacted | AK79: =IF(AG79="","",WORKDAY(AG79,5))
A80: Germany | B80: 79 | C80: 4 | D80: DIY & Tools | E80: Wiha Werkzeuge GmbH | F80: A - Strong (household name) | G80: https://www.wiha.com | H80: Schonach (Black Forest) | J80: EU / Europe | K80: Higher | L80: Schonach | M80: +49 7722 959-0 | N80: info.de@wiha.com | O80: Brand owner / manufacturer | P80: Wiha screwdrivers, VDE insulated tools, bits | Q80: Professional hand tools | R80: Account based | S80: Distributors (separate export order desk) | T80: Ask - regional offices (Benelux, Finland, Italy) | U80: Unknown | V80: Unknown | X80: Family-owned premium tool maker; Wikipedia entry | AA80: Company catalogue + Wikipedia | AB80: PASS - well-known company: Major German hand-tool manufacturer. | AC80: Source link | AD80: Search LinkedIn | AE80: Round 4 | AF80: Not contacted | AK80: =IF(AG80="","",WORKDAY(AG80,5))
A81: Germany | B81: 80 | C81: 4 | D81: DIY & Tools | E81: kwb Germany GmbH (Einhell group) | F81: B - Moderate | G81: https://www.kwb.eu | H81: Stuhr (near Bremen) | J81: EU / Europe | K81: Higher | L81: Hauptstraße 132, 28816 Stuhr | M81: +49 421 8994-0 | N81: welcome@kwb.eu | O81: Trading & service company | P81: kwb power-tool accessories (drill bits, saw blades, abrasives) & hand tools | Q81: Tool accessories | R81: On request | S81: DIY stores & tool retailers (has e-commerce sales team) | T81: Ask - has UK catalogue | U81: Unknown | V81: Unknown | X81: Part of Einhell group; MD Markus Vieler | Y81: Accessories are small/light - good FBA economics | AA81: Company catalogues + website | AB81: PASS - established brand / group | AC81: Source link | AD81: Search LinkedIn | AE81: Round 3 | AF81: Not contacted | AK81: =IF(AG81="","",WORKDAY(AG81,5))
A82: Germany | B82: 81 | C82: 4 | D82: DIY & Tools | E82: Scheppach GmbH | F82: B - Moderate | G82: https://www.scheppach.com | H82: Ichenhausen (Bavaria) | J82: EU / Europe | K82: Higher | L82: Günzburger Str. 69, 89335 Ichenhausen | M82: +49 8223 4002-0 | N82: info@scheppach.com | O82: Manufacturer & trading company | P82: Scheppach woodworking machines, garden & workshop tools | Q82: Workshop & garden machines | R82: On request | S82: Dealers & retailers | T82: Ask | U82: Unknown | V82: Unknown | X82: Founded 1927; Bayern International company database | Y82: Bulky machines = high FBA fees; smaller tools fine | AA82: State trade database + registry profile | AB82: PASS - company register entry | AC82: Source link | AD82: Search LinkedIn | AE82: Round 4 | AF82: Not contacted | AK82: =IF(AG82="","",WORKDAY(AG82,5))
A83: Germany | B83: 82 | C83: 3 | D83: DIY & Tools | E83: GÜDE GmbH & Co. KG | F83: B - Moderate | G83: https://www.guede.com | H83: Wolpertshausen (Baden-Württemberg) | J83: EU / Europe | K83: Higher | L83: Wolpertshausen (HQ on A6 Heilbronn-Nuremberg) | O83: Brand owner / wholesaler | P83: GÜDE workshop machines, compressors, garden & power tools | Q83: Workshop & garden tools | R83: On request | S83: Specialist retailers, DIY stores, mail-order (5,000+ traders) | T83: European subsidiaries - ask | U83: Unknown | V83: Unknown | X83: Supplies 5,000+ traders across Europe | AA83: Logistics-partner case study + job listings | AB83: PASS - well-known company: Established German tools & machinery brand. | AC83: Source link | AD83: Search LinkedIn | AE83: Round 4 | AF83: Not contacted | AK83: =IF(AG83="","",WORKDAY(AG83,5))
A84: Germany | B84: 83 | C84: 3 | D84: DIY & Tools | E84: wolfcraft GmbH | F84: B - Moderate | G84: https://www.wolfcraft.com | H84: Kempenich (Eifel) | J84: EU / Europe | K84: Higher | L84: Wolffstraße 1, Kempenich | O84: Brand owner / manufacturer | P84: wolfcraft clamps, workbenches, drill stands, tool accessories | Q84: DIY accessories | R84: On request | S84: Hardware & specialist retailers | T84: 70% export; distribution partners worldwide - ask | U84: Unknown | V84: Unknown | X84: Offices in AT, FR, IT, ES | Y84: Popular DIY accessory brand | AA84: Company directory + retailer pages | AB84: PASS - well-known company: Established German DIY tool maker (50 countries). | AC84: Source link | AD84: Search LinkedIn | AE84: Round 3 | AF84: Not contacted | AK84: =IF(AG84="","",WORKDAY(AG84,5))
A85: Germany | B85: 84 | C85: 3 | D85: Fragrance | E85: Emporium Handels & Vertriebs GmbH (B&S Group) | F85: A - Strong (household name) | G85: Not confirmed - click to search | H85: Rodenbach (near Hanau) | J85: EU / Europe | K85: Higher | L85: Industriestr. 15, 63517 Rodenbach | O85: Wholesaler | P85: 8,000+ perfume & cosmetics products | Q85: Designer fragrance / cosmetics | R85: On request | S85: Trade only | T85: Check | U85: Unknown | V85: Unknown | X85: Part of B&S Group (listed Dutch distributor); one of the leading DACH perfume wholesalers | Z85: Parfumtrend listed at same address. | AA85: Job listing + directory - find website/Impressum | AB85: PASS - established brand / group | AC85: Source link | AD85: Search LinkedIn | AE85: Round 1 | AF85: Not contacted | AK85: =IF(AG85="","",WORKDAY(AG85,5))
A86: Germany | B86: 85 | C86: 4 | D86: Health & Personal Care | E86: Beurer GmbH (Beurer UK Ltd) | F86: A - Strong (household name) | G86: https://www.beurer.com/uk/facts/ | H86: Ulm (HQ); UK office Lowton | J86: EU / Europe | K86: Higher | L86: Söflinger Str. 218, 89077 Ulm / UK: Suite 16, Stonecross Place, Lowton WA3 2SH | M86: +49 731 3989-0 | O86: Brand owner with UK subsidiary | P86: Beurer BP monitors, thermometers, massagers, scales, TENS, beauty devices | Q86: Health devices | R86: Account based | S86: Online & high-street retailers (Boots, Argos, John Lewis...) | T86: Yes - Beurer UK Ltd | U86: Unknown | V86: Unknown | X86: Founded 1919; BHETA member (UK) | Y86: Huge Amazon health-device brand; check UK account terms | AA86: Company site + BHETA listing | AB86: PASS - established brand / group | AC86: Source link | AD86: Search LinkedIn | AE86: Round 3 | AF86: Not contacted | AK86: =IF(AG86="","",WORKDAY(AG86,5))
A87: Germany | B87: 86 | C87: 3 | D87: Health & Personal Care | E87: MEDISANA AG | F87: A - Strong (household name) | G87: https://www.medisana.de | H87: Neuss | J87: EU / Europe | K87: Higher | L87: Jagenbergstraße 19, 41468 Neuss | M87: +49 2131 3668-0 | N87: info@medisana.de | O87: Brand owner | P87: Medisana BP monitors, inhalers, massagers, scales, heated blankets | Q87: Health devices | R87: On request | S87: Retailers & pharmacies | T87: Ask | U87: Unknown | V87: Unknown | X87: Part of Ogawa Smart Healthcare group | Y87: Also on Qogita (low MOV) | AA87: Business press + directory | AB87: PASS - established brand / group | AC87: Source link | AD87: Search LinkedIn | AE87: Round 3 | AF87: Not contacted | AK87: =IF(AG87="","",WORKDAY(AG87,5))
A88: Germany | B88: 87 | C88: 3 | D88: Health & Personal Care | E88: Kneipp GmbH | F88: B - Moderate | G88: https://www.kneipp.com | H88: Würzburg | J88: EU / Europe | K88: Higher | L88: Winterhäuser Str. 85, 97084 Würzburg | M88: +49 931 8002-0 | O88: Brand owner / manufacturer | P88: Kneipp bath & body care, herbal supplements | Q88: Bath & body / wellness | R88: Account based | S88: Distributors & retailers (18 countries) | T88: Ask | U88: Unknown | V88: Unknown | X88: Bayern International database; sold in US & Japan | Y88: Bath products sell well; liquids may need hazmat review | AA88: State trade database + press release | AB88: PASS - well-known company: Major German bath & wellness brand. | AC88: Source link | AD88: Search LinkedIn | AE88: Round 4 | AF88: Not contacted | AK88: =IF(AG88="","",WORKDAY(AG88,5))
A89: Germany | B89: 88 | C89: 3 | D89: Health & Personal Care | E89: PAUL HARTMANN AG | F89: B - Moderate | G89: https://www.hartmann.info | H89: Heidenheim | J89: EU / Europe | K89: Higher | L89: Paul-Hartmann-Straße 12, 89522 Heidenheim | M89: +49 7321 36-0 | O89: Brand owner / manufacturer (listed) | P89: Hartmann first aid & wound care, Molicare incontinence, Veroval health devices | Q89: First aid & medical consumer | R89: Account based | S89: Distributors in 100+ countries; pharmacies | T89: Has UK subsidiary - ask | U89: Unknown | V89: Unknown | X89: Frankfurt-listed medical group | Y89: First aid & Veroval BP monitors sell well | AA89: Stock exchange profile + chamber directory | AB89: PASS - listed company | AC89: Source link | AD89: Search LinkedIn | AE89: Round 4 | AF89: Not contacted | AK89: =IF(AG89="","",WORKDAY(AG89,5))
A90: Germany | B90: 89 | C90: 3 | D90: Health & Personal Care | E90: Dr. Theiss Naturwaren GmbH | F90: C - Low / little UK demand | G90: https://www.naturwaren-theiss.de | H90: Homburg (Saarland) | J90: EU / Europe | K90: Higher | L90: Michelinstraße 10, 66424 Homburg | M90: +49 6841 7090 | N90: info@naturwaren-theiss.de | O90: Brand owner / manufacturer | P90: Dr. Theiss natural remedies & cosmetics, Allgäuer Latschenkiefer, Lavera (group) | Q90: Natural health & body care | R90: On request | S90: Distributors (MD Giuseppe Nardi leads export) | T90: Ask | U90: Unknown | V90: Unknown | X90: Long-established German pharmacy-brand maker | AA90: Pharma directory + trade press | AB90: PASS - established brand / group | AC90: Source link | AD90: Search LinkedIn | AE90: Round 4 | AF90: Not contacted | AK90: =IF(AG90="","",WORKDAY(AG90,5))
A91: Germany | B91: 90 | C91: 3 | D91: Home & Kitchen | E91: Leifheit AG | F91: A - Strong (household name) | G91: https://www.leifheit.com | H91: Nassau | J91: EU / Europe | K91: Higher | L91: Leifheitstraße 1, 56377 Nassau | O91: Brand owner (listed company) | P91: Leifheit, Soehnle - cleaning, laundry, kitchen, scales | Q91: Household & kitchen | R91: Account based | S91: Mass retail, specialty chains, e-commerce; distribution markets team | T91: Sells in 80+ countries - ask | U91: Unknown | V91: Unknown | X91: Frankfurt-listed household brand | Y91: Brand-direct; very popular on Amazon (may have MAP rules) | AA91: Company profiles + trade data | AB91: PASS - listed company | AC91: Source link | AD91: Search LinkedIn | AE91: Round 3 | AF91: Not contacted | AK91: =IF(AG91="","",WORKDAY(AG91,5))
A92: Germany | B92: 91 | C92: 3 | D92: Home & Kitchen | E92: Wolfsohn | F92: A - Strong (household name) | G92: https://www.ifa-berlin.com/exhibitors/wolfsohn | H92: Germany | J92: EU / Europe | K92: Higher | O92: Branded electronics & household wholesaler | P92: 6,000+ SKUs in stock: Braun, Philips, Samsung, Xiaomi, QCY, PoundMax | Q92: Small appliances & consumer electronics | R92: On request | S92: B2B | T92: Ask | U92: Unknown | V92: Unknown | X92: IFA Berlin exhibitor | AA92: Trade show profile - find Impressum | AB92: PASS (checked) - IFA Berlin exhibitor; 6,000+ branded SKUs in stock. | AC92: Source link | AD92: Search LinkedIn | AE92: Round 2 | AF92: Not contacted | AK92: =IF(AG92="","",WORKDAY(AG92,5))
A93: Germany | B93: 92 | C93: 4 | D93: Home & Kitchen | E93: GEFU GmbH | F93: B - Moderate | G93: https://www.gefu.com | H93: Eslohe (Sauerland) | J93: EU / Europe | K93: Higher | L93: Braukweg 28, 59889 Eslohe | M93: +49 2973 97130 | N93: info@gefu.com | O93: Brand owner | P93: GEFU kitchen tools, spiralizers, pasta makers, gadgets | Q93: Kitchen tools | R93: On request | S93: Retailers (2,000+ stores) & B2B customers | T93: Ask | U93: Unknown | V93: Unknown | X93: Family company; Maison&Objet exhibitor | Y93: Kitchen gadgets largely ungated | AA93: Business press + trade fair | AB93: PASS - major trade-fair exhibitor | AC93: Source link | AD93: Search LinkedIn | AE93: Round 4 | AF93: Not contacted | AK93: =IF(AG93="","",WORKDAY(AG93,5))
A94: Germany | B94: 93 | C94: 4 | D94: Home & Kitchen | E94: SEVERIN Elektrogeräte GmbH | F94: B - Moderate | G94: https://www.severin.com | H94: Sundern (Sauerland) | J94: EU / Europe | K94: Higher | L94: Röhre 27, 59846 Sundern | M94: +49 2933 98 20 | N94: information@severin.de | O94: Brand owner / manufacturer | P94: SEVERIN coffee machines, kettles, toasters, grills, fridges | Q94: Small domestic appliances | R94: Account based | S94: Retailers (5-6 own European sales companies) | T94: EU plugs - check UK versions/subsidiary | U94: Unknown | V94: Unknown | X94: ~€148m turnover; IFA exhibitor; production in DE & CN | AA94: Trade fair + company profiles | AB94: PASS - major trade-fair exhibitor | AC94: Source link | AD94: Search LinkedIn | AE94: Round 4 | AF94: Not contacted | AK94: =IF(AG94="","",WORKDAY(AG94,5))
A95: Germany | B95: 94 | C95: 4 | D95: Home & Kitchen | E95: Westmark GmbH | F95: B - Moderate | G95: https://www.westmark.de | H95: Lennestadt | J95: EU / Europe | K95: Higher | L95: Bielefelder Straße 125, 57368 Lennestadt | M95: +49 2721 92580 | O95: Brand owner / manufacturer | P95: Westmark, Monopol, Saleen - 2,500+ kitchen utensils | Q95: Kitchen utensils | R95: On request | S95: Retailers & distributors | T95: Exports - ask | U95: Unknown | V95: Unknown | X95: Since 1956; Ambiente exhibitor; largely own manufacturing | Y95: Kitchen gadgets are largely ungated on Amazon | AA95: Trade fair directory | AB95: PASS - major trade-fair exhibitor | AC95: Source link | AD95: Search LinkedIn | AE95: Round 3 | AF95: Not contacted | AK95: =IF(AG95="","",WORKDAY(AG95,5))
A96: Germany | B96: 95 | C96: 3 | D96: Home & Kitchen | E96: Clatronic International GmbH | F96: B - Moderate | G96: https://www.clatronic.de | H96: Kempen | J96: EU / Europe | K96: Higher | L96: Kempen (sister trading company C. Bomann GmbH, Kempen) | O96: Brand owner (appliances) | P96: Clatronic, Bomann, ProfiCook, ProfiCare small & large appliances | Q96: Household appliances | R96: On request | S96: Retailers & B2B | T96: EU plugs - check UK versions | U96: Unknown | V96: Unknown | X96: Family business since 1982; ~100 staff in Germany | Y96: Popular budget appliance brands on Amazon EU | AA96: Business registry profile (C. Bomann) | AB96: PASS - company register entry | AC96: Source link | AD96: Search LinkedIn | AE96: Round 4 | AF96: Not contacted | AK96: =IF(AG96="","",WORKDAY(AG96,5))
A97: Germany | B97: 96 | C97: 5 | D97: Pet Supplies | E97: TRIXIE Heimtierbedarf (incl. Trixie UK Pet Product Ltd) | F97: A - Strong (household name) | G97: https://www.trixie.de | H97: Tarp (DE); UK warehouse | I97: UK | J97: EU / Europe | K97: Higher | L97: Tarp, Schleswig-Holstein; UK warehouse (opened Dec 2025) | M97: +44 20 7154 2940 (UK - verify) | N97: sales@trixie.de | O97: Brand owner selling direct to retailers | P97: TRIXIE - 6,000+ pet accessories, toys, beds, treats; exports to 80+ countries | Q97: Pet accessories & treats | R97: On request | S97: Retailers / resellers (own UK sales team) | T97: Yes - UK entity + UK warehouse | U97: Unknown | V97: Unknown | X97: Major European pet accessories brand; Interzoo exhibitor | Y97: Brand-direct invoices; very popular Amazon brand | AA97: Trade press + trade directory | AB97: PASS - major trade-fair exhibitor | AC97: Source link | AD97: Search LinkedIn | AE97: Round 2 | AF97: Not contacted | AK97: =IF(AG97="","",WORKDAY(AG97,5))
A98: Germany | B98: 97 | C98: 4 | D98: Pet Supplies | E98: Albert Kerbl GmbH | F98: B - Moderate | G98: https://www.kerbl.com | H98: Buchbach (Bavaria) | J98: EU / Europe | K98: Higher | L98: Felizenzell 9, 84428 Buchbach | M98: +49 8086 933-100 | N98: info@kerbl.de (UK: enquiries@kerbl.co.uk) | O98: Wholesaler & manufacturer | P98: Kerbl pet accessories, grooming, small-animal, chew toys + farm/equestrian | Q98: Pet accessories | R98: On request | S98: Retailers | T98: Yes - Kerbl UK (Oakham) | U98: Unknown | V98: Unknown | X98: Interzoo exhibitor; subsidiaries in AT, FR, UK | Y98: Brand-direct invoices; UK arm removes import hassle | AA98: Company product docs + trade show | AB98: PASS - major trade-fair exhibitor | AC98: Source link | AD98: Search LinkedIn | AE98: Round 3 | AF98: Not contacted | AK98: =IF(AG98="","",WORKDAY(AG98,5))
A99: Germany | B99: 98 | C99: 4 | D99: Pet Supplies | E99: H. von Gimborn GmbH (GimCat, GimDog, Biokat's) | F99: B - Moderate | G99: https://www.gimborn.eu | H99: Emmerich am Rhein | J99: EU / Europe | K99: Higher | L99: Albert-Einstein-Straße 6, 46446 Emmerich am Rhein | M99: +49 2822 9640 | N99: info@gimborn.de | O99: Brand owner / manufacturer | P99: GimCat, GimDog snacks & care, Biokat's cat litter | Q99: Pet treats & litter | R99: On request | S99: Retailers & distributors | T99: Ask | U99: Unknown | V99: Unknown | X99: Founded 1855; own factory since 1965; Interzoo exhibitor; LEI registered | AA99: Trade fair + business press | AB99: PASS - company register entry | AC99: Source link | AD99: Search LinkedIn | AE99: Round 4 | AF99: Not contacted | AK99: =IF(AG99="","",WORKDAY(AG99,5))
A100: Germany | B100: 99 | C100: 4 | D100: Pet Supplies | E100: HUNTER International GmbH | F100: B - Moderate | G100: https://www.hunter.de | H100: Bielefeld | J100: EU / Europe | K100: Higher | L100: Mittelbreede 5, 33719 Bielefeld | M100: +49 521 16399-500 | N100: info@hunter.de | O100: Brand owner (B2B shop for retailers) | P100: HUNTER, stylecats, KESSI - collars, leads, beds, cat accessories | Q100: Pet accessories | R100: On request | S100: Trade customers - B2B shop b2b.hunter.de | T100: Yes - HUNTER UK (Knipton, Lincs) | U100: Unknown | V100: Unknown | X100: Interzoo exhibitor; long-established German brand | Y100: Brand-direct invoices | AA100: Company document + trade show | AB100: PASS - major trade-fair exhibitor | AC100: Source link | AD100: Search LinkedIn | AE100: Round 3 | AF100: Not contacted | AK100: =IF(AG100="","",WORKDAY(AG100,5))
...

Sheet Low Priority
A1: Low Priority suppliers (priority 1-2) - reference only
A2: 42 suppliers moved off the main Suppliers tab: weak Amazon fit, marketplaces/retailers, or capped after the scam check. Work the main list first; vet these carefully before paying.
A4: Country | B4: Category | C4: Priority | D4: Company | E4: Website | F4: Phone | G4: Email | H4: Supplier Type | I4: Key Brands | J4: Why low priority / notes | K4: Scam Check | L4: Source
A5: Austria | B5: Sports & Outdoors | C5: 2 | D5: SWAROVSKI OPTIK Vertriebs GmbH | E5: https://www.swarovskioptik.com | F5: +43 5223 511-0 | G5: info@swarovskioptik.com | H5: Brand owner / manufacturer | I5: Swarovski Optik binoculars, scopes | J5: Selective distribution - Amazon resale may be restricted; High-ticket, low volume; brand control is strict | K5: PASS - established brand / group | L5: https://swarovskioptik.com/ch/en/hunting/about-us/quality-and-innovation/facts-and-figures
A6: Belgium | B6: Beauty | C6: 2 | D6: Euro Cosmetic | E6: https://www.eurocosmetic.be | F6: +32 472 ... (see website) | H6: Distributor / wholesaler | I6: Cosmetic brands (salons & retailers) | K6: CAUTION - Likely Eurocosmetics & Accessoires BVBA (BE0479.392.014) - confirm before ordering. | L6: https://oncosmetics.com/company/eurocosmetic-international/
A7: Bulgaria | B7: Baby Products | C7: 2 | D7: Iventas | E7: https://bulmedica.bg/en/main/iventas-2/ | H7: Importer / national distributor | I7: Philips AVENT, Philips Sonicare, Tommee Tippee + others | K7: CAUTION - Details only from its own page - verify in the Bulgarian Commercial Register. | L7: https://bulmedica.bg/en/main/iventas-2/
A8: Czech Republic | B8: Pet Supplies | C8: 2 | D8: Samohýl Group | E8: https://samohyl.cz/?lang=en | H8: Wholesaler / exclusive distributor | I8: Exclusive CZ distributor for ~20 brands incl. KONG | K8: PASS (checked) - Listed among Forbes Czech's largest family firms (2026); vet wholesaler since 1991. | L8: https://samohyl.cz/?lang=en
A9: Czech Republic | B9: Toys & Games | C9: 2 | D9: Teddies s.r.o. | H9: Toy importer / wholesaler | I9: Teddies plush & toys range (sold via Alza etc.) | K9: PASS (checked) - Registered (IČ 28268164); no insolvency found. | L9: https://www.emis.cn/php/company-profile/CZ/Teddies_SRO_en_6714203.html
A10: France | B10: B2B Marketplace | C10: 2 | D10: Ankorstore | E10: https://www.ankorstore.com | H10: Wholesale marketplace (independent brands) | I10: ~30,000 independent brands - beauty, toys, gifts, home | J10: 60-day payment terms.; CAUTION: many brands prohibit marketplace resale - check each brand | K10: PASS - well-known company: Major VC-backed European wholesale marketplace. | L10: https://alven.co/news/ankorstore-reaches-unicorn-status-in-only-two-years-with-its-last-e250-million-series-c-funding-round
A11: France | B11: B2B Marketplace | C11: 2 | D11: Stocklear | E11: https://www.stocklear.com | H11: B2B auction marketplace (overstock & returns) | I11: Non-food overstock & returns from retailers like Carrefour, Leroy Merlin, Decathlon | J11: Same caution as other liquidation - condition varies | K11: PASS (checked) - VC-backed French B2B auction platform (escrow payments). | L11: https://app.dealroom.co/companies/stocklear_1
A12: France | B12: Beauty | C12: 2 | D12: CSP Cosmetics | E12: https://www.cspcosmetics.com | F12: +33 7 53 39 50 23 | H12: Wholesale distributor | I12: The Ordinary, CeraVe, Cetaphil (claims authorised) | J12: CeraVe / The Ordinary are huge Amazon sellers but heavily counterfeited - demand authorisation proof | K12: CAUTION - Real company (SIREN 904632312, ~EUR 36m revenue) but loss-making with negative equity - avoid large prepayments. | L12: https://oncosmetics.com/company/csp-cosmetics/
A13: Germany | B13: Fragrance | C13: 2 | D13: NOBILIS Group GmbH | H13: Authorised brand distributor | I13: Lacoste (DACH), Xerjoff, Casamorati + prestige & lifestyle fragrances | J13: Long-term target once you have a track record.; Authorised distributor - best invoice quality but selective about accounts | K13: PASS (checked) - Major DACH fragrance distributor; co-owned by Gebr. Heinemann; Lacoste & Elizabeth Arden contracts. | L13: https://fashionunited.de/nachrichten/business/lacoste-gibt-parfum-vertrieb-fuer-dach-region-an-die-nobilis-group-ab/2024010554623
A14: Germany | B14: Health & Personal Care | C14: 2 | D14: IHTCT GmbH | E14: https://www.odoo.com/ar/customers/ihtct-gmbh-6263453 | H14: Licensed pharma & healthcare distributor (export B2B) | I14: Healthcare products, medical devices, beauty & skincare, baby, toys | K14: CAUTION - Self-described licensed pharma wholesaler - ask for the wholesale licence and HRB number. | L14: https://www.odoo.com/ar/customers/ihtct-gmbh-6263453
A15: Germany | B15: Toys & Games | C15: 2 | D15: Landahl & Baumann Spielwaren GmbH | H15: Toy wholesaler | I15: Branded toys - Europe-wide | K15: PASS (checked) - ~50 staff licensed-toy wholesaler; no insolvency found. | L15: https://www.ausbildung.de/unternehmen/landahl-baumann-spielwaren-gmbh/stellen/
A16: Ireland | B16: Beauty | C16: 1 | D16: Xpert Professional | E16: https://www.irishbeauty.ie/Xpert-Professional-expand-Olaplex-distribution.html | H16: Professional haircare distributor | I16: Olaplex (IE, Scotland, SE England), Alfaparf, Joico, R+Co, Moroccanoil | J16: Listed for reference - unlikely to supply Amazon sellers.; CAUTION: pro brands usually prohibit Amazon resale | K16: PASS (checked) - Olaplex distributor for Ireland since 2015; trading since 1997. | L16: https://www.irishbeauty.ie/Xpert-Professional-expand-Olaplex-distribution.html
A17: Italy | B17: B2B Marketplace | C17: 2 | D17: Brandsdistribution | E17: https://www.brandsdistribution.com | F17: +39 011 198 292 34 | H17: B2B fashion wholesale / dropship | I17: 120+ fashion brands: clothing, shoes, bags, accessories | J17: Fashion rather than core niches. | K17: PASS (checked) - Established Turin B2B platform (IDT S.p.A.), 450k+ registered retailers. | L17: https://www.cbinsights.com/company/brandsdistributioncom/
A18: Italy | B18: Fragrance | C18: 2 | D18: Profumerie P & P Srl | E18: https://www.profumeriepep.it | H18: Wholesaler + retail | I18: Perfumes | K18: CAUTION - Real company (~EUR 6.5m revenue) but registered as a perfume RETAILER - check invoices meet Amazon rules. | L18: https://atoka.io/public/it/azienda/profumerie-p-p-srl/b936935a4339
A19: Italy | B19: Toys & Games | C19: 2 | D19: Joy Toy SpA | H19: Licensed toy distributor | I19: Licensed toys & plush (30 years) | J19: Contact direct - not via Faire (Faire bans Amazon sellers) | K19: PASS (checked) - Licensed-goods specialist since 1989; no insolvency found. | L19: https://faire.com/brand/b_th6zdpbbr9
A20: Lithuania | B20: DIY & Tools | C20: 2 | D20: Doho | E20: https://linkedin.com/company/do-ho | H20: Retailer & wholesaler | I20: Bosch, Makita, DeWalt, Metabo, Stanley | J20: Small firm - verify. | K20: CAUTION - Founded 2019 retailer; Lithuanian registration code not found - retailer invoices may not suit Amazon. | L20: https://linkedin.com/company/do-ho
A21: Netherlands | B21: Fragrance | C21: 2 | D21: B&S Group (B&S Beauty) | F21: +352 26870881 (Luxembourg) | H21: Large distributor | I21: Beauty, personal care, health, food, liquor - major fragrance distributor | J21: Major player - better for later scale | K21: PASS - well-known company: Euronext-listed distribution group. | L21: https://www.morningstar.com.au/investments/security/fra/70B
A22: Netherlands | B22: Fragrance | C22: 2 | D22: Beautinow B.V. | E22: https://beautinow.com/wholesale-perfume-supplier-europe/ | F22: +31 684 714 856 (WhatsApp - verify) | G22: via website wholesale form | H22: Wholesaler + online retailer | I22: 2,000+ fragrances, 200+ designer & niche brands | J22: Also offers dropshipping | K22: CAUTION - Parallel importer; Trustpilot 3.8 but some reports of non-delivery and a suspected counterfeit (2025). Small test order only. | L22: https://beautinow.com/wholesale-perfume-supplier-europe/
A23: Netherlands | B23: General Wholesale / FMCG | C23: 2 | D23: METRO / Makro (EU cash & carry) | E23: https://www.makro.nl | H23: Cash & carry | I23: FMCG, household, H&B, toys, electronics | J23: Useful for Amazon EU sellers | K23: PASS - established brand / group | L23: https://help.makro.nl/en/support/solutions/articles/77000586989-can-i-use-a-foreign-makro-or-metro-card-
A24: Netherlands | B24: Health & Personal Care | C24: 2 | D24: Topbrands | E24: https://www.topbrands.nl | G24: via contact form | H24: A-brand stock-lot trader | I24: 160m+ A-brand items from 200+ manufacturers: personal care, home care, confectionery | J24: Target later when volumes grow.; Stock lots - check expiry/packaging condition | K24: PASS (checked) - Trading since 2002; offices in 5 EU countries; supplies large retail chains. | L24: https://www.topbrands.nl/faq/
A25: Netherlands | B25: Health & Personal Care | C25: 2 | D25: Van der Tang Trading (cosmeticapartijen.nl) | E25: https://www.cosmeticapartijen.nl | H25: Drugstore goods wholesaler | I25: Baby care, hair, makeup, oral hygiene, skincare - branded drugstore lots | J25: Stock lots - check dates & packaging | K25: PASS (checked) - Established family drugstore wholesaler (11-50 staff); no complaints found. | L25: https://oncosmetics.com/company/van-der-tang-trading/
A26: Netherlands | B26: Pet Supplies | C26: 2 | D26: Papillon Pet Products B.V. | E26: https://www.papillonpetproducts.com | F26: +31 162 311 109 | G26: info@papillonpetproducts.com | H26: Importer / distributor | I26: Papillon pet accessories (mainly imported) | K26: PASS (checked) - Interzoo & Zoomark 2025 exhibitor; exports to 30 countries. | L26: https://www.interzoo.com/en/exhibitors/papillon-pet-products-bv-2227601
A27: Netherlands | B27: Toys & Games | C27: 2 | D27: Bellus Toys B.V. | E27: https://iaapa.org/partners/marketplace/bellus-toys-bv | H27: Toy wholesaler | I27: Plush & small toys | K27: CAUTION - Small (since 2015), mainly vending/capsule toys - low Amazon fit. | L27: https://iaapa.org/partners/marketplace/bellus-toys-bv
A28: Netherlands | B28: Toys & Games | C28: 2 | D28: Channel Distribution B.V. | E28: https://www.channeldistribution.nl | F28: +31 512 570 050 | H28: Gifts & gadgets wholesaler | I28: Gifts, gadgets, novelty | K28: PASS (checked) - Since 2014; own 4,500 m² warehouse; exclusive Benelux brand agencies. | L28: https://www.ampliz.com/company/channel-distribution-bv/90357002
A29: Poland | B29: B2B Marketplace | C29: 1 | D29: Merkandi | E29: https://merkandi.com | H29: Stock-lot / liquidation marketplace | I29: Overstock, clearance, returns (mixed condition) | J29: CAUTION: filter for 'New' grade only; vet each seller | K29: CAUTION - Platform is real but sellers are third parties - vet every seller separately. | L29: https://tr-web.dev.trustradius.com/products/merkandi-com
A30: Poland | B30: DIY & Tools | C30: 2 | D30: Alpex-Tools | H30: Tools wholesaler | I30: Tools, power tools, welding & abrasives | K30: PASS (checked) - Trading since 1993; NIP 9562331451. | L30: https://www.aplikuj.pl/pracodawca/159889/alpex-tools/opinie
A31: Poland | B31: Health & Personal Care | C31: 2 | D31: Profimed | H31: Oral care distributor | I31: 7+ global professional oral care brands (CEE) | K31: PASS (checked) - CEDE dental fair exhibitor; TePe distributor in Central Europe. | L31: https://www.cede.pl/2019/en/exhibition/exhibitors-catalogue/?exh=5799
A32: Poland | B32: Pet Supplies | C32: 2 | D32: Hurtowniakarm.pl | E32: https://hurtowniakarm.pl | H32: Pet food wholesaler | I32: Pet food brands | K32: PASS (checked) - Registered Sp. z o.o. (NIP 9372759476); Google 4.9/5 from 126 reviews. | L32: https://business.google.com/v/_/08939480399253784979/a394/_
A33: Poland | B33: Sports & Outdoors | C33: 2 | D33: Marba-Sport (e-hurtowniasportowa.pl) | E33: https://e-hurtowniasportowa.pl | H33: Sports wholesaler & manufacturer | I33: Sports & tourism equipment | K33: PASS (checked) - Wholesaler since 1991; Decathlon marketplace seller. | L33: https://www.pracuj.pl/praca/specjalista-specjalistka-ds-obslugi-klienta-b2b-miszewko-pow-kartuski-gdynska-69a,oferta,1003183320
A34: Poland | B34: Toys & Games | C34: 2 | D34: Hurtownia Ikonka | E34: https://ikonka.pl | H34: Wholesaler + dropshipping | I34: Toys, electronics, kids' goods, home (mostly imported unbranded) | J34: Mostly generic goods - check for brand registry / listing ownership issues | K34: CAUTION - Only self-published claims found - check NIP on the Polish VAT whitelist. | L34: https://www.aplikuj.pl/pracodawca/412938/hurtownia-ikonka
A35: Spain | B35: Baby Products | C35: 2 | D35: Smart Baby Brands | H35: Official distributor | I35: Joie, Joie Signature, Nuna, Tavo | J35: Useful for Amazon.es; not for UK.; Territorial distributor - UK rights belong to Joie UK | K35: PASS (checked) - Official Joie distributor for Spain/Portugal since 2014 (trade press). | L35: https://www.interempresas.net/Puericultura/609658-Smart-Baby-Brands-se-refuerza-en-Espana-y-Portugal.html
A36: Spain | B36: Baby Products | C36: 2 | D36: Tata Batata | H36: Distributor | I36: Mid-high end nursery & baby furniture brands | K36: CAUTION - Only directory information (2-10 staff) - confirm registration. | L36: https://www.arounddeal.com/c/tata-batata/e1vibvmjrt
A37: Spain | B37: Toys & Games | C37: 2 | D37: Bizak S.A. | E37: https://www.bizak.es | F37: +34 944 34 190 (verify) | H37: Toy brand & distributor | I37: Bizak + distributed brands (Salta Pirata etc.) | K37: PASS - company register entry | L37: https://www.iberinform.es/empresa/17738/bizak
A38: Spain | B38: Toys & Games | C38: 2 | D38: Nomaco Spain | F38: +34 917 462 601 | H38: Wholesale distributor | I38: Meccano, Crayola, Nikko, Bontempi, Welly, K's Kids | K38: PASS (checked) - Toy wholesaler since 2007; supplies El Corte Inglés, Carrefour, Alcampo. | L38: https://proveedores.com/proveedores/nomaco/
A39: UK | B39: Beauty | C39: 2 | D39: Aston & Fincher | E39: https://www.astonandfincher.co.uk | H39: Hair & beauty trade wholesaler | I39: Professional hair, beauty, barbering & nail brands | J39: Better for beauty consumables than gated pro brands.; CAUTION: many pro brands forbid online/Amazon resale - check per brand | K39: PASS (checked) - Companies House 00970902 active; trading since 1959; 34 stores. | L39: https://www.astonandfincher.co.uk/pages/new-customers
A40: UK | B40: Beauty | C40: 2 | D40: Capital Hair & Beauty | E40: https://www.capitalhairandbeauty.co.uk | F40: +44 330 094 0450 (verify) | H40: Hair & beauty trade wholesaler | I40: Professional hair & beauty | J40: Same caution as other pro-beauty suppliers | K40: PASS (checked) - Companies House 00530201 active. | L40: https://pay.company-information.service.gov.uk/company/00530201
A41: UK | B41: Beauty | C41: 2 | D41: Exquisite Cosmetics Ltd | E41: https://www.exquisitecosmetics.co.uk | H41: Wholesaler | I41: Makeup and skincare | K41: PASS (checked) - Companies House 01315797 active since 1977. | L41: https://pay.company-information.service.gov.uk/company/01315797
A42: UK | B42: General Wholesale / FMCG | C42: 2 | D42: Wholesale Clearance UK | E42: https://www.wholesaleclearance.co.uk | H42: Clearance / surplus wholesaler | I42: Branded clearance & surplus | J42: CAUTION: clearance stock may be damaged/expired - check condition | K42: PASS (checked) - Trustpilot 4.5/5 from 261 reviews; replies to all negative reviews. | L42: https://wholesalehelper.io/es/blog/Los-10-principales-proveedores-mayoristas-del-Reino-Unido/
A43: UK | B43: Health & Personal Care | C43: 2 | D43: Kinetic Natural Product Distributor (Kinetic Enterprises Ltd) | E43: https://www.kinetic4health.co.uk | H43: Distributor | I43: Natural & organic beauty, nutrition, superfoods | J43: Ask about online-seller policy | K43: PASS (checked) - Active company (02565441) with LEI; trading since 1990. | L43: https://cosmeticsbusiness.com/kinetic-natural-products-distributor-120192
A44: UK | B44: Health & Personal Care | C44: 2 | D44: Suma Wholefoods | E44: https://www.suma.coop | H44: Wholesaler (co-op) | I44: Natural/organic food, health & eco beauty/household | K44: PASS - well-known company: Large UK wholefood co-operative wholesaler (since 1977). | L44: https://de.trustpilot.com/review/www.suma.coop?page=3
A45: Pan-European / Online | B45: B2B Marketplace | C45: 2 | D45: B-Stock - Amazon EU Liquidation Auctions | E45: https://bstock.com/amazoneu/about/ | H45: Official Amazon liquidation auction marketplace | I45: Amazon EU/UK customer returns, overstock & salvage - electronics, toys, home, sports, pets, office | J45: CAUTION: returns can't be sold as 'New' on Amazon - grade carefully, resell as Used/elsewhere | K45: PASS - well-known company: Amazon's official liquidation partner. | L45: https://bstock.com/amazoneu/about/
A46: Pan-European / Online | B46: B2B Marketplace | C46: 1 | D46: Faire | E46: https://www.faire.com | H46: Wholesale marketplace | I46: 100,000+ brands incl. Bigjigs Toys | J46: Listed so you know to avoid it for Amazon.; NOT SUITABLE: Faire states it cannot fulfil orders for retailers selling on Amazon/eBay/Etsy | K46: CAUTION - Legitimate, but bans Amazon sellers - contact brands directly instead. | L46: https://faire.com/support/articles/29881314074139

Sheet LinkedIn Outreach
A1: Country | B1: ID | C1: Company | D1: Category | E1: Company Page Search | F1: Find Sales / Account Managers | G1: Person Name | H1: Job Title | I1: Profile URL | J1: Connection Sent | K1: Accepted? | L1: Message Sent | M1: Reply? | N1: Notes
A2: =Suppliers!A2 -> Austria | B2: =Suppliers!B2 -> 1 | C2: =Suppliers!E2 -> KORES GmbH | D2: =Suppliers!D2 -> Stationery & Office | E2: Company page | F2: Find people
A3: =Suppliers!A3 -> Austria | B3: =Suppliers!B3 -> 2 | C3: =Suppliers!E3 -> Stadlbauer Marketing + Vertrieb GmbH | D3: =Suppliers!D3 -> Toys & Games | E3: Company page | F3: Find people
A4: =Suppliers!A4 -> Austria | B4: =Suppliers!B4 -> 3 | C4: =Suppliers!E4 -> Wiener Spielkartenfabrik Ferd. Piatnik & Söhne | D4: =Suppliers!D4 -> Toys & Games | E4: Company page | F4: Find people
A5: =Suppliers!A5 -> Belgium | B5: =Suppliers!B5 -> 4 | C5: =Suppliers!E5 -> Varo (Vic Van Rompuy NV) | D5: =Suppliers!D5 -> DIY & Tools | E5: Company page | F5: Find people
A6: =Suppliers!A6 -> Belgium | B6: =Suppliers!B6 -> 5 | C6: =Suppliers!E6 -> Beautylux | D6: =Suppliers!D6 -> Fragrance | E6: Company page | F6: Find people
A7: =Suppliers!A7 -> Belgium | B7: =Suppliers!B7 -> 6 | C7: =Suppliers!E7 -> Galico NV | D7: =Suppliers!D7 -> Home & Kitchen | E7: Company page | F7: Find people
A8: =Suppliers!A8 -> Belgium | B8: =Suppliers!B8 -> 7 | C8: =Suppliers!E8 -> Savic NV | D8: =Suppliers!D8 -> Pet Supplies | E8: Company page | F8: Find people
A9: =Suppliers!A9 -> Belgium | B9: =Suppliers!B9 -> 8 | C9: =Suppliers!E9 -> Flamingo Pet Products NV | D9: =Suppliers!D9 -> Pet Supplies | E9: Company page | F9: Find people
A10: =Suppliers!A10 -> Belgium | B10: =Suppliers!B10 -> 9 | C10: =Suppliers!E10 -> Laroy Group (Duvo+) | D10: =Suppliers!D10 -> Pet Supplies | E10: Company page | F10: Find people
A11: =Suppliers!A11 -> Belgium | B11: =Suppliers!B11 -> 10 | C11: =Suppliers!E11 -> Moderna Products NV | D11: =Suppliers!D11 -> Pet Supplies | E11: Company page | F11: Find people
A12: =Suppliers!A12 -> Belgium | B12: =Suppliers!B12 -> 11 | C12: =Suppliers!E12 -> Vadigran NV | D12: =Suppliers!D12 -> Pet Supplies | E12: Company page | F12: Find people
A13: =Suppliers!A13 -> Bulgaria | B13: =Suppliers!B13 -> 12 | C13: =Suppliers!E13 -> Bulgarian Rose AD (Bulgarska Roza Karlovo) | D13: =Suppliers!D13 -> Beauty | E13: Company page | F13: Find people
... A359: =Suppliers!A359 -> UK | B359: =Suppliers!B359 -> 358 | C359: =Suppliers!E359 -> Puckator Ltd | D359: =Suppliers!D359 -> Toys & Games | E359: Company page | F359: Find people

Sheet Country Index
A1: Country | B1: Suppliers | C1: Priority 4-5 | D1: Niches covered | E1: Jump to list | F1: Price Level
A2: Austria | B2: =COUNTIF(Suppliers!$A$2:$A$359,A2) -> 3 | C2: =COUNTIFS(Suppliers!$A$2:$A$359,A2,Suppliers!$C$2:$C$359,">=4") -> 0 | D2: Stationery & Office, Toys & Games | E2: Go to > | F2: Higher
A3: Belgium | B3: =COUNTIF(Suppliers!$A$2:$A$359,A3) -> 8 | C3: =COUNTIFS(Suppliers!$A$2:$A$359,A3,Suppliers!$C$2:$C$359,">=4") -> 3 | D3: DIY & Tools, Fragrance, Home & Kitchen, Pet Supplies | E3: Go to > | F3: Higher
A4: Bulgaria | B4: =COUNTIF(Suppliers!$A$2:$A$359,A4) -> 3 | C4: =COUNTIFS(Suppliers!$A$2:$A$359,A4,Suppliers!$C$2:$C$359,">=4") -> 1 | D4: Beauty, Home & Kitchen | E4: Go to > | F4: Low-cost
A5: Croatia | B5: =COUNTIF(Suppliers!$A$2:$A$359,A5) -> 1 | C5: =COUNTIFS(Suppliers!$A$2:$A$359,A5,Suppliers!$C$2:$C$359,">=4") -> 0 | D5: Health & Personal Care | E5: Go to > | F5: Low-cost
A6: Czech Republic | B6: =COUNTIF(Suppliers!$A$2:$A$359,A6) -> 24 | C6: =COUNTIFS(Suppliers!$A$2:$A$359,A6,Suppliers!$C$2:$C$359,">=4") -> 11 | D6: Beauty, DIY & Tools, Fragrance, Health & Personal Care, Home & Kitchen, Pet Supplies, Sports & Outdoors, Stationery & Office, Toys & Games | E6: Go to > | F6: Low-cost
A7: Denmark | B7: =COUNTIF(Suppliers!$A$2:$A$359,A7) -> 8 | C7: =COUNTIFS(Suppliers!$A$2:$A$359,A7,Suppliers!$C$2:$C$359,">=4") -> 3 | D7: Baby Products, Beauty, Pet Supplies, Sports & Outdoors, Stationery & Office, Toys & Games | E7: Go to > | F7: Higher
A8: Finland | B8: =COUNTIF(Suppliers!$A$2:$A$359,A8) -> 4 | C8: =COUNTIFS(Suppliers!$A$2:$A$359,A8,Suppliers!$C$2:$C$359,">=4") -> 4 | D8: Beauty, DIY & Tools, Home & Kitchen, Toys & Games | E8: Go to > | F8: Higher
A9: France | B9: =COUNTIF(Suppliers!$A$2:$A$359,A9) -> 11 | C9: =COUNTIFS(Suppliers!$A$2:$A$359,A9,Suppliers!$C$2:$C$359,">=4") -> 6 | D9: Baby Products, Health & Personal Care, Pet Supplies, Sports & Outdoors, Stationery & Office, Toys & Games | E9: Go to > | F9: Higher
A10: Germany | B10: =COUNTIF(Suppliers!$A$2:$A$359,A10) -> 66 | C10: =COUNTIFS(Suppliers!$A$2:$A$359,A10,Suppliers!$C$2:$C$359,">=4") -> 40 | D10: B2B Marketplace, Baby Products, Beauty, DIY & Tools, Fragrance, Health & Personal Care, Home & Kitchen, Pet Supplies, Sports & Outdoors, Stationery & Office, Toys & Games | E10: Go to > | F10: Higher
A11: Greece | B11: =COUNTIF(Suppliers!$A$2:$A$359,A11) -> 4 | C11: =COUNTIFS(Suppliers!$A$2:$A$359,A11,Suppliers!$C$2:$C$359,">=4") -> 2 | D11: Beauty | E11: Go to > | F11: Low-cost
A12: Hungary | B12: =COUNTIF(Suppliers!$A$2:$A$359,A12) -> 3 | C12: =COUNTIFS(Suppliers!$A$2:$A$359,A12,Suppliers!$C$2:$C$359,">=4") -> 1 | D12: Beauty, Health & Personal Care | E12: Go to > | F12: Low-cost
A13: Ireland | B13: =COUNTIF(Suppliers!$A$2:$A$359,A13) -> 2 | C13: =COUNTIFS(Suppliers!$A$2:$A$359,A13,Suppliers!$C$2:$C$359,">=4") -> 1 | D13: Beauty, Health & Personal Care | E13: Go to > | F13: Higher
... A26: UK | B26: =COUNTIF(Suppliers!$A$2:$A$359,A26) -> 50 | C26: =COUNTIFS(Suppliers!$A$2:$A$359,A26,Suppliers!$C$2:$C$359,">=4") -> 23 | D26: B2B Marketplace, Baby Products, DIY & Tools, Fragrance, General Wholesale / FMCG, Health & Personal Care, Home & Kitchen, Pet Supplies, Sports & Outdoors, Stationery & Office, Toys & Games | E26: Go to > | F26: UK (no import)
A27: Total | B27: =SUM(B2:B26) -> 358 | C27: =SUM(C2:C26) -> 170

Sheet Best-Value Countries
A1: Where to buy each niche cheapest in the EU
A2: Guide only - always compare landed cost (unit price + freight + duty/VAT) in the Profit Calculator. Low-cost countries are cheapest for their OWN manufacturers' brands; big international brands are often cheapest from large German / Dutch distributors because of volume. 'On your list' counts are live formulas.
A4: Niche | B4: Cheapest EU countries (best first) | C4: Why it's cheaper there | D4: Good brands / makers to start with | E4: On your list: Low-cost countries | F4: On your list: total
A5: Baby Products | B5: Poland, Spain, Lithuania | C5: Poland is a major nursery-goods producer with low labour costs (bottles, teethers, prams, car seats). Spain has big feeding/soother makers at mid prices. | D5: Canpol babies, BabyOno, Lionelo, Kinderkraft (PL); Suavinex, Jané (ES) | E5: =COUNTIFS(Suppliers!$D$2:$D$359,A5,Suppliers!$K$2:$K$359,"Low-cost") -> 7 | F5: =COUNTIF(Suppliers!$D$2:$D$359,A5) -> 30
A6: Beauty | B6: Poland, Bulgaria, Czech Republic, Romania, Spain | C6: Poland has one of Europe's largest cosmetics industries with very low unit prices; Bulgaria is cheapest for rose-based products; Czech & Romanian brands are cheap with little UK competition. | D6: Ziaja, Eveline, Bielenda, Farmona, Delia (PL); Bulgarian Rose, Lema (BG); Dermacol, Manufaktura (CZ); Gerovital (RO) | E6: =COUNTIFS(Suppliers!$D$2:$D$359,A6,Suppliers!$K$2:$K$359,"Low-cost") -> 24 | F6: =COUNTIF(Suppliers!$D$2:$D$359,A6) -> 38
A7: DIY & Tools | B7: Poland, Czech Republic, Spain | C7: Polish tool groups (TOYA/YATO, GTX/NEO, Dedra) import and assemble at scale and sell well below German brand prices. | D7: TOYA/YATO, GTX Poland, Dedra, Logo-Tools (PL); Bellota, EGA Master (ES) | E7: =COUNTIFS(Suppliers!$D$2:$D$359,A7,Suppliers!$K$2:$K$359,"Low-cost") -> 9 | F7: =COUNTIF(Suppliers!$D$2:$D$359,A7) -> 30
A8: Fragrance | B8: Poland, Spain, Netherlands/Germany (distributors) | C8: Polish & Spanish fragrance houses make cheap 'inspired' and own-brand lines; genuine designer fragrance is usually cheapest from large NL/DE distributors - but check authenticity and invoices carefully. | D8: Parfum Company (PL); Instituto Español (ES); verified NL/DE distributors only | E8: =COUNTIFS(Suppliers!$D$2:$D$359,A8,Suppliers!$K$2:$K$359,"Low-cost") -> 4 | F8: =COUNTIF(Suppliers!$D$2:$D$359,A8) -> 11
A9: General Wholesale / FMCG | B9: Poland, Netherlands, Germany | C9: Poland for cheap local FMCG; NL/DE for large multi-brand distributors and clearance stock. | D9: Check Due Diligence tab before any clearance / stock-lot deal | E9: =COUNTIFS(Suppliers!$D$2:$D$359,A9,Suppliers!$K$2:$K$359,"Low-cost") -> 0 | F9: =COUNTIF(Suppliers!$D$2:$D$359,A9) -> 8
A10: Health & Personal Care | B10: Poland, Hungary, Czech Republic | C10: Poland & Hungary are big sports-nutrition producers (Olimp, Trec, BioTechUSA); Czech makers are cheap for oral care & brushes. | D10: Olimp, Trec (PL); BioTechUSA (HU); Nutrend, Spokar, Alpa (CZ) | E10: =COUNTIFS(Suppliers!$D$2:$D$359,A10,Suppliers!$K$2:$K$359,"Low-cost") -> 14 | F10: =COUNTIF(Suppliers!$D$2:$D$359,A10) -> 34
A11: Home & Kitchen | B11: Poland, Czech Republic, Portugal | C11: Low manufacturing costs for cookware, cleaning tools, kitchen utensils and storage; Portugal is cheap for cookware, ceramics and textiles. | D11: Gerlach, Konex, Homla (PL); Tescoma, BLEX, Dřevotvar (CZ); Silampos (PT) | E11: =COUNTIFS(Suppliers!$D$2:$D$359,A11,Suppliers!$K$2:$K$359,"Low-cost") -> 19 | F11: =COUNTIF(Suppliers!$D$2:$D$359,A11) -> 49
A12: Pet Supplies | B12: Poland, Czech Republic, Spain | C12: Poland is a major pet food & accessories producer (86-88% of its pet food is exported within the EU); Spanish & Italian accessory makers are mid-priced. | D12: Dingo, Vitapol, DermaPharm (PL); Funky Dog (CZ); Gaun (ES); Georplast (IT) | E12: =COUNTIFS(Suppliers!$D$2:$D$359,A12,Suppliers!$K$2:$K$359,"Low-cost") -> 10 | F12: =COUNTIF(Suppliers!$D$2:$D$359,A12) -> 41
A13: Sports & Outdoors | B13: Poland, Czech Republic, Spain | C13: Polish fitness/sports accessory brands are cheap and well known in Central Europe; Spain for padel & fitness accessories. | D13: Spokey, Meteor, Bacha Sport (PL); Softee/Jim Sports (ES) | E13: =COUNTIFS(Suppliers!$D$2:$D$359,A13,Suppliers!$K$2:$K$359,"Low-cost") -> 9 | F13: =COUNTIF(Suppliers!$D$2:$D$359,A13) -> 31
A14: Stationery & Office | B14: Poland, Czech Republic, Spain, Portugal | C14: Local paper & stationery industries with low costs; Spain's APLI & MILAN are cheap for labels and school supplies. | D14: Interdruk (PL); KOH-I-NOOR (CZ); APLI, MILAN (ES); Bi-silque (PT) | E14: =COUNTIFS(Suppliers!$D$2:$D$359,A14,Suppliers!$K$2:$K$359,"Low-cost") -> 6 | F14: =COUNTIF(Suppliers!$D$2:$D$359,A14) -> 29
A15: Toys & Games | B15: Poland, Czech Republic, Spain | C15: Poland & Czechia make puzzles and board games cheaply in-house (Trefl, Dino); Spain's Ibi/Onil toy cluster for dolls, ride-ons and outdoor toys. | D15: Trefl, COBI, Wader, Granna (PL); Dino Toys, Albi (CZ); Miniland, Colorbaby, Famosa (ES) | E15: =COUNTIFS(Suppliers!$D$2:$D$359,A15,Suppliers!$K$2:$K$359,"Low-cost") -> 13 | F15: =COUNTIF(Suppliers!$D$2:$D$359,A15) -> 54
A16: B2B Marketplace | B16: Varies | C16: Marketplaces aggregate many sellers - prices vary by seller. Verify each seller's company registration and VAT number. | D16: See Due Diligence tab | E16: =COUNTIFS(Suppliers!$D$2:$D$359,A16,Suppliers!$K$2:$K$359,"Low-cost") -> 0 | F16: =COUNTIF(Suppliers!$D$2:$D$359,A16) -> 3
A18: Avoiding scammers when buying cheap
A19: - Prices far below every other quote are the #1 warning sign - genuine low-cost countries are cheaper, not 70% cheaper.
A20: - Check the company on the official register: Poland KRS/CEIDG, Czech ARES/justice.cz, Bulgaria Commercial Register (EIK), Romania ONRC, Lithuania Registrų centras, Spain Registro Mercantil, Portugal NIF. Then check the VAT number on the EU VIES site.
A21: - Prefer suppliers listed by a government export agency (CzechTrade, trade.gov.pl / PAIH, ICEX, AICEP) or exhibiting at major trade fairs - these are noted in the Legitimacy Evidence column.
A22: - Bank details must be in the company's own name and country. Never pay a personal account, crypto, or a 'new' bank account sent by email - phone the supplier on a number from their website to confirm.
A23: - Start with a small test order, ask for an invoice that meets Amazon's requirements, and use a card or escrow-style payment where possible for the first order.

Sheet Contact First
A1: Contact First - best EU suppliers with a direct phone or email
A2: 99 priority 4-5 EU suppliers that passed the scam check and list a phone number or email, ordered cheapest country first (Low-cost > Mid > Higher), then country and niche. Status updates live from the Suppliers tab - click 'Open row' to log your outreach there.
A4: Price Level | B4: Country | C4: Category | D4: Priority | E4: Company | F4: Phone | G4: Email | H4: Key Brands / Products | I4: Status (live) | J4: Go to
A5: Low-cost | B5: Czech Republic | C5: DIY & Tools | D5: 4 | E5: HECHT MOTORS s.r.o. | G5: export@hecht.cz | H5: HECHT lawn mowers, trimmers, chainsaws, pressure washers, workshop tools, e-scooters | I5: =Suppliers!AF19 -> Not contacted | J5: Open row >
A6: Low-cost | B6: Czech Republic | C6: DIY & Tools | D6: 4 | E6: NAREX s.r.o. | F6: +420 481 645 183 | G6: narex@narex.cz | H6: Narex power tools (drills, grinders, saws); Narex Bystřice chisels & woodworking tools | I6: =Suppliers!AF20 -> Not contacted | J6: Open row >
A7: Low-cost | B7: Czech Republic | C7: Health & Personal Care | D7: 4 | E7: NUTREND D.S., a.s. | F7: +420 583 842 592 | G7: export@nutrend.eu | H7: Nutrend sports nutrition, bars, supplements | I7: =Suppliers!AF23 -> Not contacted | J7: Open row >
A8: Low-cost | B8: Czech Republic | C8: Home & Kitchen | D8: 4 | E8: PLASTIA s.r.o. (Urbalive) | F8: +420 566 667 001 | G8: info@plastia.cz | H8: Plastia self-watering planters, Urbalive (incl. pet products) | I8: =Suppliers!AF28 -> Not contacted | J8: Open row >
A9: Low-cost | B9: Czech Republic | C9: Home & Kitchen | D9: 4 | E9: Tescoma s.r.o. (export centre Tescoma S.p.A., Italy) | F9: +39 030 775 1394 (export centre) | H9: Tescoma kitchen utensils, cookware, baking, storage (thousands of SKUs) | I9: =Suppliers!AF26 -> Not contacted | J9: Open row >
A10: Low-cost | B10: Czech Republic | C10: Sports & Outdoors | D10: 4 | E10: GALA a.s. | F10: +420 739 648 045 | G10: grmelova@gala.cz (sales manager) | H10: Gala volleyballs, basketballs, footballs, handballs | I10: =Suppliers!AF33 -> Not contacted | J10: Open row >
A11: Low-cost | B11: Czech Republic | C11: Stationery & Office | D11: 4 | E11: KOH-I-NOOR HARDTMUTH a.s. | G11: kht@koh-i-noor.cz | H11: Koh-i-noor pencils, crayons, art supplies, Progresso | I11: =Suppliers!AF37 -> Not contacted | J11: Open row >
A12: Low-cost | B12: Czech Republic | C12: Toys & Games | D12: 4 | E12: Dino Toys s.r.o. | F12: +420 324 709 315 (verify) | G12: export@dinotoys.cz | H12: Dino puzzles, board games, cards; Disney & Krtek (Little Mole) licences | I12: =Suppliers!AF38 -> Not contacted | J12: Open row >
A13: Low-cost | B13: Greece | C13: Beauty | D13: 4 | E13: Papoutsanis S.A. | F13: +30 22620 85 000 | G13: info@papoutsanis.gr | H13: Papoutsanis olive-oil soaps, Karavaki, Aloe Vera; private label & hotel amenities | I13: =Suppliers!AF132 -> Not contacted | J13: Open row >
A14: Low-cost | B14: Lithuania | C14: Beauty | D14: 4 | E14: BIOK laboratorija, UAB | F14: +370 614 03676 (verify) | H14: Ecodenta toothpaste & oral care, Margarita, RASA, BIOK natural cosmetics | I14: =Suppliers!AF165 -> Not contacted | J14: Open row >
A15: Low-cost | B15: Poland | C15: Baby Products | D15: 5 | E15: BrandLine Group Sp. z o.o. (Lionelo) | F15: +48 61 222 2980 | G15: sprzedaz@brandlinegroup.com | H15: Lionelo baby products; also Overmax electronics, Pelvio | I15: =Suppliers!AF190 -> Not contacted | J15: Open row >
A16: Low-cost | B16: Poland | C16: Baby Products | D16: 4 | E16: Canpol Sp. z o.o. (Canpol babies, LOVI, Difrax) | G16: babies@canpolbabies.com | H16: Canpol babies, LOVI, Difrax - bottles, dummies, feeding, baby accessories | I16: =Suppliers!AF193 -> Not contacted | J16: Open row >
A17: Low-cost | B17: Poland | C17: Baby Products | D17: 4 | E17: Ceba Sp. z o.o. (Ceba Baby) | G17: kontakt@ceba.com.pl | H17: Ceba Baby changing mats, pregnancy & nursing pillows, blankets | I17: =Suppliers!AF194 -> Not contacted | J17: Open row >
A18: Low-cost | B18: Poland | C18: Baby Products | D18: 4 | E18: WOMAR (Zaffiro brand) | F18: +48 34 369 71 38 | G18: export@womar.com.pl | H18: Zaffiro baby carriers & slings, sleeping bags, wool blankets, cot & pram bedding | I18: =Suppliers!AF195 -> Not contacted | J18: Open row >
A19: Low-cost | B19: Poland | C19: Beauty | D19: 4 | E19: Delia Cosmetics Sp. z o.o. | F19: +48 42 225 44 84 (verify) | H19: Delia, Cameleo (hair), Humanist | I19: =Suppliers!AF200 -> Not contacted | J19: Open row >
A20: Low-cost | B20: Poland | C20: Beauty | D20: 4 | E20: Dr Irena Eris S.A. | F20: +48 22 717 1111 | H20: Dr Irena Eris, Pharmaceris, Lirene, Emotopic, Under Twenty | I20: =Suppliers!AF201 -> Not contacted | J20: Open row >
A21: Low-cost | B21: Poland | C21: Beauty | D21: 4 | E21: Eveline Cosmetics | F21: +48 22 228 8228 (verify) | H21: Eveline skincare, makeup, body care | I21: =Suppliers!AF197 -> Not contacted | J21: Open row >
A22: Low-cost | B22: Poland | C22: DIY & Tools | D22: 5 | E22: TOYA S.A. (YATO, VOREL, STHOR, FLO, LUND) | F22: +48 71 32 46 200 | G22: export@yato.pl | H22: YATO professional tools, VOREL, STHOR, FLO garden, LUND | I22: =Suppliers!AF207 -> Not contacted | J22: Open row >
A23: Low-cost | B23: Poland | C23: DIY & Tools | D23: 4 | E23: GTX Poland Sp. z o.o. Sp. k. (formerly Grupa Topex) | G23: office@gtx-group.com | H23: NEO TOOLS, TOPEX, VERTO, TOP TOOLS, GRAPHITE, BAILDON | I23: =Suppliers!AF210 -> Not contacted | J23: Open row >
A24: Low-cost | B24: Poland | C24: Health & Personal Care | D24: 4 | E24: SFD S.A. (Allnutrition) | F24: +48 77 549 25 00 | G24: sekretariat@sfd.pl (ask for export / wholesale) | H24: SFD Nutrition, Allnutrition, Alldeynn, FitKing, NutLove | I24: =Suppliers!AF220 -> Not contacted | J24: Open row >
A25: Low-cost | B25: Poland | C25: Home & Kitchen | D25: 4 | E25: KONEX Sp. z o.o. | G25: export@konex.pl | H25: Konex mops, brushes, dustpans, cleaning sets; private label | I25: =Suppliers!AF222 -> Not contacted | J25: Open row >
A26: Low-cost | B26: Poland | C26: Pet Supplies | D26: 4 | E26: Amiplay Sp. z o.o. (Comfy) | F26: +48 696 607 221 (export director: +48 888 787 666) | H26: Comfy & Amiplay dog/cat toys, beds, leads, travel & hygiene | I26: =Suppliers!AF227 -> Not contacted | J26: Open row >
A27: Low-cost | B27: Poland | C27: Pet Supplies | D27: 4 | E27: Cazo Sp. z o.o. | F27: +48 34 323 50 77 | G27: cazo@cazo.eu | H27: Cazo dog & cat beds, mattresses, houses, carriers | I27: =Suppliers!AF228 -> Not contacted | J27: Open row >
A28: Low-cost | B28: Poland | C28: Pet Supplies | D28: 4 | E28: EMPETS Group | F28: +48 882 668 215 | G28: biuro@empetsgroup.com | H28: Empets pet beds, Hoppa modular cat trees | I28: =Suppliers!AF229 -> Not contacted | J28: Open row >
A29: Low-cost | B29: Poland | C29: Pet Supplies | D29: 4 | E29: Laboratorium DermaPharm Sp. z o.o. | F29: +48 604 555 652 | G29: a.gorzkowska@dermapharm.com.pl | H29: Dr Seidel, Mr. Smell, Sabunol pet care | I29: =Suppliers!AF230 -> Not contacted | J29: Open row >
A30: Low-cost | B30: Poland | C30: Sports & Outdoors | D30: 4 | E30: Cumulus Sp. z o.o. | F30: +48 58 620 94 12 | H30: Cumulus down sleeping bags, down jackets, quilts | I30: =Suppliers!AF237 -> Not contacted | J30: Open row >
A31: Low-cost | B31: Poland | C31: Stationery & Office | D31: 4 | E31: Euro-Trade Sp. z o.o. Sp.K. (Starpak) | F31: +48 12 614 42 00 | G31: biuro@euro-trade.pl | H31: Starpak school & office supplies, art & craft, gifts; toys (8 own brands) | I31: =Suppliers!AF240 -> Not contacted | J31: Open row >
A32: Low-cost | B32: Poland | C32: Stationery & Office | D32: 4 | E32: St. Majewski Sp. z o.o. (incl. Unipap) | F32: +48 22 758 70 41 | G32: st-majewski@st-majewski.pl | H32: Bambino crayons & pencils, Stright, St. Majewski notebooks, pencil cases, schoolbags, licensed collections | I32: =Suppliers!AF241 -> Not contacted | J32: Open row >
A33: Low-cost | B33: Poland | C33: Toys & Games | D33: 4 | E33: ANEK Sp. z o.o. (Smily Play) | F33: +48 22 123 08 14 | G33: zabawki@anek.com.pl | H33: Smily Play baby & toddler toys; also distributes Mattel & Hasbro | I33: =Suppliers!AF246 -> Not contacted | J33: Open row >
A34: Low-cost | B34: Poland | C34: Toys & Games | D34: 4 | E34: Granna Sp. z o.o. | G34: handel@granna.pl | H34: Granna board games (Superfarmer, Potwory do szafy) | I34: =Suppliers!AF247 -> Not contacted | J34: Open row >
A35: Low-cost | B35: Poland | C35: Toys & Games | D35: 4 | E35: Trefl S.A. | G35: trefl@trefl.com | H35: Trefl puzzles, board & card games, licensed games | I35: =Suppliers!AF244 -> Not contacted | J35: Open row >
A36: Low-cost | B36: Poland | C36: Toys & Games | D36: 4 | E36: Wader-Woźniak Sp. z o.o. | F36: +48 32 264 60 40 | G36: mail@wader.toys.pl | H36: Wader plastic toys, vehicles, sand & garden toys | I36: =Suppliers!AF248 -> Not contacted | J36: Open row >
A37: Low-cost | B37: Portugal | C37: Home & Kitchen | D37: 4 | E37: Domingos de Sousa & Filhos, S.A. | F37: +351 253 480 030 | H37: Jacquard & terry towels, bathrobes | I37: =Suppliers!AF253 -> Not contacted | J37: Open row >
A38: Low-cost | B38: Portugal | C38: Home & Kitchen | D38: 4 | E38: Têxteis J.F. Almeida, S.A. (JFA) | F38: +351 253 560 000 | H38: Towels, bathrobes, home textiles | I38: =Suppliers!AF254 -> Not contacted | J38: Open row >
A39: Low-cost | B39: Portugal | C39: Home & Kitchen | D39: 4 | E39: Villafelpos - Comércio e Indústria Têxtil, S.A. | F39: +351 253 520 570 | H39: Bath towels, beach towels, bathrobes | I39: =Suppliers!AF255 -> Not contacted | J39: Open row >
A40: Low-cost | B40: Portugal | C40: Stationery & Office | D40: 4 | E40: Ambar - Passion S.A. | F40: +351 22 615 1400 | H40: Ambar notebooks, school & office paper products | I40: =Suppliers!AF261 -> Not contacted | J40: Open row >
A41: Low-cost | B41: Portugal | C41: Stationery & Office | D41: 4 | E41: Bi-silque - Produtos de Comunicação Visual, S.A. | F41: +351 256 750 120 | H41: Bi-Office whiteboards, noticeboards, flipcharts | I41: =Suppliers!AF262 -> Not contacted | J41: Open row >
A42: Mid | B42: Italy | C42: DIY & Tools | D42: 4 | E42: Beta Utensili S.p.A. | F42: +39 039 2077 231 | H42: Beta hand tools, tool trolleys, workwear | I42: =Suppliers!AF143 -> Not contacted | J42: Open row >
A43: Mid | B43: Italy | C43: Home & Kitchen | D43: 4 | E43: Bialetti Industrie S.p.A. | F43: +39 030 7720011 | H43: Bialetti moka pots & coffee, Rondine & Aeternum cookware, Girmi appliances | I43: =Suppliers!AF147 -> Not contacted | J43: Open row >
A44: Mid | B44: Italy | C44: Home & Kitchen | D44: 4 | E44: Guardini S.p.A. | F44: +39 011 995 2890 | H44: Guardini bakeware, cake tins, baking trays, muffin pans | I44: =Suppliers!AF151 -> Not contacted | J44: Open row >
A45: Mid | B45: Italy | C45: Pet Supplies | D45: 4 | E45: Ferplast S.p.A. | F45: +39 0445 429111 | G45: info@ferplast.com | H45: Ferplast cages, aquariums, beds, carriers, accessories - 5,000+ products | I45: =Suppliers!AF152 -> Not contacted | J45: Open row >
A46: Mid | B46: Italy | C46: Pet Supplies | D46: 4 | E46: Georplast s.r.l. | F46: +39 039 602 0021 | G46: georplast@georplast.it (verify) | H46: Georplast pet carriers, beds, bowls, litter trays | I46: =Suppliers!AF153 -> Not contacted | J46: Open row >
A47: Mid | B47: Italy | C47: Stationery & Office | D47: 4 | E47: CARIOCA S.p.A. | G47: amministrazione@carioca.it (ask for export) | H47: Carioca markers, colouring pencils, tempera | I47: =Suppliers!AF160 -> Not contacted | J47: Open row >
A48: Mid | B48: Italy | C48: Toys & Games | D48: 4 | E48: Quercetti & C. S.p.A. | F48: +39 011 235656 (verify) | G48: export@quercetti.com | H48: Quercetti pegboards, marble runs, educational toys (made in Italy) | I48: =Suppliers!AF162 -> Not contacted | J48: Open row >
A49: Mid | B49: Spain | C49: Baby Products | D49: 4 | E49: R&J Cambrass S.A. | F49: +34 96 291 2965 | G49: Contact form via ASEPRI brand page | H49: Cambrass baby textiles - cot bedding, sleeping bags, changing bags, muslins | I49: =Suppliers!AF269 -> Not contacted | J49: Open row >
A50: Mid | B50: Spain | C50: Beauty | D50: 4 | E50: ISDIN S.A. | F50: +34 93 519 11 00 | G50: customer.es@isdin.com | H50: ISDIN sun care (Fotoprotector), Ureadin, Lambdapil | I50: =Suppliers!AF273 -> Not contacted | J50: Open row >
A51: Mid | B51: Spain | C51: DIY & Tools | D51: 4 | E51: Bellota Herramientas S.L.U. | F51: +34 943 739 000 | H51: Bellota hand tools, garden & agricultural tools, construction tools | I51: =Suppliers!AF278 -> Not contacted | J51: Open row >
A52: Mid | B52: Spain | C52: Home & Kitchen | D52: 4 | E52: IBILI Menaje S.A. | F52: +34 943 763 544 | H52: Ibili kitchen gadgets, bakeware, paella pans, cookware | I52: =Suppliers!AF284 -> Not contacted | J52: Open row >
A53: Mid | B53: Spain | C53: Home & Kitchen | D53: 4 | E53: Lékué S.L. | G53: info@lekue.com | H53: Lékué silicone cookware, steam cases, lunch boxes, baking | I53: =Suppliers!AF282 -> Not contacted | J53: Open row >
A54: Mid | B54: Spain | C54: Stationery & Office | D54: 5 | E54: APLI Paper S.A.U. | F54: +34 937 479 100 | G54: apli@apli.com | H54: APLI labels, Miquelrius notebooks, Agipa, Decadry, Back2Fun | I54: =Suppliers!AF290 -> Not contacted | J54: Open row >
A55: Mid | B55: Spain | C55: Stationery & Office | D55: 4 | E55: Factis S.A. (MILAN) | F55: +34 972 30 32 00 | H55: MILAN erasers, pencils, school & office supplies | I55: =Suppliers!AF291 -> Not contacted | J55: Open row >
A56: Mid | B56: Spain | C56: Toys & Games | D56: 4 | E56: Miniland S.A. | F56: +34 965 564 950 | H56: Miniland Educational dolls & STEM, Miniland Baby (thermometers, monitors) | I56: =Suppliers!AF297 -> Not contacted | J56: Open row >
A57: Higher | B57: Belgium | C57: DIY & Tools | D57: 4 | E57: Varo (Vic Van Rompuy NV) | F57: +32 3 292 92 90 | G57: info@varo.com | H57: Powerplus, Kreator, Premion tools & garden equipment | I57: =Suppliers!AF5 -> Not contacted | J57: Open row >
A58: Higher | B58: Belgium | C58: Pet Supplies | D58: 4 | E58: Flamingo Pet Products NV | F58: +32 14 25 84 80 | G58: info@flamingo.be | H58: Flamingo - 10,000+ pet products; private label available | I58: =Suppliers!AF9 -> Not contacted | J58: Open row >
A59: Higher | B59: Belgium | C59: Pet Supplies | D59: 4 | E59: Savic NV | F59: +32 65 35 33 45 | G59: info@savic.be (verify) | H59: Savic small-animal cages, cat litter trays, dog & bird products | I59: =Suppliers!AF8 -> Not contacted | J59: Open row >
A60: Higher | B60: Denmark | C60: Baby Products | D60: 4 | E60: BabyDan A/S | G60: info@babydan.com | H60: BabyDan safety gates (EN 1930), playpens, home safety | I60: =Suppliers!AF41 -> Not contacted | J60: Open row >
A61: Higher | B61: Finland | C61: Home & Kitchen | D61: 4 | E61: Orthex Finland Ab Oy (SmartStore) | F61: +358 19 32961 (verify) | G61: Contact form on orthexgroup.fi | H61: SmartStore storage boxes, GastroMax kitchenware, Orthex garden | I61: =Suppliers!AF51 -> Not contacted | J61: Open row >
A62: Higher | B62: Finland | C62: Toys & Games | D62: 5 | E62: Tactic Games Oy | G62: sales.uk@tactic.net (UK distributor enquiries) | H62: Tactic games, Mölkky, Heros wooden toys, Plasto, Bex Sport, Puzzle Lovers | I62: =Suppliers!AF52 -> Not contacted | J62: Open row >
A63: Higher | B63: France | C63: Baby Products | D63: 4 | E63: Babymoov Group | F63: +33 4 73 28 60 00 (verify) | H63: Babymoov, doomoo | I63: =Suppliers!AF54 -> Not contacted | J63: Open row >
A64: Higher | B64: France | C64: Stationery & Office | D64: 4 | E64: Groupe Hamelin (Oxford, ELBA) - Hamelin GmbH export arm | G64: corporate.de@hamelinbrands.zendesk.com | H64: Oxford notebooks, ELBA filing, Lamouette, Herlitz-style school paper | I64: =Suppliers!AF59 -> Not contacted | J64: Open row >
A65: Higher | B65: France | C65: Stationery & Office | D65: 4 | E65: Maped SAS | F65: +33 4 50 27 26 85 (verify) | H65: Maped scissors, geometry, pencil cases, colouring; Helix (UK); owns Juratoys | I65: =Suppliers!AF60 -> Not contacted | J65: Open row >
A66: Higher | B66: France | C66: Toys & Games | D66: 4 | E66: Juratoys SAS (Janod, Kaloo, Lilliputiens) | F66: +33 3 84 25 40 26 (verify) | H66: Janod wooden toys, Kaloo plush, Lilliputiens | I66: =Suppliers!AF62 -> Not contacted | J66: Open row >
A67: Higher | B67: Germany | C67: Baby Products | D67: 4 | E67: Lässig GmbH | F67: +49 6073 744890 | G67: service@laessig-gmbh.de | H67: LÄSSIG changing bags, kids' backpacks, tableware, swimwear (GOTS certified) | I67: =Suppliers!AF68 -> Not contacted | J67: Open row >
A68: Higher | B68: Germany | C68: Beauty | D68: 4 | E68: cosnova GmbH (essence, CATRICE) | F68: +49 6196 76156-0 | G68: service@cosnova.eu | H68: essence, CATRICE, Physicians Formula (EU) | I68: =Suppliers!AF71 -> Not contacted | J68: Open row >
A69: Higher | B69: Germany | C69: Beauty | D69: 4 | E69: Weleda AG (German branch) | G69: dialog@weleda.de | H69: Weleda natural skincare, baby care (Calendula), Skin Food | I69: =Suppliers!AF72 -> Not contacted | J69: Open row >
A70: Higher | B70: Germany | C70: DIY & Tools | D70: 4 | E70: fischerwerke GmbH & Co. KG | F70: +49 7443 120 | H70: fischer wall plugs, anchors & fixings; fischertechnik | I70: =Suppliers!AF76 -> Not contacted | J70: Open row >
A71: Higher | B71: Germany | C71: DIY & Tools | D71: 4 | E71: GARDENA Deutschland GmbH (Husqvarna Group) | F71: +49 731 490-0 | G71: service@gardena.com | H71: GARDENA hoses, watering, garden tools, robotic mowers | I71: =Suppliers!AF77 -> Not contacted | J71: Open row >
A72: Higher | B72: Germany | C72: DIY & Tools | D72: 4 | E72: KNIPEX-Werk C. Gustav Putsch KG | F72: +49 202 4794-0 | G72: info@knipex.de | H72: KNIPEX pliers, Cobra, wire strippers | I72: =Suppliers!AF78 -> Not contacted | J72: Open row >
A73: Higher | B73: Germany | C73: DIY & Tools | D73: 4 | E73: kwb Germany GmbH (Einhell group) | F73: +49 421 8994-0 | G73: welcome@kwb.eu | H73: kwb power-tool accessories (drill bits, saw blades, abrasives) & hand tools | I73: =Suppliers!AF81 -> Not contacted | J73: Open row >
A74: Higher | B74: Germany | C74: DIY & Tools | D74: 4 | E74: Scheppach GmbH | F74: +49 8223 4002-0 | G74: info@scheppach.com | H74: Scheppach woodworking machines, garden & workshop tools | I74: =Suppliers!AF82 -> Not contacted | J74: Open row >
A75: Higher | B75: Germany | C75: DIY & Tools | D75: 4 | E75: Wera Werkzeuge GmbH | F75: +49 202 4045-322 | G75: info@wera.de | H75: Wera screwdrivers, bits, ratchets, Kraftform | I75: =Suppliers!AF79 -> Not contacted | J75: Open row >
A76: Higher | B76: Germany | C76: DIY & Tools | D76: 4 | E76: Wiha Werkzeuge GmbH | F76: +49 7722 959-0 | G76: info.de@wiha.com | H76: Wiha screwdrivers, VDE insulated tools, bits | I76: =Suppliers!AF80 -> Not contacted | J76: Open row >
A77: Higher | B77: Germany | C77: Health & Personal Care | D77: 4 | E77: Beurer GmbH (Beurer UK Ltd) | F77: +49 731 3989-0 | H77: Beurer BP monitors, thermometers, massagers, scales, TENS, beauty devices | I77: =Suppliers!AF86 -> Not contacted | J77: Open row >
A78: Higher | B78: Germany | C78: Home & Kitchen | D78: 4 | E78: GEFU GmbH | F78: +49 2973 97130 | G78: info@gefu.com | H78: GEFU kitchen tools, spiralizers, pasta makers, gadgets | I78: =Suppliers!AF93 -> Not contacted | J78: Open row >
A79: Higher | B79: Germany | C79: Home & Kitchen | D79: 4 | E79: SEVERIN Elektrogeräte GmbH | F79: +49 2933 98 20 | G79: information@severin.de | H79: SEVERIN coffee machines, kettles, toasters, grills, fridges | I79: =Suppliers!AF94 -> Not contacted | J79: Open row >
A80: Higher | B80: Germany | C80: Home & Kitchen | D80: 4 | E80: Westmark GmbH | F80: +49 2721 92580 | H80: Westmark, Monopol, Saleen - 2,500+ kitchen utensils | I80: =Suppliers!AF95 -> Not contacted | J80: Open row >
A81: Higher | B81: Germany | C81: Pet Supplies | D81: 5 | E81: TRIXIE Heimtierbedarf (incl. Trixie UK Pet Product Ltd) | F81: +44 20 7154 2940 (UK - verify) | G81: sales@trixie.de | H81: TRIXIE - 6,000+ pet accessories, toys, beds, treats; exports to 80+ countries | I81: =Suppliers!AF97 -> Not contacted | J81: Open row >
A82: Higher | B82: Germany | C82: Pet Supplies | D82: 4 | E82: Albert Kerbl GmbH | F82: +49 8086 933-100 | G82: info@kerbl.de (UK: enquiries@kerbl.co.uk) | H82: Kerbl pet accessories, grooming, small-animal, chew toys + farm/equestrian | I82: =Suppliers!AF98 -> Not contacted | J82: Open row >
A83: Higher | B83: Germany | C83: Pet Supplies | D83: 4 | E83: H. von Gimborn GmbH (GimCat, GimDog, Biokat's) | F83: +49 2822 9640 | G83: info@gimborn.de | H83: GimCat, GimDog snacks & care, Biokat's cat litter | I83: =Suppliers!AF99 -> Not contacted | J83: Open row >
A84: Higher | B84: Germany | C84: Pet Supplies | D84: 4 | E84: HUNTER International GmbH | F84: +49 521 16399-500 | G84: info@hunter.de | H84: HUNTER, stylecats, KESSI - collars, leads, beds, cat accessories | I84: =Suppliers!AF100 -> Not contacted | J84: Open row >
A85: Higher | B85: Germany | C85: Pet Supplies | D85: 4 | E85: Nobby Pet Shop GmbH | F85: +49 2871 2394390 | G85: info@nobby.de | H85: 7,000+ pet products: dog, cat, small animal, bird, aquarium, pond | I85: =Suppliers!AF101 -> Not contacted | J85: Open row >
A86: Higher | B86: Germany | C86: Sports & Outdoors | D86: 4 | E86: SIGMA-ELEKTRO GmbH (SIGMA SPORT) | F86: +49 6321 91200 | G86: info@sigma.bike | H86: SIGMA bike computers, bike lights, e-bike electronics | I86: =Suppliers!AF107 -> Not contacted | J86: Open row >
A87: Higher | B87: Germany | C87: Stationery & Office | D87: 4 | E87: DURABLE Hunke & Jochheim GmbH & Co. KG | F87: +49 2371 9792-0 (logistics - verify) | H87: DURABLE filing, ID badges, desk organisers, LED lamps, workplace | I87: =Suppliers!AF119 -> Not contacted | J87: Open row >
A88: Higher | B88: Germany | C88: Stationery & Office | D88: 4 | E88: edding International GmbH | F88: +49 4102 808-0 | G88: info@edding.de | H88: edding markers, paint pens, highlighters, nail varnish | I88: =Suppliers!AF117 -> Not contacted | J88: Open row >
A89: Higher | B89: Germany | C89: Stationery & Office | D89: 4 | E89: Schneider Schreibgeräte GmbH | F89: +49 7729 888-0 | G89: info@schneiderpen.de | H89: Schneider pens, refills, markers, highlighters | I89: =Suppliers!AF120 -> Not contacted | J89: Open row >
A90: Higher | B90: Germany | C90: Stationery & Office | D90: 4 | E90: STAEDTLER Mars GmbH & Co. KG | F90: +49 911 9365-0 | G90: info@staedtler.com | H90: STAEDTLER pencils, markers, erasers, art & drawing supplies | I90: =Suppliers!AF118 -> Not contacted | J90: Open row >
A91: Higher | B91: Germany | C91: Toys & Games | D91: 5 | E91: Franckh-Kosmos Verlags-GmbH & Co. KG (KOSMOS) | F91: +49 711 21910 | G91: info@kosmos.de | H91: CATAN, EXIT games, Ubongo, KOSMOS science kits | I91: =Suppliers!AF122 -> Not contacted | J91: Open row >
A92: Higher | B92: Germany | C92: Toys & Games | D92: 4 | E92: Gollnest & Kiesel GmbH & Co. KG (goki) | F92: +49 4158 88220 | G92: info@goki.eu | H92: goki, HEIMESS, HOLZTIGER - 2,000+ wooden toys & gifts | I92: =Suppliers!AF126 -> Not contacted | J92: Open row >
A93: Higher | B93: Germany | C93: Toys & Games | D93: 4 | E93: Simba Dickie Group GmbH (Simba, Dickie, Smoby, Majorette, Noris, Schuco) | F93: +49 911 9765-01 | H93: Simba, Dickie Toys, Smoby, Majorette, BIG, Noris games, Eichhorn, Schuco, Jada | I93: =Suppliers!AF124 -> Not contacted | J93: Open row >
A94: Higher | B94: Netherlands | C94: Baby Products | D94: 4 | E94: Difrax B.V. | G94: sales@difrax.com | H94: Difrax bottles, dummies, feeding (Benelux market leader) | I94: =Suppliers!AF167 -> Not contacted | J94: Open row >
A95: Higher | B95: Netherlands | C95: General Wholesale / FMCG | D95: 4 | E95: West Coast Supply Group | G95: sales@westcoastsupplygroup.com | H95: A-brands: personal care, beauty, home care, food, drinks, medical, electronics | I95: =Suppliers!AF169 -> Not contacted | J95: Open row >
A96: Higher | B96: Netherlands | C96: Health & Personal Care | D96: 4 | E96: NaskorSports B.V. | F96: +31 77 720 1200 | H96: 140+ sports nutrition brands, 8,000+ products | I96: =Suppliers!AF170 -> Not contacted | J96: Open row >
A97: Higher | B97: Netherlands | C97: Home & Kitchen | D97: 4 | E97: Bolsius Nederland BV | F97: +31 73 543 3000 | H97: Bolsius candles, tealights, citronella, LED candles | I97: =Suppliers!AF173 -> Not contacted | J97: Open row >
A98: Higher | B98: Netherlands | C98: Home & Kitchen | D98: 4 | E98: Koopman International B.V. | F98: +31 20 494 7777 | G98: info@koopmanint.com | H98: 30,000+ non-food items: houseware, kitchen, storage, seasonal, garden, DIY | I98: =Suppliers!AF174 -> Not contacted | J98: Open row >
A99: Higher | B99: Netherlands | C99: Home & Kitchen | D99: 4 | E99: Mepal B.V. | F99: +31 573 820 840 | G99: info@mepal.com | H99: Mepal Campus lunchboxes & bottles, storage, tableware | I99: =Suppliers!AF175 -> Not contacted | J99: Open row >
A100: Higher | B100: Netherlands | C100: Pet Supplies | D100: 4 | E100: Beaphar B.V. | F100: +31 572 348834 (verify) | H100: Beaphar pet health & care (flea, worming, grooming, treats) - 600+ products | I100: =Suppliers!AF179 -> Not contacted | J100: Open row >
A101: Higher | B101: Netherlands | C101: Toys & Games | D101: 4 | E101: European Player Network (EPN) - Asmodee | G101: info@epn-europe.com | H101: English-language tabletop games: AEG, Mandoo, Runes Editions + more | I101: =Suppliers!AF185 -> Not contacted | J101: Open row >
...

Sheet Niche Guide
A1: Niche | B1: Suppliers in list | C1: Priority 4-5 | D1: Amazon UK gating (check Seller Central) | E1: Compliance / documents to ask for | F1: What tends to sell | G1: Sourcing tips
A2: B2B Marketplace | B2: =COUNTIF(Suppliers!$D$2:$D$359,A2) -> 3 | C2: =COUNTIFS(Suppliers!$D$2:$D$359,A2,Suppliers!$C$2:$C$359,">=4") -> 1 | D2: Depends on brand. | E2: Ask platform for commercial invoices + compliance docs per product. | F2: Branded H&B (Qogita), FMCG (Parallel), general merchandise (BigBuy, zentrada). | G2: Fastest way to test a niche with low MOQs; liquidation platforms are not suitable for 'New' Amazon listings.
A3: Baby Products | B3: =COUNTIF(Suppliers!$D$2:$D$359,A3) -> 30 | C3: =COUNTIFS(Suppliers!$D$2:$D$359,A3,Suppliers!$C$2:$C$359,">=4") -> 14 | D3: Category and many brands may need approval; formula, car seats & safety items are high scrutiny. | E3: EN/BS safety standards (e.g. EN 14350 feeding, EN 1888 pushchairs), UKCA/CE, age warnings. | F3: Feeding bottles, dummies, teethers, nappies, baby toiletries, monitors. | G3: Avoid infant formula and car seats until established; feeding & soothers (MAM, Tommee Tippee) are steady sellers.
A4: Beauty | B4: =COUNTIF(Suppliers!$D$2:$D$359,A4) -> 38 | C4: =COUNTIFS(Suppliers!$D$2:$D$359,A4,Suppliers!$C$2:$C$359,">=4") -> 16 | D4: Many brands gated; prestige/luxury beauty is the hardest. Some topical products need approval. | E4: UK Responsible Person + SCPN notification; batch codes & expiry/PAO; INCI ingredients; CPNP for EU stock. | F4: K-beauty (COSRX, Beauty of Joseon, Anua), derma skincare (CeraVe), mass cosmetics, hair care. | G4: Counterfeits are common in CeraVe/The Ordinary - insist on authorised-distributor proof. Pro-salon brands usually ban Amazon.
A5: DIY & Tools | B5: =COUNTIF(Suppliers!$D$2:$D$359,A5) -> 30 | C5: =COUNTIFS(Suppliers!$D$2:$D$359,A5,Suppliers!$C$2:$C$359,">=4") -> 19 | D5: Mostly ungated; big power-tool brands (DeWalt, Makita, Bosch) are often restricted. | E5: Lithium batteries = hazmat (SDS / UN38.3); UKCA/CE for power tools; UK plugs. | F5: Hand tools, accessories & consumables, garage/workshop, cordless tool kits. | G5: Toolbank is trade-only for resellers; Draper has a stockist programme with brand-direct invoices.
A6: Fragrance | B6: =COUNTIF(Suppliers!$D$2:$D$359,A6) -> 11 | C6: =COUNTIFS(Suppliers!$D$2:$D$359,A6,Suppliers!$C$2:$C$359,">=4") -> 4 | D6: Many designer brands are brand-gated. Fragrance is also hazmat (flammable). | E6: Safety Data Sheet (SDS) per product for hazmat review; sealed retail stock only (no testers); UK RP on pack. | F6: Designer gift sets (Q4), Arabian brands (Lattafa, Armaf), mass fragrance & body sprays. | G6: Arabian-brand distributors are often easier to get approved with; ask designer wholesalers for authorised-distributor invoices.
A7: General Wholesale / FMCG | B7: =COUNTIF(Suppliers!$D$2:$D$359,A7) -> 8 | C7: =COUNTIFS(Suppliers!$D$2:$D$359,A7,Suppliers!$C$2:$C$359,">=4") -> 2 | D7: Grocery may need approval; FMCG brands vary. | E7: Expiry dates (FBA min. remaining shelf life), batch codes. | F7: Household cleaning, toiletries, confectionery, multipacks. | G7: Cash & carry promotions can work for arbitrage-style wholesale; margins are thin.
A8: Health & Personal Care | B8: =COUNTIF(Suppliers!$D$2:$D$359,A8) -> 34 | C8: =COUNTIFS(Suppliers!$D$2:$D$359,A8,Suppliers!$C$2:$C$359,">=4") -> 14 | D8: Some brands gated; supplements, OTC medicines and topicals face extra scrutiny. | E8: Supplements: label compliance & batch CoA; GSL medicines: MHRA rules; electrical grooming: UKCA/CE. | F8: Oral care, shaving, deodorants, vitamins, sports nutrition, first aid. | G8: Sports nutrition and first aid are strong for wholesale; check expiry dates for FBA (min. shelf life).
A9: Home & Kitchen | B9: =COUNTIF(Suppliers!$D$2:$D$359,A9) -> 49 | C9: =COUNTIFS(Suppliers!$D$2:$D$359,A9,Suppliers!$C$2:$C$359,">=4") -> 21 | D9: Largely ungated; some premium brands restricted. | E9: Electricals: UKCA/CE + UK plug + WEEE; food-contact materials compliance for kitchenware. | F9: Small appliances (Tower, Swan, Kenwood), storage, kitchen gadgets, cookware. | G9: Brand owners like RKW (Tower/Swan) supply directly; watch MAP pricing on premium cookware.
A10: Pet Supplies | B10: =COUNTIF(Suppliers!$D$2:$D$359,A10) -> 41 | C10: =COUNTIFS(Suppliers!$D$2:$D$359,A10,Suppliers!$C$2:$C$359,">=4") -> 17 | D10: Mostly open; some major brands restricted. | E10: Pet food: labelling & expiry; accessories: general product safety. | F10: Toys (KONG, Trixie), grooming, beds, treats, cat litter accessories. | G10: Trixie sells direct to retailers with a UK warehouse - good first call. Heavy bulky food has high FBA fees.
A11: Sports & Outdoors | B11: =COUNTIF(Suppliers!$D$2:$D$359,A11) -> 31 | C11: =COUNTIFS(Suppliers!$D$2:$D$359,A11,Suppliers!$C$2:$C$359,">=4") -> 13 | D11: Mostly ungated; branded apparel/footwear (Nike, adidas) often restricted. | E11: Gas canisters & some fuels are hazmat; bike parts safety; fitness equipment weight = high FBA fees. | F11: Home fitness accessories, cycling accessories, camping gear, team sports. | G11: Small/light items (bike accessories, resistance bands) work best for FBA fees.
A12: Stationery & Office | B12: =COUNTIF(Suppliers!$D$2:$D$359,A12) -> 29 | C12: =COUNTIFS(Suppliers!$D$2:$D$359,A12,Suppliers!$C$2:$C$359,">=4") -> 18 | D12: Largely ungated. | E12: Ink/toner: counterfeit risk - originals only from authorised distributors; art materials: toy-safety if for children. | F12: Branded pens (Pilot, BIC, Stabilo), notebooks, art supplies, school supplies, labels. | G12: Low price points - bundle/multipacks to beat FBA fees.
A13: Toys & Games | B13: =COUNTIF(Suppliers!$D$2:$D$359,A13) -> 54 | C13: =COUNTIFS(Suppliers!$D$2:$D$359,A13,Suppliers!$C$2:$C$359,">=4") -> 31 | D13: Brand-gated (LEGO, Disney, Hasbro, Mattel). Amazon has restricted new sellers in Q4 in past years. | E13: UKCA/CE marking, EN71 test reports, age & small-parts warnings, UK importer address on pack. | F13: Board games, LEGO-licensed goods, collectibles (Funko), pocket-money toys, licensed character toys. | G13: Official UK distributors (A.B. Gee, Wind Designs) give the best invoices; board games via EPN are low-risk.
A15: Gating rules change often - always confirm in Seller Central (Add a Product > search ASIN > 'Request approval').

Sheet Profit Calculator
A1: Profit Calculator - Amazon UK (FBA)
A2: Blue = your inputs. Black = formulas. Assumes you are VAT-registered (input VAT reclaimed, fees shown ex VAT).
A4: EUR to GBP rate | B4: 0.85 | C4: Placeholder - update to today's rate (e.g. from xe.com) before using.
A5: UK VAT rate | B5: 0.2 | C5: Standard UK VAT rate. Some baby/children's items are zero-rated - adjust per row.
A6: Default referral fee | B6: 0.15 | C6: Typical Amazon UK referral fee; varies by category (check Amazon's fee schedule).
A7: Target ROI | B7: 0.3 | C7: Your minimum ROI to buy. Change to suit your strategy.
A10: Product | B10: Supplier | C10: ASIN | D10: Unit cost (supplier ccy, ex VAT) | E10: Currency | F10: FX to GBP | G10: Unit cost £ | H10: Freight / unit £ | I10: Import duty % | J10: Duty £ | K10: Prep / other £ | L10: Landed cost £ | M10: Sell price inc VAT £ | N10: VAT rate | O10: Sell price ex VAT £ | P10: Referral % | Q10: Referral fee £ | R10: FBA fee £ | S10: Storage / other fees £ | T10: Net profit £ | U10: ROI | V10: Margin | W10: Break-even price inc VAT £ | X10: Verdict
A11: Example: Arabian EDP 100ml | B11: BJUTIP a.s. | C11: B0EXAMPLE1 | D11: 12.5 | E11: EUR | F11: =IF(D11="","",IF(E11="EUR",$B$4,1)) -> 0.85 | G11: =IF(D11="","",D11*F11) -> 10.625 | H11: 0.6 | I11: 0 | J11: =IF(D11="","",(G11+H11)*I11) -> 0 | K11: 0.3 | L11: =IF(D11="","",G11+H11+J11+K11) -> 11.525 | M11: 32.99 | N11: =IF(M11="","",$B$5) -> 0.2 | O11: =IF(M11="","",M11/(1+N11)) -> 27.491667 | P11: =IF(M11="","",$B$6) -> 0.15 | Q11: =IF(M11="","",M11*P11) -> 4.9485 | R11: 3.4 | S11: 0.15 | T11: =IF(OR(D11="",M11=""),"",O11-L11-Q11-R11-S11) -> 7.4681667 | U11: =IF(T11="","",IF(L11=0,"",T11/L11)) -> 0.64799711 | V11: =IF(T11="","",T11/O11) -> 0.27165202 | W11: =IF(OR(D11="",M11=""),"",IF((1/(1+N11)-P11)<=0,"",(L11+R11+S11)/(1/(1+N11)-P11))) -> 22.060976 | X11: =IF(U11="","",IF(U11>=$B$7,"BUY","SKIP")) -> BUY
A12: Example: Pet toy (UK supplier) | B12: Pedigree Wholesale | C12: B0EXAMPLE2 | D12: 4.2 | E12: GBP | F12: =IF(D12="","",IF(E12="EUR",$B$4,1)) -> 1 | G12: =IF(D12="","",D12*F12) -> 4.2 | H12: 0.25 | I12: 0 | J12: =IF(D12="","",(G12+H12)*I12) -> 0 | K12: 0.1 | L12: =IF(D12="","",G12+H12+J12+K12) -> 4.55 | M12: 12.99 | N12: =IF(M12="","",$B$5) -> 0.2 | O12: =IF(M12="","",M12/(1+N12)) -> 10.825 | P12: =IF(M12="","",$B$6) -> 0.15 | Q12: =IF(M12="","",M12*P12) -> 1.9485 | R12: 2.9 | S12: 0.05 | T12: =IF(OR(D12="",M12=""),"",O12-L12-Q12-R12-S12) -> 1.3765 | U12: =IF(T12="","",IF(L12=0,"",T12/L12)) -> 0.30252747 | V12: =IF(T12="","",T12/O12) -> 0.12715935 | W12: =IF(OR(D12="",M12=""),"",IF((1/(1+N12)-P12)<=0,"",(L12+R12+S12)/(1/(1+N12)-P12))) -> 10.97561 | X12: =IF(U12="","",IF(U12>=$B$7,"BUY","SKIP")) -> BUY
F13: =IF(D13="","",IF(E13="EUR",$B$4,1)) | G13: =IF(D13="","",D13*F13) | J13: =IF(D13="","",(G13+H13)*I13) | L13: =IF(D13="","",G13+H13+J13+K13) | N13: =IF(M13="","",$B$5) | O13: =IF(M13="","",M13/(1+N13)) | P13: =IF(M13="","",$B$6) | Q13: =IF(M13="","",M13*P13) | T13: =IF(OR(D13="",M13=""),"",O13-L13-Q13-R13-S13) | U13: =IF(T13="","",IF(L13=0,"",T13/L13)) | V13: =IF(T13="","",T13/O13) | W13: =IF(OR(D13="",M13=""),"",IF((1/(1+N13)-P13)<=0,"",(L13+R13+S13)/(1/(1+N13)-P13))) | X13: =IF(U13="","",IF(U13>=$B$7,"BUY","SKIP"))
F14: =IF(D14="","",IF(E14="EUR",$B$4,1)) | G14: =IF(D14="","",D14*F14) | J14: =IF(D14="","",(G14+H14)*I14) | L14: =IF(D14="","",G14+H14+J14+K14) | N14: =IF(M14="","",$B$5) | O14: =IF(M14="","",M14/(1+N14)) | P14: =IF(M14="","",$B$6) | Q14: =IF(M14="","",M14*P14) | T14: =IF(OR(D14="",M14=""),"",O14-L14-Q14-R14-S14) | U14: =IF(T14="","",IF(L14=0,"",T14/L14)) | V14: =IF(T14="","",T14/O14) | W14: =IF(OR(D14="",M14=""),"",IF((1/(1+N14)-P14)<=0,"",(L14+R14+S14)/(1/(1+N14)-P14))) | X14: =IF(U14="","",IF(U14>=$B$7,"BUY","SKIP"))
F15: =IF(D15="","",IF(E15="EUR",$B$4,1)) | G15: =IF(D15="","",D15*F15) | J15: =IF(D15="","",(G15+H15)*I15) | L15: =IF(D15="","",G15+H15+J15+K15) | N15: =IF(M15="","",$B$5) | O15: =IF(M15="","",M15/(1+N15)) | P15: =IF(M15="","",$B$6) | Q15: =IF(M15="","",M15*P15) | T15: =IF(OR(D15="",M15=""),"",O15-L15-Q15-R15-S15) | U15: =IF(T15="","",IF(L15=0,"",T15/L15)) | V15: =IF(T15="","",T15/O15) | W15: =IF(OR(D15="",M15=""),"",IF((1/(1+N15)-P15)<=0,"",(L15+R15+S15)/(1/(1+N15)-P15))) | X15: =IF(U15="","",IF(U15>=$B$7,"BUY","SKIP"))
F16: =IF(D16="","",IF(E16="EUR",$B$4,1)) | G16: =IF(D16="","",D16*F16) | J16: =IF(D16="","",(G16+H16)*I16) | L16: =IF(D16="","",G16+H16+J16+K16) | N16: =IF(M16="","",$B$5) | O16: =IF(M16="","",M16/(1+N16)) | P16: =IF(M16="","",$B$6) | Q16: =IF(M16="","",M16*P16) | T16: =IF(OR(D16="",M16=""),"",O16-L16-Q16-R16-S16) | U16: =IF(T16="","",IF(L16=0,"",T16/L16)) | V16: =IF(T16="","",T16/O16) | W16: =IF(OR(D16="",M16=""),"",IF((1/(1+N16)-P16)<=0,"",(L16+R16+S16)/(1/(1+N16)-P16))) | X16: =IF(U16="","",IF(U16>=$B$7,"BUY","SKIP"))
F17: =IF(D17="","",IF(E17="EUR",$B$4,1)) | G17: =IF(D17="","",D17*F17) | J17: =IF(D17="","",(G17+H17)*I17) | L17: =IF(D17="","",G17+H17+J17+K17) | N17: =IF(M17="","",$B$5) | O17: =IF(M17="","",M17/(1+N17)) | P17: =IF(M17="","",$B$6) | Q17: =IF(M17="","",M17*P17) | T17: =IF(OR(D17="",M17=""),"",O17-L17-Q17-R17-S17) | U17: =IF(T17="","",IF(L17=0,"",T17/L17)) | V17: =IF(T17="","",T17/O17) | W17: =IF(OR(D17="",M17=""),"",IF((1/(1+N17)-P17)<=0,"",(L17+R17+S17)/(1/(1+N17)-P17))) | X17: =IF(U17="","",IF(U17>=$B$7,"BUY","SKIP"))
F18: =IF(D18="","",IF(E18="EUR",$B$4,1)) | G18: =IF(D18="","",D18*F18) | J18: =IF(D18="","",(G18+H18)*I18) | L18: =IF(D18="","",G18+H18+J18+K18) | N18: =IF(M18="","",$B$5) | O18: =IF(M18="","",M18/(1+N18)) | P18: =IF(M18="","",$B$6) | Q18: =IF(M18="","",M18*P18) | T18: =IF(OR(D18="",M18=""),"",O18-L18-Q18-R18-S18) | U18: =IF(T18="","",IF(L18=0,"",T18/L18)) | V18: =IF(T18="","",T18/O18) | W18: =IF(OR(D18="",M18=""),"",IF((1/(1+N18)-P18)<=0,"",(L18+R18+S18)/(1/(1+N18)-P18))) | X18: =IF(U18="","",IF(U18>=$B$7,"BUY","SKIP"))
F19: =IF(D19="","",IF(E19="EUR",$B$4,1)) | G19: =IF(D19="","",D19*F19) | J19: =IF(D19="","",(G19+H19)*I19) | L19: =IF(D19="","",G19+H19+J19+K19) | N19: =IF(M19="","",$B$5) | O19: =IF(M19="","",M19/(1+N19)) | P19: =IF(M19="","",$B$6) | Q19: =IF(M19="","",M19*P19) | T19: =IF(OR(D19="",M19=""),"",O19-L19-Q19-R19-S19) | U19: =IF(T19="","",IF(L19=0,"",T19/L19)) | V19: =IF(T19="","",T19/O19) | W19: =IF(OR(D19="",M19=""),"",IF((1/(1+N19)-P19)<=0,"",(L19+R19+S19)/(1/(1+N19)-P19))) | X19: =IF(U19="","",IF(U19>=$B$7,"BUY","SKIP"))
F20: =IF(D20="","",IF(E20="EUR",$B$4,1)) | G20: =IF(D20="","",D20*F20) | J20: =IF(D20="","",(G20+H20)*I20) | L20: =IF(D20="","",G20+H20+J20+K20) | N20: =IF(M20="","",$B$5) | O20: =IF(M20="","",M20/(1+N20)) | P20: =IF(M20="","",$B$6) | Q20: =IF(M20="","",M20*P20) | T20: =IF(OR(D20="",M20=""),"",O20-L20-Q20-R20-S20) | U20: =IF(T20="","",IF(L20=0,"",T20/L20)) | V20: =IF(T20="","",T20/O20) | W20: =IF(OR(D20="",M20=""),"",IF((1/(1+N20)-P20)<=0,"",(L20+R20+S20)/(1/(1+N20)-P20))) | X20: =IF(U20="","",IF(U20>=$B$7,"BUY","SKIP"))
F21: =IF(D21="","",IF(E21="EUR",$B$4,1)) | G21: =IF(D21="","",D21*F21) | J21: =IF(D21="","",(G21+H21)*I21) | L21: =IF(D21="","",G21+H21+J21+K21) | N21: =IF(M21="","",$B$5) | O21: =IF(M21="","",M21/(1+N21)) | P21: =IF(M21="","",$B$6) | Q21: =IF(M21="","",M21*P21) | T21: =IF(OR(D21="",M21=""),"",O21-L21-Q21-R21-S21) | U21: =IF(T21="","",IF(L21=0,"",T21/L21)) | V21: =IF(T21="","",T21/O21) | W21: =IF(OR(D21="",M21=""),"",IF((1/(1+N21)-P21)<=0,"",(L21+R21+S21)/(1/(1+N21)-P21))) | X21: =IF(U21="","",IF(U21>=$B$7,"BUY","SKIP"))
F22: =IF(D22="","",IF(E22="EUR",$B$4,1)) | G22: =IF(D22="","",D22*F22) | J22: =IF(D22="","",(G22+H22)*I22) | L22: =IF(D22="","",G22+H22+J22+K22) | N22: =IF(M22="","",$B$5) | O22: =IF(M22="","",M22/(1+N22)) | P22: =IF(M22="","",$B$6) | Q22: =IF(M22="","",M22*P22) | T22: =IF(OR(D22="",M22=""),"",O22-L22-Q22-R22-S22) | U22: =IF(T22="","",IF(L22=0,"",T22/L22)) | V22: =IF(T22="","",T22/O22) | W22: =IF(OR(D22="",M22=""),"",IF((1/(1+N22)-P22)<=0,"",(L22+R22+S22)/(1/(1+N22)-P22))) | X22: =IF(U22="","",IF(U22>=$B$7,"BUY","SKIP"))
F23: =IF(D23="","",IF(E23="EUR",$B$4,1)) | G23: =IF(D23="","",D23*F23) | J23: =IF(D23="","",(G23+H23)*I23) | L23: =IF(D23="","",G23+H23+J23+K23) | N23: =IF(M23="","",$B$5) | O23: =IF(M23="","",M23/(1+N23)) | P23: =IF(M23="","",$B$6) | Q23: =IF(M23="","",M23*P23) | T23: =IF(OR(D23="",M23=""),"",O23-L23-Q23-R23-S23) | U23: =IF(T23="","",IF(L23=0,"",T23/L23)) | V23: =IF(T23="","",T23/O23) | W23: =IF(OR(D23="",M23=""),"",IF((1/(1+N23)-P23)<=0,"",(L23+R23+S23)/(1/(1+N23)-P23))) | X23: =IF(U23="","",IF(U23>=$B$7,"BUY","SKIP"))
F24: =IF(D24="","",IF(E24="EUR",$B$4,1)) | G24: =IF(D24="","",D24*F24) | J24: =IF(D24="","",(G24+H24)*I24) | L24: =IF(D24="","",G24+H24+J24+K24) | N24: =IF(M24="","",$B$5) | O24: =IF(M24="","",M24/(1+N24)) | P24: =IF(M24="","",$B$6) | Q24: =IF(M24="","",M24*P24) | T24: =IF(OR(D24="",M24=""),"",O24-L24-Q24-R24-S24) | U24: =IF(T24="","",IF(L24=0,"",T24/L24)) | V24: =IF(T24="","",T24/O24) | W24: =IF(OR(D24="",M24=""),"",IF((1/(1+N24)-P24)<=0,"",(L24+R24+S24)/(1/(1+N24)-P24))) | X24: =IF(U24="","",IF(U24>=$B$7,"BUY","SKIP"))
... F50: =IF(D50="","",IF(E50="EUR",$B$4,1)) | G50: =IF(D50="","",D50*F50) | J50: =IF(D50="","",(G50+H50)*I50) | L50: =IF(D50="","",G50+H50+J50+K50) | N50: =IF(M50="","",$B$5) | O50: =IF(M50="","",M50/(1+N50)) | P50: =IF(M50="","",$B$6) | Q50: =IF(M50="","",M50*P50) | T50: =IF(OR(D50="",M50=""),"",O50-L50-Q50-R50-S50) | U50: =IF(T50="","",IF(L50=0,"",T50/L50)) | V50: =IF(T50="","",T50/O50) | W50: =IF(OR(D50="",M50=""),"",IF((1/(1+N50)-P50)<=0,"",(L50+R50+S50)/(1/(1+N50)-P50))) | X50: =IF(U50="","",IF(U50>=$B$7,"BUY","SKIP"))
A52: Notes: rows 11-12 are examples with made-up prices - overwrite them. FBA fee: use Amazon's Revenue Calculator for the ASIN. Import duty: look up the commodity code on the UK Trade Tariff (gov.uk/trade-tariff); EU-origin goods may qualify for 0% under the UK-EU TCA with proof of origin. VAT & Referral columns default from the settings above - type over them per product if different.

Sheet Templates
B2: Outreach templates - replace [brackets] before sending
B4: Email 1 - First contact | C4: Subject: Trade account enquiry - Crowsons Distribution (UK online retailer)
C5: Hi [Name / Sales Team], I'm [Your Name], founder of Crowsons Distribution, a UK-registered online retailer (Company No. [xxxx], VAT No. [xxxx]). We sell branded [category] to UK customers through our online channels, including Amazon UK. We're looking for reliable, long-term suppliers and would like to open a trade account with [Company]. Could you please let me know: 1. Your trade account application process and requirements 2. Minimum order quantity / minimum order value 3. Current price list or stock list 4. Payment terms and delivery options to the UK 5. Whether you're happy to supply retailers who sell online / on marketplaces We place repeat orders on lines that sell well, and we're happy to start with a test order. Kind regards, [Your Name] Crowsons Distribution [Phone] | [Email] | [Website]
B7: Email 1b - EU supplier version | C7: Subject: Trade account enquiry - UK online retailer (delivery to UK)
C8: Hello [Name / Sales Team], I'm [Your Name] from Crowsons Distribution, a UK-registered online retailer (Company No. [xxxx], UK VAT No. [xxxx], EORI [GBxxxx]). We'd like to open a trade account with [Company] for [category]. Could you please share: 1. Your account requirements and minimum order value 2. Your price list / stock list 3. Whether you deliver to the UK - ideally DDP (delivered duty paid) or with export paperwork (commercial invoice, statement of origin) 4. Whether products are labelled/compliant for the UK market (UK Responsible Person / UKCA where relevant) 5. Whether you supply retailers selling on online marketplaces Happy to start with a trial order. English is easiest for us, but we can work with a translated message if preferred. Best regards, [Your Name] Crowsons Distribution [Phone] | [Email] | [Website]
B10: Email 2 - Follow-up (5 working days) | C10: Subject: Re: Trade account enquiry - Crowsons Distribution
C11: Hi [Name], Just following up on my email from [day] about opening a trade account. We're keen to place an initial order in the next few weeks - is there a price list or application form you could share? If there's a better person to speak to, I'd be grateful if you could point me in the right direction. Thanks, [Your Name]
B13: LinkedIn connection note (max 300 chars) | C13: Hi [First name], I run Crowsons Distribution, a UK online retailer of branded [category]. I'm looking to open trade accounts with established distributors like [Company] and would love to connect.
B15: LinkedIn message (after they accept) | C15: Thanks for connecting, [First name]! We're a UK-registered online retailer (Amazon UK + own channels) growing our range of branded [category]. I'd love to explore opening a trade account with [Company]. Who's the best person to speak to about new accounts, and is there a price list or application form you could share? Happy to jump on a quick call if easier.
B17: Invoice / Amazon ungating request | C17: Subject: Invoice requirements for our order
C18: Hi [Name], Thanks for processing our order. For our records, could you please make sure the invoice shows: - Your company name, full address, phone number and website - Our company name and address: [Crowsons Distribution, address] - Invoice date, product names/descriptions and quantities (in units) - Prices are optional and can be hidden if you prefer If available, could you also send Safety Data Sheets (SDS) / compliance documents for the products? Many thanks, [Your Name]

Sheet Dashboard
B2: Outreach dashboard
B3: All figures are formulas linked to the Suppliers tab.
B5: Niche | C5: Suppliers | D5: UK | E5: EU / Europe | F5: Priority 4-5 | G5: Contacted+ | H5: Approved | I5: Low-cost country
B6: B2B Marketplace | C6: =COUNTIF(Suppliers!$D$2:$D$359,B6) -> 3 | D6: =COUNTIFS(Suppliers!$D$2:$D$359,B6,Suppliers!$J$2:$J$359,"UK") -> 1 | E6: =COUNTIFS(Suppliers!$D$2:$D$359,B6,Suppliers!$J$2:$J$359,"<>UK") -> 2 | F6: =COUNTIFS(Suppliers!$D$2:$D$359,B6,Suppliers!$C$2:$C$359,">=4") -> 1 | G6: =COUNTIFS(Suppliers!$D$2:$D$359,B6,Suppliers!$AF$2:$AF$359,"<>Not contacted") -> 0 | H6: =COUNTIFS(Suppliers!$D$2:$D$359,B6,Suppliers!$AL$2:$AL$359,"Yes") -> 0 | I6: =COUNTIFS(Suppliers!$D$2:$D$359,B6,Suppliers!$K$2:$K$359,"Low-cost") -> 0
B7: Baby Products | C7: =COUNTIF(Suppliers!$D$2:$D$359,B7) -> 30 | D7: =COUNTIFS(Suppliers!$D$2:$D$359,B7,Suppliers!$J$2:$J$359,"UK") -> 3 | E7: =COUNTIFS(Suppliers!$D$2:$D$359,B7,Suppliers!$J$2:$J$359,"<>UK") -> 27 | F7: =COUNTIFS(Suppliers!$D$2:$D$359,B7,Suppliers!$C$2:$C$359,">=4") -> 14 | G7: =COUNTIFS(Suppliers!$D$2:$D$359,B7,Suppliers!$AF$2:$AF$359,"<>Not contacted") -> 0 | H7: =COUNTIFS(Suppliers!$D$2:$D$359,B7,Suppliers!$AL$2:$AL$359,"Yes") -> 0 | I7: =COUNTIFS(Suppliers!$D$2:$D$359,B7,Suppliers!$K$2:$K$359,"Low-cost") -> 7
B8: Beauty | C8: =COUNTIF(Suppliers!$D$2:$D$359,B8) -> 38 | D8: =COUNTIFS(Suppliers!$D$2:$D$359,B8,Suppliers!$J$2:$J$359,"UK") -> 0 | E8: =COUNTIFS(Suppliers!$D$2:$D$359,B8,Suppliers!$J$2:$J$359,"<>UK") -> 38 | F8: =COUNTIFS(Suppliers!$D$2:$D$359,B8,Suppliers!$C$2:$C$359,">=4") -> 16 | G8: =COUNTIFS(Suppliers!$D$2:$D$359,B8,Suppliers!$AF$2:$AF$359,"<>Not contacted") -> 0 | H8: =COUNTIFS(Suppliers!$D$2:$D$359,B8,Suppliers!$AL$2:$AL$359,"Yes") -> 0 | I8: =COUNTIFS(Suppliers!$D$2:$D$359,B8,Suppliers!$K$2:$K$359,"Low-cost") -> 24
B9: DIY & Tools | C9: =COUNTIF(Suppliers!$D$2:$D$359,B9) -> 30 | D9: =COUNTIFS(Suppliers!$D$2:$D$359,B9,Suppliers!$J$2:$J$359,"UK") -> 4 | E9: =COUNTIFS(Suppliers!$D$2:$D$359,B9,Suppliers!$J$2:$J$359,"<>UK") -> 26 | F9: =COUNTIFS(Suppliers!$D$2:$D$359,B9,Suppliers!$C$2:$C$359,">=4") -> 19 | G9: =COUNTIFS(Suppliers!$D$2:$D$359,B9,Suppliers!$AF$2:$AF$359,"<>Not contacted") -> 0 | H9: =COUNTIFS(Suppliers!$D$2:$D$359,B9,Suppliers!$AL$2:$AL$359,"Yes") -> 0 | I9: =COUNTIFS(Suppliers!$D$2:$D$359,B9,Suppliers!$K$2:$K$359,"Low-cost") -> 9
B10: Fragrance | C10: =COUNTIF(Suppliers!$D$2:$D$359,B10) -> 11 | D10: =COUNTIFS(Suppliers!$D$2:$D$359,B10,Suppliers!$J$2:$J$359,"UK") -> 4 | E10: =COUNTIFS(Suppliers!$D$2:$D$359,B10,Suppliers!$J$2:$J$359,"<>UK") -> 7 | F10: =COUNTIFS(Suppliers!$D$2:$D$359,B10,Suppliers!$C$2:$C$359,">=4") -> 4 | G10: =COUNTIFS(Suppliers!$D$2:$D$359,B10,Suppliers!$AF$2:$AF$359,"<>Not contacted") -> 0 | H10: =COUNTIFS(Suppliers!$D$2:$D$359,B10,Suppliers!$AL$2:$AL$359,"Yes") -> 0 | I10: =COUNTIFS(Suppliers!$D$2:$D$359,B10,Suppliers!$K$2:$K$359,"Low-cost") -> 4
B11: General Wholesale / FMCG | C11: =COUNTIF(Suppliers!$D$2:$D$359,B11) -> 8 | D11: =COUNTIFS(Suppliers!$D$2:$D$359,B11,Suppliers!$J$2:$J$359,"UK") -> 7 | E11: =COUNTIFS(Suppliers!$D$2:$D$359,B11,Suppliers!$J$2:$J$359,"<>UK") -> 1 | F11: =COUNTIFS(Suppliers!$D$2:$D$359,B11,Suppliers!$C$2:$C$359,">=4") -> 2 | G11: =COUNTIFS(Suppliers!$D$2:$D$359,B11,Suppliers!$AF$2:$AF$359,"<>Not contacted") -> 0 | H11: =COUNTIFS(Suppliers!$D$2:$D$359,B11,Suppliers!$AL$2:$AL$359,"Yes") -> 0 | I11: =COUNTIFS(Suppliers!$D$2:$D$359,B11,Suppliers!$K$2:$K$359,"Low-cost") -> 0
B12: Health & Personal Care | C12: =COUNTIF(Suppliers!$D$2:$D$359,B12) -> 34 | D12: =COUNTIFS(Suppliers!$D$2:$D$359,B12,Suppliers!$J$2:$J$359,"UK") -> 6 | E12: =COUNTIFS(Suppliers!$D$2:$D$359,B12,Suppliers!$J$2:$J$359,"<>UK") -> 28 | F12: =COUNTIFS(Suppliers!$D$2:$D$359,B12,Suppliers!$C$2:$C$359,">=4") -> 14 | G12: =COUNTIFS(Suppliers!$D$2:$D$359,B12,Suppliers!$AF$2:$AF$359,"<>Not contacted") -> 0 | H12: =COUNTIFS(Suppliers!$D$2:$D$359,B12,Suppliers!$AL$2:$AL$359,"Yes") -> 0 | I12: =COUNTIFS(Suppliers!$D$2:$D$359,B12,Suppliers!$K$2:$K$359,"Low-cost") -> 14
B13: Home & Kitchen | C13: =COUNTIF(Suppliers!$D$2:$D$359,B13) -> 49 | D13: =COUNTIFS(Suppliers!$D$2:$D$359,B13,Suppliers!$J$2:$J$359,"UK") -> 6 | E13: =COUNTIFS(Suppliers!$D$2:$D$359,B13,Suppliers!$J$2:$J$359,"<>UK") -> 43 | F13: =COUNTIFS(Suppliers!$D$2:$D$359,B13,Suppliers!$C$2:$C$359,">=4") -> 21 | G13: =COUNTIFS(Suppliers!$D$2:$D$359,B13,Suppliers!$AF$2:$AF$359,"<>Not contacted") -> 0 | H13: =COUNTIFS(Suppliers!$D$2:$D$359,B13,Suppliers!$AL$2:$AL$359,"Yes") -> 0 | I13: =COUNTIFS(Suppliers!$D$2:$D$359,B13,Suppliers!$K$2:$K$359,"Low-cost") -> 19
B14: Pet Supplies | C14: =COUNTIF(Suppliers!$D$2:$D$359,B14) -> 41 | D14: =COUNTIFS(Suppliers!$D$2:$D$359,B14,Suppliers!$J$2:$J$359,"UK") -> 3 | E14: =COUNTIFS(Suppliers!$D$2:$D$359,B14,Suppliers!$J$2:$J$359,"<>UK") -> 38 | F14: =COUNTIFS(Suppliers!$D$2:$D$359,B14,Suppliers!$C$2:$C$359,">=4") -> 17 | G14: =COUNTIFS(Suppliers!$D$2:$D$359,B14,Suppliers!$AF$2:$AF$359,"<>Not contacted") -> 0 | H14: =COUNTIFS(Suppliers!$D$2:$D$359,B14,Suppliers!$AL$2:$AL$359,"Yes") -> 0 | I14: =COUNTIFS(Suppliers!$D$2:$D$359,B14,Suppliers!$K$2:$K$359,"Low-cost") -> 10
B15: Sports & Outdoors | C15: =COUNTIF(Suppliers!$D$2:$D$359,B15) -> 31 | D15: =COUNTIFS(Suppliers!$D$2:$D$359,B15,Suppliers!$J$2:$J$359,"UK") -> 3 | E15: =COUNTIFS(Suppliers!$D$2:$D$359,B15,Suppliers!$J$2:$J$359,"<>UK") -> 28 | F15: =COUNTIFS(Suppliers!$D$2:$D$359,B15,Suppliers!$C$2:$C$359,">=4") -> 13 | G15: =COUNTIFS(Suppliers!$D$2:$D$359,B15,Suppliers!$AF$2:$AF$359,"<>Not contacted") -> 0 | H15: =COUNTIFS(Suppliers!$D$2:$D$359,B15,Suppliers!$AL$2:$AL$359,"Yes") -> 0 | I15: =COUNTIFS(Suppliers!$D$2:$D$359,B15,Suppliers!$K$2:$K$359,"Low-cost") -> 9
B16: Stationery & Office | C16: =COUNTIF(Suppliers!$D$2:$D$359,B16) -> 29 | D16: =COUNTIFS(Suppliers!$D$2:$D$359,B16,Suppliers!$J$2:$J$359,"UK") -> 4 | E16: =COUNTIFS(Suppliers!$D$2:$D$359,B16,Suppliers!$J$2:$J$359,"<>UK") -> 25 | F16: =COUNTIFS(Suppliers!$D$2:$D$359,B16,Suppliers!$C$2:$C$359,">=4") -> 18 | G16: =COUNTIFS(Suppliers!$D$2:$D$359,B16,Suppliers!$AF$2:$AF$359,"<>Not contacted") -> 0 | H16: =COUNTIFS(Suppliers!$D$2:$D$359,B16,Suppliers!$AL$2:$AL$359,"Yes") -> 0 | I16: =COUNTIFS(Suppliers!$D$2:$D$359,B16,Suppliers!$K$2:$K$359,"Low-cost") -> 6
B17: Toys & Games | C17: =COUNTIF(Suppliers!$D$2:$D$359,B17) -> 54 | D17: =COUNTIFS(Suppliers!$D$2:$D$359,B17,Suppliers!$J$2:$J$359,"UK") -> 9 | E17: =COUNTIFS(Suppliers!$D$2:$D$359,B17,Suppliers!$J$2:$J$359,"<>UK") -> 45 | F17: =COUNTIFS(Suppliers!$D$2:$D$359,B17,Suppliers!$C$2:$C$359,">=4") -> 31 | G17: =COUNTIFS(Suppliers!$D$2:$D$359,B17,Suppliers!$AF$2:$AF$359,"<>Not contacted") -> 0 | H17: =COUNTIFS(Suppliers!$D$2:$D$359,B17,Suppliers!$AL$2:$AL$359,"Yes") -> 0 | I17: =COUNTIFS(Suppliers!$D$2:$D$359,B17,Suppliers!$K$2:$K$359,"Low-cost") -> 13
B18: Total | C18: =SUM(C6:C17) -> 358 | D18: =SUM(D6:D17) -> 50 | E18: =SUM(E6:E17) -> 308 | F18: =SUM(F6:F17) -> 170 | G18: =SUM(G6:G17) -> 0 | H18: =SUM(H6:H17) -> 0 | I18: =SUM(I6:I17) -> 115
B21: Outreach status | C21: Count | D21: % of list
B22: Not contacted | C22: =COUNTIF(Suppliers!$AF$2:$AF$359,B22) -> 358 | D22: =IF(COUNTA(Suppliers!$D$2:$D$359)=0,0,C22/COUNTA(Suppliers!$D$2:$D$359)) -> 1
B23: Contacted | C23: =COUNTIF(Suppliers!$AF$2:$AF$359,B23) -> 0 | D23: =IF(COUNTA(Suppliers!$D$2:$D$359)=0,0,C23/COUNTA(Suppliers!$D$2:$D$359)) -> 0
B24: Follow-up sent | C24: =COUNTIF(Suppliers!$AF$2:$AF$359,B24) -> 0 | D24: =IF(COUNTA(Suppliers!$D$2:$D$359)=0,0,C24/COUNTA(Suppliers!$D$2:$D$359)) -> 0
B25: Replied | C25: =COUNTIF(Suppliers!$AF$2:$AF$359,B25) -> 0 | D25: =IF(COUNTA(Suppliers!$D$2:$D$359)=0,0,C25/COUNTA(Suppliers!$D$2:$D$359)) -> 0
B26: Application submitted | C26: =COUNTIF(Suppliers!$AF$2:$AF$359,B26) -> 0 | D26: =IF(COUNTA(Suppliers!$D$2:$D$359)=0,0,C26/COUNTA(Suppliers!$D$2:$D$359)) -> 0
B27: Account approved | C27: =COUNTIF(Suppliers!$AF$2:$AF$359,B27) -> 0 | D27: =IF(COUNTA(Suppliers!$D$2:$D$359)=0,0,C27/COUNTA(Suppliers!$D$2:$D$359)) -> 0
B28: Price list received | C28: =COUNTIF(Suppliers!$AF$2:$AF$359,B28) -> 0 | D28: =IF(COUNTA(Suppliers!$D$2:$D$359)=0,0,C28/COUNTA(Suppliers!$D$2:$D$359)) -> 0
B29: First order placed | C29: =COUNTIF(Suppliers!$AF$2:$AF$359,B29) -> 0 | D29: =IF(COUNTA(Suppliers!$D$2:$D$359)=0,0,C29/COUNTA(Suppliers!$D$2:$D$359)) -> 0
B30: Rejected | C30: =COUNTIF(Suppliers!$AF$2:$AF$359,B30) -> 0 | D30: =IF(COUNTA(Suppliers!$D$2:$D$359)=0,0,C30/COUNTA(Suppliers!$D$2:$D$359)) -> 0
B31: Not suitable | C31: =COUNTIF(Suppliers!$AF$2:$AF$359,B31) -> 0 | D31: =IF(COUNTA(Suppliers!$D$2:$D$359)=0,0,C31/COUNTA(Suppliers!$D$2:$D$359)) -> 0
B33: Follow-ups overdue | C33: =SUMPRODUCT((Suppliers!$AK$2:$AK$359<>"")*(Suppliers!$AK$2:$AK$359<=TODAY())*((Suppliers!$AF$2:$AF$359="Contacted")+(Suppliers!$AF$2:$AF$359="Follow-up sent"))) -> 0

Sheet Find More Suppliers
A1: Resource | B1: Type | C1: Use it for | D1: Link
A2: Companies House | B2: UK registry | C2: Verify any UK supplier: status, address, directors, SIC 46450 = perfume & cosmetics wholesale | D2: https://find-and-update.company-information.service.gov.uk/
A3: EU VIES VAT checker | B3: EU registry | C3: Confirm an EU supplier's VAT number is real and active | D3: https://ec.europa.eu/taxation_customs/vies/
