Workbook

Sheet Summary
A1: EU Perfume & Aftershave Wholesale Suppliers - Outreach List
A2: Compiled Oct 2026 from public web sources. Websites marked 'From directory - verify' came from business directories; open them to confirm before outreach.
A4: Metric | B4: Count
A5: Total EU suppliers | B5: =COUNT('EU Suppliers'!A2:A79) -> 66
A6: With a website | B6: =COUNTIF('EU Suppliers'!E2:E79,"http*") -> 55
A7: No website found | B7: =COUNTIF('EU Suppliers'!E2:E79,"Not found") -> 11
A8: High priority | B8: =COUNTIF('EU Suppliers'!N2:N79,"High") -> 20
A9: Medium priority | B9: =COUNTIF('EU Suppliers'!N2:N79,"Medium") -> 27
A10: Low priority / caution | B10: =COUNTIF('EU Suppliers'!N2:N79,"Low") -> 19
A11: With a direct email listed | B11: =COUNTIF('EU Suppliers'!H2:H79,"*@*.*") -> 9
A12: Contacted so far | B12: =COUNTA('EU Suppliers'!Q2:Q79)-COUNTIF('EU Suppliers'!Q2:Q79,"Not contacted") -> 0
A13: Accounts opened | B13: =COUNTIF('EU Suppliers'!Q2:Q79,"Account opened") -> 0
A15: Suppliers by country
A16: Country | B16: Suppliers
A17: Austria | B17: =COUNTIF('EU Suppliers'!C2:C79,A17) -> 1
A18: Belgium | B18: =COUNTIF('EU Suppliers'!C2:C79,A18) -> 5
A19: Bulgaria | B19: =COUNTIF('EU Suppliers'!C2:C79,A19) -> 3
A20: Czech Republic | B20: =COUNTIF('EU Suppliers'!C2:C79,A20) -> 3
A21: France | B21: =COUNTIF('EU Suppliers'!C2:C79,A21) -> 7
A22: Germany | B22: =COUNTIF('EU Suppliers'!C2:C79,A22) -> 6
A23: Greece | B23: =COUNTIF('EU Suppliers'!C2:C79,A23) -> 1
A24: Hungary | B24: =COUNTIF('EU Suppliers'!C2:C79,A24) -> 1
A25: Italy | B25: =COUNTIF('EU Suppliers'!C2:C79,A25) -> 7
A26: Lithuania | B26: =COUNTIF('EU Suppliers'!C2:C79,A26) -> 1
A27: Netherlands | B27: =COUNTIF('EU Suppliers'!C2:C79,A27) -> 9
A28: Poland | B28: =COUNTIF('EU Suppliers'!C2:C79,A28) -> 6
A29: Romania | B29: =COUNTIF('EU Suppliers'!C2:C79,A29) -> 3
A30: Spain | B30: =COUNTIF('EU Suppliers'!C2:C79,A30) -> 12
A31: Sweden | B31: =COUNTIF('EU Suppliers'!C2:C79,A31) -> 1
A33: HOW TO USE
A34: - The supplier list is grouped into numbered sections: marketplaces first, then by country, then leads with no website found.
A35: - Website = company homepage. 'Wholesale Sign-up / Contact Page' = the best page to start outreach from.
A36: - Priority: High = designer/branded focus, clear B2B terms or official distributor; Medium = relevant but unverified; Low = directory-only, mainly retail, or a risk flag.
A37: - Yellow columns are yours to fill in. Outreach Status has a drop-down.
A38: AMAZON-SPECIFIC CHECKS BEFORE BUYING
A39: - Ask for a sample invoice: supplier's full name, address and VAT number; your business name/address; product names + quantities.
A40: - Fragrance ungating usually needs distributor/manufacturer invoices (often 10+ units, last 180 days). Ask if their invoices have passed ungating before.
A41: - Ask for a Letter of Authorisation or chain-of-supply proof for restricted / brand-registered lines.
A42: - Avoid 'equivalents', 'dupes', 'testers' and unrealistically cheap designer stock (e.g. under EUR 5 a bottle).
A43: - Check VAT numbers on VIES and the company on its national registry (KvK, Handelsregister, Pappers, KRS, ARES) before paying.

Sheet EU Suppliers
A1: # | B1: Company | C1: Country | D1: City / Region | E1: Website | F1: Website Check | G1: Wholesale Sign-up / Contact Page | H1: Email | I1: Phone | J1: Address | K1: Supplier Type | L1: Brands / Focus | M1: MOQ / Terms | N1: Priority | O1: Notes / Risk Flags | P1: Source (where found) | Q1: Outreach Status | R1: Date Contacted | S1: Follow-up Date | T1: Response / Notes
A2: 1. B2B MARKETPLACES & WHOLESALE PLATFORMS (EU-wide) (3)
A3: 1 | B3: Qogita | C3: Netherlands | D3: Amsterdam | E3: https://www.qogita.com | F3: Confirmed | G3: https://www.qogita.com | H3: Via help centre / chat after sign-up | J3: Amsterdam | K3: B2B wholesale marketplace (500+ vetted distributors) | L3: Health, beauty & fragrance - big designer brands; GTIN-based catalogue | M3: Low MOQ; invoices supplied for 3rd-party resellers | N3: High | O3: Popular with Amazon sellers. Check per-brand ungating acceptance. | P3: https://www.qogita.com/brands/lamour/ | Q3: Not contacted
A4: 2 | B4: Nova Engel | C4: Spain | D4: Palma de Mallorca (logistics Madrid) | E4: https://www.novaengel.com | F4: Confirmed | G4: https://www.novaengel.com/en/company_wholesaler_perfumery | H4: Via website contact form | I4: +34 971 75 67 27 / 902 999 169 | J4: C/ Asipo 4, 07011 Palma de Mallorca | K4: Perfumery wholesaler + dropship/crossdock | L4: Large branded perfume & cosmetics catalogue; API for wholesale & dropship | M4: Professional buyers only | N4: High | O4: 75+ years trading. | P4: https://www.novaengel.com/en/company_wholesaler_perfumery | Q4: Not contacted
A5: 3 | B5: BigBuy | C5: Spain | D5: Aldaia (Valencia) | E5: https://www.bigbuy.eu | F5: Confirmed | G5: https://www.bigbuy.eu | H5: Via website | J5: Aldaia, Valencia | K5: B2B wholesale / dropship platform | L5: Multi-category incl. perfume & cosmetics | M5: Subscription (~EUR 69-99/month + setup) - verify | N5: Medium | O5: Easy start; higher prices than specialists. | P5: https://help.wizishop.com/hc/en-us/articles/360015881879-Presentation-of-BigBuy | Q5: Not contacted
A6: 2. NETHERLANDS (7)
A7: 4 | B7: Beautinow | C7: Netherlands | D7: NL warehouse | E7: https://beautinow.com | F7: Confirmed | G7: https://beautinow.com/wholesale-perfume-supplier-europe/ | H7: Not public - use website contact page | J7: Netherlands | K7: Perfume wholesaler & dropship | L7: 2,000+ fragrances, niche & designer | M7: Enquire by email; account manager replies in 1 working day | N7: High | O7: Claims 100% original stock. | P7: https://beautinow.com/wholesale-perfume-supplier-europe/ | Q7: Not contacted
A8: 5 | B8: AH Beauté BV | C8: Netherlands | D8: Utrecht (warehouses Rotterdam & Antwerp) | E8: https://www.beautetrade.com/suppliers/ah-beauty-bv-107939/ | F8: Beautetrade profile only | G8: https://www.beautetrade.com/suppliers/ah-beauty-bv-107939/ | H8: Via Beautetrade 'contact supplier' | J8: Utrecht | K8: Wholesaler (est. 2014) | L8: Branded perfumes, aftershaves, skincare, make-up | M8: Full or partial orders, break-bulk | N8: High | O8: Exactly matches perfume + aftershave brief. | P8: https://www.beautetrade.com/suppliers/ah-beauty-bv-107939/ | Q8: Not contacted
A9: 6 | B9: EleganceWholesale | C9: Netherlands | E9: https://elegancewholesale.co.nl | F9: Confirmed | G9: https://elegancewholesale.co.nl/partner-with-us | H9: Not public - use website contact page | J9: Netherlands | K9: Wholesaler (B2B only) | L9: Luxury perfumes, cosmetics, designer clothing | M9: Verified businesses only; partner form | N9: Medium | O9: Disclaimer says 'EleganceTrading' - check KvK. | P9: https://elegancewholesale.co.nl/our-services | Q9: Not contacted
A10: 7 | B10: Tradefor7 | C10: Netherlands | D10: Zoetermeer | E10: https://tradefor7.com | F10: From directory - verify | G10: https://tradefor7.com | H10: Not public - use website contact page | J10: Zoetermeer | K10: Wholesaler / distributor | L10: Lattafa, French Avenue, Volare, Swiss Arabian | M10: Min EUR 350 ex VAT; min 6 pcs per fragrance | N10: Medium | O10: Fast-moving Arabian brands. | P10: https://www.marktplaats.nl/v/sieraden-tassen-en-uiterlijk/uiterlijk-parfum/m2420639384-volare-french-avenue-swiss-arabian-lattafa-groothandel | Q10: Not contacted
A11: 8 | B11: Stock Perfume | C11: Netherlands | D11: Utrecht | E11: https://stockperfume.com | F11: Confirmed | G11: https://stockperfume.com | H11: Not public - use website contact page | J11: Utrecht | K11: Perfume wholesaler | L11: Branded perfumes | M11: Min order EUR 500 (page may be dated) | N11: Medium | O11: Confirm still trading. | P11: https://oncosmetics.com/company/stock-perfume/ | Q11: Not contacted
A12: 9 | B12: Join Stadskanaal B.V. | C12: Netherlands | D12: Stadskanaal | E12: https://www.beautetrade.com/products/global-wholesale-distributor-of-cosmetics-skincare-fragrances/75837 | F12: Beautetrade profile only | G12: https://www.beautetrade.com/products/global-wholesale-distributor-of-cosmetics-skincare-fragrances/75837 | H12: Via Beautetrade 'contact supplier' | J12: Stadskanaal | K12: Global wholesale distributor | L12: Cosmetics, skincare, fragrances | N12: Medium | O12: Ask for brand list. | P12: https://www.beautetrade.com/products/global-wholesale-distributor-of-cosmetics-skincare-fragrances/75837 | Q12: Not contacted
A13: 10 | B13: La Parfumista | C13: Netherlands | D13: Utrecht | E13: https://laparfumista.com | F13: From directory - verify | G13: https://laparfumista.com | H13: Not public - use website contact page | J13: Floridadreef 100, Utrecht | K13: Distributor + online retail (est. 2010) | L13: Popular & niche perfumes | N13: Low | O13: Mainly retail - ask about trade. | P13: https://oncosmetics.com/company/la-parfumista/ | Q13: Not contacted
A14: 3. BELGIUM (2)
A15: 11 | B15: Beautylux (Desa Beautylux) | C15: Belgium | D15: Brussels (Schaerbeek) | E15: https://www.beautylux.be | F15: From directory - verify | G15: https://www.beautylux.be | H15: @beautylux.be (see website) | I15: +32 2 7.. (see website) | J15: Rue François Bossaerts 47-51, Brussels | K15: Importer & distributor (since 1980) | L15: Benelux brand distributor e.g. Ariana Grande, Bentley; 450+ doors | N15: High | O15: Official brand distributor. | P15: https://oncosmetics.com/company/beautylux/ | Q15: Not contacted
A16: 12 | B16: Fragrance Privée | C16: Belgium | D16: Brussels | E16: https://www.fragrance-privee.com | F16: From directory - verify | G16: https://www.fragrance-privee.com | H16: contact@fragrance-privee.com | I16: +32 4 88 82 50 07 (Michel Delogne) | J16: Brussels 1000/1030 | K16: Branded perfume wholesaler | L16: Big-brand perfumes, '100% authentic' | M16: Conditions on request | N16: High | O16: Named contact - good first call. | P16: https://www.destockplus.com/acheter/recherche-fournisseur-2-parfumerie.html | Q16: Not contacted
A17: 4. GERMANY (5)
A18: 13 | B18: Alexander Frank - Perfume-Trading.com | C18: Germany | D18: Rangsdorf | E18: https://perfume-trading.com | F18: From directory - verify | G18: https://perfume-trading.com | H18: Not public - use website contact page | J18: Rangsdorf | K18: Wholesale & trading company | L18: Perfumes, fragrances, skin & hair care | N18: Medium | O18: Small (1-10 staff). | P18: https://ensun.io/search/perfume-cologne-fragrance/germany | Q18: Not contacted
A19: 14 | B19: Emporium Handels & Vertriebs GmbH (Parfumtrend) | C19: Germany | D19: Rodenbach | E19: https://parfumtrend.com | F19: From directory - verify | G19: https://parfumtrend.com | H19: Not public - use website contact page | J19: Industriestr. 15, Rodenbach | K19: Perfume wholesaler / e-tailer | L19: 1,800+ luxury perfumes in stock, 48h delivery | N19: Medium | O19: Website linked by shared address - confirm via Impressum. | P19: https://oncosmetics.com/company/parfumtrend/ | Q19: Not contacted
A20: 15 | B20: Aroma Company | C20: Germany | D20: Langen (Hessen) | E20: https://aromacompany.de | F20: From directory - verify | G20: https://aromacompany.de | H20: Not public - use website contact page | J20: August-Bebel-Straße 22, Langen | K20: Distributor / wholesaler / retailer (est. 1998) | L20: Fragrances | N20: Low | P20: https://oncosmetics.com/company/aroma-company | Q20: Not contacted
A21: 16 | B21: Brocard Parfums GmbH | C21: Germany | D21: Berlin | E21: https://brocard.com | F21: From directory - verify | G21: https://brocard.com | H21: Not public - use website contact page | J21: Berlin | K21: Exporter / distributor | L21: Distributes 70+ European manufacturers (CIS focus) | N21: Low | O21: Export focus East. | P21: https://oncosmetics.com/company/brocard/ | Q21: Not contacted
A22: 17 | B22: Parfimo GmbH | C22: Germany | D22: Munich | E22: https://www.parfimo.de | F22: From directory - verify | G22: https://www.parfimo.de | H22: klein@parfimo.de | I22: +49 89 20190347 | J22: Stahlgruberring 36, 81829 München | K22: Perfume trader / online shop | L22: Designer perfumes | N22: Low | O22: Mainly consumer shop (ships DE only) - ask about B2B. | P22: https://implisense.com/de/companies/parfimo-gmbh-muenchen-DE5DGBY5YA30 | Q22: Not contacted
A23: 5. FRANCE (6)
A24: 18 | B24: Perfume Europe | C24: France | D24: Paris (warehouse) | E24: https://perfumeeurope.com | F24: Confirmed | G24: https://perfumeeurope.com/en/ | H24: Not public - use website contact page | J24: Paris | K24: Online B2B perfume wholesaler | L24: 1,500+ references, designer brands | M24: Min EUR 200 ex VAT; free EU delivery over EUR 500 | N24: High | O24: EU VAT auto-checked; ex-VAT invoices. | P24: https://perfumeeurope.com/en/ | Q24: Not contacted
A25: 19 | B25: Parfums en Gros | C25: France | D25: Vénissieux (69) | E25: https://parfums-en-gros.com | F25: From directory - verify | G25: https://parfums-en-gros.com | H25: Not public - use website contact page | I25: +33 6 .. (see website) | J25: 30 Rue Léo Lagrange, Vénissieux | K25: Perfume wholesaler (B2B) | L25: Perfumes & fragrances | N25: Medium | P25: https://oncosmetics.com/company/parfums-en-gros/ | Q25: Not contacted
A26: 20 | B26: Europ Cosmetics (Ed. Pinaud Inovital) | C26: France | D26: Torcy (77) | E26: https://www.beautetrade.com/suppliers/europ-cosmetics-209557 | F26: Beautetrade profile only | G26: https://www.beautetrade.com/suppliers/europ-cosmetics-209557 | H26: Via Beautetrade 'contact supplier' | J26: 3 Rue des Épinettes, 77200 Torcy | K26: Trading / wholesale / export | L26: Skincare, haircare, fragrances | N26: Medium | P26: https://www.beautetrade.com/suppliers/europ-cosmetics-209557 | Q26: Not contacted
A27: 21 | B27: Grossmaillot | C27: France | D27: Montfermeil (93) | E27: https://grossmaillot.com | F27: From directory - verify | G27: https://grossmaillot.com | H27: Not public - use website contact page | J27: Montfermeil 93370 | K27: Wholesaler | L27: Branded, niche & oriental perfumes | M27: Bulk pricing on request | N27: Low | O27: Classified-ad lead - verify authenticity. | P27: https://www.destockplus.com/acheter/recherche-fournisseur-2-parfumerie.html | Q27: Not contacted
A28: 22 | B28: Royaume du Parfum International (RPI) | C28: France | D28: Paris 10e | E28: https://royaumeduparfumparis.com | F28: From directory - verify | G28: https://royaumeduparfumparis.com | H28: Not public - use website contact page | J28: Rue Poissonnière, Paris | K28: Wholesaler & retailer (est. 1996) | L28: French-made perfumes (own label) | N28: Low | O28: Mostly own label. | P28: https://oncosmetics.com/company/royaume-du-parfum-international-rpi/ | Q28: Not contacted
A29: 23 | B29: Firoza Distribution SAS | C29: France | D29: Choisy-le-Roi (94) | E29: https://www.firozadistribution.com | F29: From directory - verify | G29: https://www.firozadistribution.com | H29: firozadistribution@hotmail.fr | I29: +33 6 68 89 19 45 (Nicolas) | J29: 4 avenue Danville, 94600 Choisy-le-Roi | K29: Wholesaler with 400 m² showroom | L29: 500+ 'branded' fragrances | M29: Volume pricing | N29: Low | O29: CAUTION: ~EUR 3.50/unit at 1,000 pcs - too cheap for genuine designer stock. | P29: https://www.destockplus.com/acheter/c-813880-firoza-distribution-destockage.html | Q29: Not contacted
A30: 6. SPAIN (10)
A31: 24 | B31: Ocean Fragrances | C31: Spain | D31: Barcelona | E31: https://oceanfragrances.com | F31: From directory - verify | G31: https://oceanfragrances.com/es/ | H31: Via website | I31: +34 682 62 27 67 | J31: La Rambla, 08005 Barcelona | K31: Wholesaler + dropship/crossdock | L31: 500+ brands, 10,000+ SKUs: Dior, Lancôme, YSL, Guerlain, Paco Rabanne | N31: High | O31: Strong designer coverage. | P31: https://www.proveedores.com/proveedores/ocean-fragrances/ | Q31: Not contacted
A32: 25 | B32: Distribuidor Perfumes | C32: Spain | D32: Barcelona | E32: https://www.distribuidorperfumes.com | F32: From directory - verify | G32: https://www.distribuidorperfumes.com/ | H32: Via website | I32: +34 902 732 332 | J32: Gran Via de les Corts Catalanes 646, 08007 Barcelona | K32: Wholesaler + dropship (24-48h) | L32: Top-brand perfumes | N32: High | P32: https://www.proveedores.com/proveedores/distribuidor-perfumes/ | Q32: Not contacted
A33: 26 | B33: IGMACO Distribución Europa S.L. | C33: Spain | D33: Madrid | E33: https://www.igmaco.com | F33: From directory - verify | G33: https://www.igmaco.com | H33: Not public - use website contact page | I33: +34 915 .. (see website) | J33: Calle Núñez de Balboa 90, Madrid | K33: Wholesaler & distributor (est. 2004) | L33: Selective perfumes, cosmetics, hair care | N33: High | O33: Selective (designer) focus. | P33: https://oncosmetics.com/company/igmaco/ | Q33: Not contacted
A34: 27 | B34: Madallmes | C34: Spain | D34: Meliana (Valencia) | E34: https://madallmes.com | F34: From directory - verify | G34: https://madallmes.com | H34: Not public - use website contact page | I34: +34 963 218 502 | J34: Carrer Llanterners 10, 46133 Meliana | K34: Perfumery wholesaler | L34: 8,000+ original products | N34: Medium | P34: https://proveedores.com/proveedores/madallmes/ | Q34: Not contacted
A35: 28 | B35: Perfumes y Diseño (PYD) | C35: Spain | D35: Madrid | E35: https://www.pyd.es | F35: From directory - verify | G35: https://www.pyd.es | H35: pyd@pyd.es | J35: Calle Isla de Java 33, 28034 Madrid | K35: Licensee & brand distributor | L35: Distributes Cartier, Versace, Moschino; licences Tous, Scalpers | M35: Trade accounts | N35: Medium | O35: Official distributor. | P35: https://empresite.eleconomista.es/PERFUMES-DISENO-ESPANA.html | Q35: Not contacted
A36: 29 | B36: Orient Fragance | C36: Spain | D36: Barcelona | E36: https://www.orientfragance.com | F36: Confirmed | G36: https://www.orientfragance.com/en/pages/contact | H36: orientfragance@gmail.com | I36: +34 623 109 380 | J36: Santa Perpètua de Mogoda (by appointment) | K36: Official distributor Spain & Portugal | L36: Lattafa, Swiss Arabian etc. CPNP registered | M36: Wholesale registration form | N36: Medium | O36: Authorised distributor for Arabian brands. | P36: https://www.orientfragance.com/en/pages/contacto | Q36: Not contacted
A37: 30 | B37: GPD Central de Perfumería y Cosmética | C37: Spain | D37: Madrid | E37: https://gpd.es | F37: From directory - verify | G37: https://gpd.es | H37: Not public - use website contact page | J37: Calle de Orense 68, Madrid | K37: Wholesaler (35+ yrs) | L37: Perfumery, cosmetics, parapharmacy | N37: Medium | P37: https://oncosmetics.com/company/gpd-central-de-perfumeria-y-cosmetica/ | Q37: Not contacted
A38: 31 | B38: Mayorista Perfumería | C38: Spain | D38: Valdemoro (Madrid) | E38: https://mayoristaperfumeria.es | F38: From directory - verify | G38: https://mayoristaperfumeria.es | H38: Not public - use website contact page | J38: Calle Ibiza 8, Valdemoro | K38: Wholesale distributor (est. 1992) | L38: Branded & private-label perfume/cosmetics | N38: Medium | P38: https://oncosmetics.com/company/mayoristaperfumeria/ | Q38: Not contacted
A39: 32 | B39: Quisben Ibérica S.L. | C39: Spain | D39: San Sebastián de los Reyes (Madrid) | E39: https://www.quisben.com | F39: From directory - verify | G39: https://www.quisben.com | H39: Not public - use website contact page | J39: San Sebastián de los Reyes | K39: Importer & wholesaler | L39: Perfumes & deodorants; buys large lots | N39: Medium | O39: Possible job-lot source. | P39: https://oncosmetics.com/company/quisben-iberica-s-l/ | Q39: Not contacted
A40: 33 | B40: Beauty Way SL | C40: Spain | D40: Valencia & Ávila | E40: https://beautyway.es | F40: From directory - verify | G40: https://beautyway.es | H40: Not public - use website contact page | J40: Ávila | K40: Designer perfume distributor (est. 2022) | L40: Designer perfumes & gift sets | M40: No minimum order | N40: Low | O40: Very small (1 employee). | P40: https://oncosmetics.com/company/beauty-way-sl/ | Q40: Not contacted
A41: 7. ITALY (5)
A42: 34 | B42: Parfulandia SRL | C42: Italy | D42: Naples / Vasto | E42: https://www.parfulandiastore.it | F42: From directory - verify | G42: https://www.parfulandiastore.it | H42: Not public - use website contact page | I42: +39 349 515 6250 | J42: Via Vicinale San Donato 16, Napoli | K42: Perfume wholesaler (60+ yrs) | L42: Dior, Lancôme, Chanel, Ferragamo, niche | N42: High | P42: https://oncosmetics.com/company/parfulandia-srl/ | Q42: Not contacted
A43: 35 | B43: Global Perfumes | C43: Italy | D43: Parma | E43: https://globalperfumes.it | F43: From directory - verify | G43: https://globalperfumes.it | H43: Not public - use website contact page | I43: +39 0521 247899 | J43: Piazza B. Lunardi 11A, Parma | K43: Importer / distributor / wholesaler (B2B) | L43: Perfumes for wholesalers & retailers | N43: High | P43: https://oncosmetics.com/company/global-perfumes | Q43: Not contacted
A44: 36 | B44: Amoretti Profumi Srl | C44: Italy | D44: Turin | E44: https://amorettiprofumi.com | F44: From directory - verify | G44: https://amorettiprofumi.com | H44: Not public - use website contact page | J44: Via F.lli De Maistre 27/A, Torino (VAT 04978330019) | K44: Wholesale & retail (since 1986) | L44: Claims official dealer of prestige brands | N44: Medium | P44: https://atoka.io/public/it/azienda/amoretti-profumi-srl/e6a0a9e0c2b7 | Q44: Not contacted
A45: 37 | B45: Profumerie P&P Srl | C45: Italy | D45: Grottaglie (TA) | E45: https://www.profumeriepep.it | F45: From directory - verify | G45: https://www.profumeriepep.it | H45: Not public - use website contact page | I45: +39 099 562 3748 | J45: Via Paganini 73, Grottaglie (VAT 02424900732) | K45: Distributor & wholesaler (~30 yrs) | L45: Perfumes & cosmetics | N45: Medium | P45: https://atoka.io/public/it/azienda/profumerie-p-p-srl/b936935a4339 | Q45: Not contacted
A46: 38 | B46: T.D. Distribuzione SRL | C46: Italy | D46: San Giuseppe Vesuviano (NA) | E46: https://www.tddistribuzione.com | F46: From directory - verify | G46: https://www.tddistribuzione.com | H46: Not public - use website contact page | J46: Via Pianillo 181, San Giuseppe Vesuviano | K46: Producer & distributor | L46: Own lines, Arabian perfumes, 'equivalents' | N46: Low | O46: CAUTION: dupes can't be listed on brand ASINs. | P46: https://oncosmetics.com/company/t-d-distribuzione-srl/ | Q46: Not contacted
A47: 8. POLAND (4)
A48: 39 | B48: Perfume-Supplier.eu (Charms Perfumes & Cosmetics) | C48: Poland | D48: Warsaw | E48: https://perfume-supplier.eu | F48: From directory - verify | G48: https://perfume-supplier.eu | H48: Not public - use website contact page | I48: +48 601 .. (see website) | J48: Zamieniecka 80/158, Warsaw | K48: Branded perfume wholesaler | L48: Branded perfumes for retailers across Europe | N48: High | P48: https://oncosmetics.com/company/charms-perfumes-and-cosmetics/ | Q48: Not contacted
A49: 40 | B49: Avemi Luxury Distribution | C49: Poland | D49: Warsaw | E49: https://avemi.com | F49: From directory - verify | G49: https://avemi.com | H49: Not public - use website contact page | J49: Nowogrodzka 6A/3, Warsaw | K49: Exclusive distributor PL/CZ/SK | L49: Boucheron, Hermès, Serge Lutens, Rochas, Philipp Plein, Juliette Has A Gun | N49: Medium | O49: Official distributor (niche/selective). | P49: https://emis.cn/php/company-profile/PL/Avemi_Sp_z_oo_en_3712319.html | Q49: Not contacted
A50: 41 | B50: Hurtownia Perfum | C50: Poland | D50: Łódź | E50: https://hurtowniaperfum.com.pl | F50: From directory - verify | G50: https://hurtowniaperfum.com.pl | H50: Not public - use website contact page | J50: Krańcowa 53, Łódź | K50: Perfume wholesaler (est. 1997) | L50: Broad range of brands | N50: Medium | P50: https://oncosmetics.com/company/hurtownia-perfum/ | Q50: Not contacted
A51: 42 | B51: Solg (Oskar Szumacher) | C51: Poland | D51: Przechlewo | E51: https://solg.pl | F51: From directory - verify | G51: https://solg.pl | H51: Not public - use website contact page | J51: Przechlewo, Pomorskie | K51: Wholesale supplier | L51: Cosmetics & perfumes; ships 20+ countries | N51: Low | O51: Founding info inconsistent. | P51: https://oncosmetics.com/company/solg-oskar-szumacher/ | Q51: Not contacted
A52: 9. CZECH REPUBLIC (3)
A53: 43 | B53: BJUTIP | C53: Czech Republic | D53: Brno - Modřice | E53: https://www.bjutip.com | F53: Confirmed | G53: https://www.bjutip.com/register | H53: sales@bjutip.com / info@bjutip.com | I53: +420 724 076 367 | J53: Tyršova 1182, 664 42 Modřice | K53: Distributor (e-com, retail, travel retail) | L53: Armaf, Lattafa, Paris Corner, Fragrance World + some designer | M53: Min EUR 1,000; ships 48h | N53: High | O53: Works direct with producers. | P53: https://bjutip.com/contact_us | Q53: Not contacted
A54: 44 | B54: Brasty Wholesale (BRASTY GROUP s.r.o.) | C54: Czech Republic | D54: Prague | E54: https://wholesale.brasty.com | F54: Confirmed | G54: https://wholesale.brasty.com/ | H54: info@brasty.cz | I54: +420 581 580 660 | J54: Lípová 511/15, 120 00 Praha 2 | K54: Wholesale arm of CZ perfume e-tailer | L54: Designer perfumes & cosmetics | M54: Min EUR 200; any EU-VAT business incl. marketplace sellers | N54: High | O54: Explicitly accepts marketplace sellers. | P54: https://wholesale.brasty.com/ | Q54: Not contacted
A55: 45 | B55: PremierParfum (fragrances-wholesale.eu) | C55: Czech Republic | E55: https://www.fragrances-wholesale.eu | F55: Confirmed | G55: https://www.fragrances-wholesale.eu | H55: Not public - use website contact page | K55: B2B perfume wholesaler | L55: Designer fragrances | M55: First order min EUR 500; pallets min EUR 15,000 | N55: High | P55: https://www.fragrances-wholesale.eu/info/terms-and-conditions-nr | Q55: Not contacted
A56: 10. ROMANIA, BULGARIA, GREECE & HUNGARY (8)
A57: 46 | B57: Parfumuri Engros | C57: Romania | D57: Miercurea Ciuc | E57: https://parfumuri-engros.ro | F57: From directory - verify | G57: https://parfumuri-engros.ro | H57: Not public - use website contact page | I57: +40 371 .. (see website) | J57: Str. Kőrösi Csoma Sándor 2, Miercurea Ciuc | K57: Wholesaler (est. 2014) | L57: 8,000+ products, 500+ brands | M57: Sells to SMEs | N57: High | P57: https://oncosmetics.com/company/parfumuri-engros/ | Q57: Not contacted
A58: 47 | B58: Romscent Trading | C58: Romania | D58: Bucharest | E58: https://romscent.com | F58: From directory - verify | G58: https://romscent.com | H58: Not public - use website contact page | J58: Bd. Theodor Pallady, Bucharest | K58: Distributor / wholesaler | L58: 40+ brands from 12 houses incl. Gulf Orchid; ~9,700 SKUs; 2,000+ B2B clients | N58: Medium | O58: Turnover EUR 15m+; new EU logistics centre. | P58: https://www.revistabiz.ro/gulf-orchid-brandul-de-parfumerie-accesibila-unul-dintre-principalele-motoare-de-crestere-din-portofoliul-romscent-trading/ | Q58: Not contacted
A59: 48 | B59: Qudo Beauty | C59: Romania | D59: Piatra Neamț | E59: https://qudobeauty.com | F59: Confirmed | G59: https://qudobeauty.com/perfumes-and-fragrances-wholesale/ | H59: Not public - use website contact page | J59: Romania | K59: EU B2B distributor | L59: Perfumes & fragrances + Korean skincare | M59: Min EUR 300-500 | N59: Medium | P59: https://qudobeauty.com/perfumes-and-fragrances-wholesale/ | Q59: Not contacted
A60: 49 | B60: Ventus S.A. (Perfumes-Supplier.com) | C60: Greece | D60: Gerakas (Athens) | E60: https://www.perfumes-supplier.com | F60: From directory - verify | G60: https://www.perfumes-supplier.com | H60: Not public - use website contact page | I60: +30 21.. (see website) | J60: Gerakas, Anatoliki Attiki | K60: Wholesale fragrance distributor (est. 1995) | L60: Bulk branded fragrances | M60: B2B only | N60: High | P60: https://oncosmetics.com/company/ventus-s-a/ | Q60: Not contacted
A61: 50 | B61: Odora | C61: Bulgaria | D61: Sofia | E61: https://odora.bg | F61: From directory - verify | G61: https://odora.bg | H61: @odora.bg (see website) | I61: +359 87 .. (see website) | J61: Frederik Zholio Kyuri St, Sofia | K61: Distributor (~300 doors) | L61: Armaf, Franck Boclet, Gritti, Masque Milano | N61: Medium | P61: https://oncosmetics.com/company/odora-beauty-corp-ad/ | Q61: Not contacted
A62: 51 | B62: Aromaray Ltd OOD | C62: Bulgaria | D62: Sofia | E62: https://aromaray.bg | F62: From directory - verify | G62: https://aromaray.bg | H62: Not public - use website contact page | J62: Razsadnik-Konyovitsa, Sofia | K62: Exclusive importer BG & EU | L62: Grandeur, Al Wataniah, Al Absar, Riiffs | N62: Medium | P62: https://oncosmetics.com/company/aromaray-ltd-ood/ | Q62: Not contacted
A63: 52 | B63: Venera Cosmetics | C63: Bulgaria | D63: Plovdiv | E63: https://fragrances.bg | F63: Likely - verify | G63: https://fragrances.bg | H63: Not public - use website contact page | J63: Plovdiv | K63: Distributor of branded perfumery (est. 1992) | L63: Branded perfumes & cosmetics | N63: Low | O63: Website inferred from search ranking. | P63: https://en.wikipedia.org/wiki/Venera_Cosmetics | Q63: Not contacted
A64: 53 | B64: Parfen Kft. | C64: Hungary | E64: https://parfen.hu | F64: From directory - verify | G64: https://parfen.hu | H64: Not public - use website contact page | I64: +36 70 .. (see website) | K64: Importer, wholesaler & retailer | L64: Fragrances & cosmetics | N64: Medium | P64: https://oncosmetics.com/company/parfen/ | Q64: Not contacted
A65: 11. OTHER EU (Lithuania, Austria) (2)
A66: 54 | B66: Amco Group UAB (Per-Fumes.com) | C66: Lithuania | D66: Vilnius | E66: https://per-fumes.com | F66: From directory - verify | G66: https://per-fumes.com | H66: Not public - use website contact page | J66: Vilnius | K66: Importer / distributor + online retail | L66: Fragrances | N66: Low | O66: Mainly retail. | P66: https://oncosmetics.com/company/amco-group-uab/ | Q66: Not contacted
A67: 55 | B67: Selective Parfums | C67: Austria | D67: Innsbruck | E67: https://selectiveparfums.at | F67: From directory - verify | G67: https://selectiveparfums.at | H67: Not public - use website contact page | J67: Innsbruck | K67: Distributor / supplier | L67: Niche & high-end | N67: Low | P67: https://oncosmetics.com/company/selective-parfums/ | Q67: Not contacted
A68: 12. LEADS WITH NO WEBSITE FOUND (directory / registry only - find site via company registry) (11)
A69: 56 | B69: Parfum Company Sp. z o.o. S.K.A. | C69: Poland | D69: Zakręt (Warsaw area) | E69: Not found | F69: - | G69: https://www.aplikuj.pl/pracodawca/380091/parfum-company-sp-z-o-o-s-k-a | H69: Not public - use website contact page | J69: Zakręt | K69: Perfume wholesaler with B2B platform | L69: Claims largest perfume wholesaler in PL | M69: 24h delivery | N69: High | O69: Worth tracking down via KRS - high potential. | P69: https://www.aplikuj.pl/pracodawca/380091/parfum-company-sp-z-o-o-s-k-a | Q69: Not contacted
A70: 57 | B70: MisterM Plus Sp. z o.o. Sp.k. | C70: Poland | D70: Kraków | E70: Not found | F70: - | G70: https://www.aplikuj.pl/pracodawca/80046/misterm-plus-sp-z-o-o-spolka-komandytowa | H70: Not public - use website contact page | J70: Trybuny Ludów 15, 30-660 Kraków (KRS 0000567077, NIP 6793113882) | K70: Perfume & cosmetics wholesaler (20+ yrs) | L70: Coty, P&G, Reckitt brands | N70: High | O70: Coty = Hugo Boss, CK, Gucci, Burberry. | P70: https://www.aplikuj.pl/pracodawca/80046/misterm-plus-sp-z-o-o-spolka-komandytowa | Q70: Not contacted
A71: 58 | B71: Prime Stock | C71: Netherlands | D71: Rotterdam | E71: Not found | F71: - | G71: https://ensun.io/search/perfume-cologne | H71: Not public - use website contact page | J71: Rotterdam | K71: Wholesale perfume distributor (est. 2015) | L71: Authentic branded & mass-market fragrances | N71: Medium | P71: https://ensun.io/search/perfume-cologne | Q71: Not contacted
A72: 59 | B72: SAR Beauty AB | C72: Sweden | E72: Not found | F72: - | G72: https://funnelfeedr.com/en/company/se/sar-beauty-ab-5595032482 | H72: Not public - use website contact page | J72: Org. no. 559503-2482 | K72: Distributor | L72: A-brand luxury fragrances across Europe | N72: Medium | O72: Look up on Bolagsverket. | P72: https://funnelfeedr.com/en/company/se/sar-beauty-ab-5595032482 | Q72: Not contacted
A73: 60 | B73: Azurtis SA | C73: Belgium | D73: Uccle (Brussels) | E73: Not found | F73: - | G73: https://us.kompass.com/c/azurtis/be0018421/ | H73: Not public - use website contact page | J73: Hamoirlaan 39, 1180 Ukkel | K73: Wholesale perfume & cosmetics (est. 2005) | N73: Low | P73: https://us.kompass.com/c/azurtis/be0018421/ | Q73: Not contacted
A74: 61 | B74: Diotima | C74: Belgium | D74: Braine-le-Château | E74: Not found | F74: - | G74: https://es.kompass.com/c/diotima/be0038464/ | H74: Not public - use website contact page | J74: Parc Industriel 20, 1440 Braine-le-Château | K74: Wholesaler (est. 1978) | N74: Low | P74: https://es.kompass.com/c/diotima/be0038464/ | Q74: Not contacted
A75: 62 | B75: Intercosmo | C75: Belgium | D75: Mechelen | E75: Not found | F75: - | G75: https://fr.kompass.com/en/c/intercosmo/be0180009/ | H75: Not public - use website contact page | J75: Eikestraat 86, 2800 Mechelen | K75: Perfume distributor (est. 1988) | N75: Low | P75: https://fr.kompass.com/en/c/intercosmo/be0180009/ | Q75: Not contacted
A76: 63 | B76: Sofrapar SARL | C76: France | D76: Paris 15e | E76: Not found | F76: - | G76: https://fr.kompass.com/c/sofrapar/fr0078081/ | H76: Not public - use website contact page | J76: Paris 15e (SIREN 632 014 080) | K76: Perfume & beauty wholesaler (est. 1963) | N76: Low | P76: https://fr.kompass.com/c/sofrapar/fr0078081/ | Q76: Not contacted
A77: 64 | B77: Mr Parfums Srl | C77: Italy | D77: Milan | E77: Not found | F77: - | G77: https://atoka.io/public/it/azienda/mr-parfums-srl-a-socio-unico/f8ca86bdc544 | H77: Not public - use website contact page | J77: Via Bergognone 27, 20144 Milano (VAT 07330390969) | K77: Perfume wholesale agent | N77: Low | O77: 1 employee - broker. | P77: https://atoka.io/public/it/azienda/mr-parfums-srl-a-socio-unico/f8ca86bdc544 | Q77: Not contacted
A78: 65 | B78: Consorzio Profumerie Estasi | C78: Italy | D78: Mignano Monte Lungo (CE) | E78: Not found | F78: - | G78: https://atoka.io/public/it/azienda/consorzio-profumerie-estasi/3cca13127885 | H78: Not public - use website contact page | I78: +39 0771 278084 (store - ask for wholesale) | J78: Via Casilina 63, 81049 Mignano Monte Lungo | K78: Wholesale perfume & cosmetics | L78: ~55,000 products, 1,150+ brands | N78: Medium | P78: https://atoka.io/public/it/azienda/consorzio-profumerie-estasi/3cca13127885 | Q78: Not contacted
A79: 66 | B79: ICOS International Cosmetics GmbH | C79: Germany | D79: Gaimersheim | E79: Not found | F79: - | G79: https://oncosmetics.com/company/icos-international-cosmetics-gmbh/ | H79: Not public - use website contact page | J79: Gaimersheim | K79: Perfume distributor | L79: Mainly German market | N79: Low | P79: https://oncosmetics.com/company/icos-international-cosmetics-gmbh/ | Q79: Not contacted

Sheet UK Suppliers (non-EU)
A1: # | B1: Company | C1: Country | D1: City / Region | E1: Website | F1: Website Check | G1: Wholesale Sign-up / Contact Page | H1: Email | I1: Phone | J1: Address | K1: Supplier Type | L1: Brands / Focus | M1: MOQ / Terms | N1: Priority | O1: Notes / Risk Flags | P1: Source (where found) | Q1: Outreach Status | R1: Date Contacted | S1: Follow-up Date | T1: Response / Notes
A2: UK SUPPLIERS (non-EU - customs apply for EU stock) (3)
A3: 1 | B3: Shaneel Group | C3: United Kingdom | D3: Wembley, London | E3: https://www.shaneel.com | F3: From directory - verify | G3: https://www.shaneel.com | H3: Not public - use website contact page | J3: 78 Wembley Park Drive, Wembley | K3: Branded fine fragrance distributor (since 1986) | L3: Branded fine fragrance for independents; owns Designer Parfums, Mayfair | N3: High | P3: https://jobs.workable.com/companies/iKxrmDgx2D2P41Cmp6pAvV.md | Q3: Not contacted
A4: 2 | B4: Affinity Fragrances | C4: United Kingdom | E4: https://affinityfragrances.com | F4: From directory - verify | G4: https://affinityfragrances.com | H4: Not public - use website contact page | K4: Fragrance wholesaler | L4: Branded perfumes; UK distributor for Lionel Messi fragrances | N4: Medium | P4: https://retail-merchandiser.com/news/affinity-fragrances-focus-on-trust-agility-and-long-term-partnerships-is-driving-its-international-expansion/ | Q4: Not contacted
A5: 3 | B5: Fragrance Wholesale International Ltd | C5: United Kingdom | E5: Not found | F5: - | G5: https://find-and-update.company-information.service.gov.uk/company/14662527 | H5: Not public - use website contact page | J5: See Companies House | K5: SIC 46450 perfume wholesale | N5: Low | P5: https://find-and-update.company-information.service.gov.uk/company/14662527 | Q5: Not contacted

Sheet Outreach Email Template
A1: Subject: | B1: Wholesale account enquiry - Crowsons Global (branded fragrances)
A3: Body: | B3: Hello [Name / Team],
B4: I'm [Your Name] from Crowsons Global, a UK/EU distribution business. We're looking for a reliable wholesale partner for branded perfumes and aftershaves, which we resell through online marketplaces including Amazon.
B5: Could you please send:
B6: 1. Your current wholesale price list / stock list (in Excel if possible)
B7: 2. Your minimum order value and payment terms
B8: 3. Delivery times and costs to [UK / your EU warehouse country]
B9: 4. Confirmation that invoices show your full company details and VAT number, and whether they've been accepted for Amazon brand approvals before
B10: 5. Which brands you're an authorised distributor for, if any
B11: Our company details: [Company name, registration number, VAT/EORI number, address, website].
B12: I'm happy to start with a trial order and grow volume from there.
B13: Kind regards,
B14: [Name] | Crowsons Global | [Phone] | [Email]
